Workbook
Name UPDATE: '[1]Data Sheet'!$E$1

Sheet Historical Financials
A13: Historical Financials -->>

Sheet Consol. Historical FS
B2: CONSOLIDATED HISTORICAL FINANCIAL STATEMENTS
B3: ₹'cr, unless otherwise stated | C3: FY21A | D3: FY22A | E3: FY23A | F3: FY24A | G3: FY25A
A5: # | B5: Profit & Loss Statement
B7: Revenue from Operations | C7: 12549.6 | D7: 17118.79 | E7: 20851.91 | F7: 26710.56 | G7: 30475.33
B8: Other Operating Revenues | C8: 0 | D8: 0 | E8: 0 | F8: 0 | G8: 0
B9: Total Revenue | C9: =ROUND(SUM(C7:C8),2) -> 12549.6 | D9: =ROUND(SUM(D7:D8),2) -> 17118.79 | E9: =ROUND(SUM(E7:E8),2) -> 20851.91 | F9: =ROUND(SUM(F7:F8),2) -> 26710.56 | G9: =ROUND(SUM(G7:G8),2) -> 30475.33
B10: Operating Expenses | C10: 3259.49 | D10: 4865.11 | E10: 5654.56 | F10: 7116.34 | G10: 8069.75
B13: Gross Profit | C13: =ROUND(C9-SUM(C10:C10),2) -> 9290.11 | D13: =ROUND(D9-SUM(D10:D10),2) -> 12253.68 | E13: =ROUND(E9-SUM(E10:E10),2) -> 15197.35 | F13: =ROUND(F9-SUM(F10:F10),2) -> 19594.22 | G13: =ROUND(G9-SUM(G10:G10),2) -> 22405.58
B14: Employee Benefits Expense | C14: 615.05 | D14: 779.43 | E14: 1178.17 | F14: 1896.4 | G14: 2008.66
B15: Loss on fair valuation of Compulsorily Convertible Preference Shares | C15: 0 | D15: 0 | E15: 0 | F15: 0 | G15: 0
B16: Other Expenses | C16: =691.62-715.24 -> -23.62 | D16: =1077.74+872.07 -> 1949.81 | E16: =1185.73+1886.32 -> 3072.05 | F16: =1833.9+112.82 -> 1946.72 | G16: =1975.55+280.85 -> 2256.4
B17: EBITDA | C17: =ROUND(C13-SUM(C14:C16),2) -> 8698.68 | D17: =ROUND(D13-SUM(D14:D16),2) -> 9524.44 | E17: =ROUND(E13-SUM(E14:E16),2) -> 10947.13 | F17: =ROUND(F13-SUM(F14:F16),2) -> 15751.1 | G17: =ROUND(G13-SUM(G14:G16),2) -> 18140.52
B18: Depreciation and Amortisation Expense | C18: 2107.34 | D18: 3099.3 | E18: 3423.24 | F18: 3888.46 | G18: 4378.93
B19: EBIT | C19: =ROUND(C17-C18,2) -> 6591.34 | D19: =ROUND(D17-D18,2) -> 6425.14 | E19: =ROUND(E17-E18,2) -> 7523.89 | F19: =ROUND(F17-F18,2) -> 11862.64 | G19: =ROUND(G17-G18,2) -> 13761.59
B20: Finance Costs | C20: =2129.16+126.13 -> 2255.29 | D20: =2559.61-15.69 -> 2543.92 | E20: =2593.62-230.98 -> 2362.64 | F20: =2784.41-51.47 -> 2732.94 | G20: =2778-246.18 -> 2531.82
B21: Other Income | C21: 1970.23 | D21: 2223.72 | E21: 1553.48 | F21: 1499.42 | G21: =1304.48+603.27 -> 1907.75
B22: Profit before share of Profit / (Loss) of Associate / Joint Ventures | C22: =ROUND(C19-C20+C21,2) -> 6306.28 | D22: =ROUND(D19-D20+D21,2) -> 6104.94 | E22: =ROUND(E19-E20+E21,2) -> 6714.73 | F22: =ROUND(F19-F20+F21,2) -> 10629.12 | G22: =ROUND(G19-G20+G21,2) -> 13137.52
B23: Share of Profit / (Loss) from Associate /Joint Ventures (net of tax) | C23: -14.27 | D23: 17.39 | E23: 47.78 | F23: -161.69 | G23: 141.56
B24: Profit before Exceptional Items and Tax | C24: =ROUND(SUM(C22:C23),2) -> 6292.01 | D24: =ROUND(SUM(D22:D23),2) -> 6122.33 | E24: =ROUND(SUM(E22:E23),2) -> 6762.51 | F24: =ROUND(SUM(F22:F23),2) -> 10467.43 | G24: =ROUND(SUM(G22:G23),2) -> 13279.08
B25: Exceptional Items | C25: 0 | D25: -405.19 | E25: -1273.38 | F25: -373.7 | G25: -249.46
B26: Profit before Tax | C26: =ROUND(SUM(C24:C25),2) -> 6292.01 | D26: =ROUND(SUM(D24:D25),2) -> 5717.14 | E26: =ROUND(SUM(E24:E25),2) -> 5489.13 | F26: =ROUND(SUM(F24:F25),2) -> 10093.73 | G26: =ROUND(SUM(G24:G25),2) -> 13029.62
B27: Current Tax | C27: 1271.51 | D27: 888.2 | E27: 977.9 | F27: 1134.73 | G27: 2221.87
B28: Adjustment of tax relating to earlier years | C28: -130.63 | D28: 0 | E28: 0 | F28: 455.16 | G28: 0
B29: Deferred Tax | C29: 102.39 | D29: -124.24 | E29: -881.52 | F29: 399.85 | G29: -253.51
B30: Net profit from continuing operations | C30: =ROUND(C26-SUM(C27:C29),2) -> 5048.74 | D30: =ROUND(D26-SUM(D27:D29),2) -> 4953.18 | E30: =ROUND(E26-SUM(E27:E29),2) -> 5392.75 | F30: =ROUND(F26-SUM(F27:F29),2) -> 8103.99 | G30: =ROUND(G26-SUM(G27:G29),2) -> 11061.26
B31: Profit before tax from discontinued operations | C31: 0 | D31: 0 | E31: 0 | F31: 0 | G31: 0
B32: Tax income / (expense) of discontinued operations | C32: 0 | D32: 0 | E32: 0 | F32: 0 | G32: 0
B33: Net profit from discontinuing operations | C33: =ROUND(SUM(C31:C32),2) -> 0 | D33: =ROUND(SUM(D31:D32),2) -> 0 | E33: =ROUND(SUM(E31:E32),2) -> 0 | F33: =ROUND(SUM(F31:F32),2) -> 0 | G33: =ROUND(SUM(G31:G32),2) -> 0
B34: Net Profit | C34: =ROUND(SUM(C30,C33),2) -> 5048.74 | D34: =ROUND(SUM(D30,D33),2) -> 4953.18 | E34: =ROUND(SUM(E30,E33),2) -> 5392.75 | F34: =ROUND(SUM(F30,F33),2) -> 8103.99 | G34: =ROUND(SUM(G30,G33),2) -> 11061.26
B35: Net Profit attributable to:
B36: Owners of the company | C36: 4994.3 | D36: 4886.03 | E36: 5310.18 | F36: 8110.64 | G36: 11092.31
B37: Non-Controlling Interest | C37: 54.44 | D37: 67.15 | E37: 82.57 | F37: -6.65 | G37: -31.05
A39: # | B39: Balance Sheet
B41: ASSETS
B42: Non-current Assets
B43: Property, Plant and Equipment | C43: 36791.51 | D43: 41488.7 | E43: 48414 | F43: 51803.83 | G43: 62394.43
B44: Right of Use Assets | C44: 1775.95 | D44: 2772.25 | E44: 3541.9 | F44: 3809.11 | G44: 6177.54
B45: Capital work-in-progress | C45: 3697.13 | D45: 4022.9 | E45: 6814.03 | F45: 10936.09 | G45: 11592.19
B46: Investment Property | C46: 0 | D46: 0 | E46: 2473.38 | F46: 1345.3 | G46: 1459.16
B47: Goodwill | C47: 4036.43 | D47: 6711.43 | E47: 6963.4 | F47: 6906.93 | G47: 7093.59
B48: Other Intangible Assets | C48: 5533.03 | D48: 11580.54 | E48: 11445.51 | F48: 11282.64 | G48: 12491.6
B49: Intangible Assets under Development | C49: 0 | D49: 0 | E49: 0 | F49: 0 | G49: 113.91
B50: Investments accounted for using the equity method | C50: 649.53 | D50: 1189.85 | E50: 2498.38 | F50: 2707.26 | G50: 3082.64
B51: Financial assets
B52: a) Other Investments | C52: 447.86 | D52: 1923.1 | E52: 1059.47 | F52: 919.61 | G52: 824.93
B53: b) Other Financial Assets | C53: =235+751.26+89.42+5010.85 -> 6086.53 | D53: =87+484.41+3072.08+4607.95 -> 8251.44 | E53: =1582.15+6.7+1552.97+4567.78 -> 7709.6 | F53: =55+4.52+1523.53+3167.65 -> 4750.7 | G53: =24+704.15+1633.51+3323.67 -> 5685.33
B54: Deferred Tax Assets (Net) | C54: 881.73 | D54: 1357.83 | E54: 2199.9 | F54: 1918.67 | G54: 1889.58
B55: Income Tax Asset (Net) | C55: 0 | D55: 0 | E55: 0 | F55: 0 | G55: 0
B56: Other Non-Current Assets | C56: 2593.44 | D56: 2299.36 | E56: 4338.04 | F56: 5065.37 | G56: 3583.21
B57: Total Non-current Assets | C57: =ROUND(SUM(C43:C56),2) -> 62493.14 | D57: =ROUND(SUM(D43:D56),2) -> 81597.4 | E57: =ROUND(SUM(E43:E56),2) -> 97457.61 | F57: =ROUND(SUM(F43:F56),2) -> 101445.51 | G57: =ROUND(SUM(G43:G56),2) -> 116388.11
B59: Current assets
B60: Inventories | C60: 991.85 | D60: 395.64 | E60: 451.97 | F60: 437.51 | G60: 521.8
B61: Financial assets
B62: a) Investments | C62: 1138.76 | D62: 47.79 | E62: 4028.69 | F62: 661.79 | G62: 751.88
B63: b) Trade receivables | C63: 2385.9 | D63: 2221.9 | E63: 3241.67 | F63: 3666.94 | G63: 4432.36
B64: c) Cash and Cash Equivalents | C64: 4198.04 | D64: 8653.02 | E64: 931.99 | F64: 1575.73 | G64: 3406.32
B65: d) Bank Balances other than Cash and Cash Equivalents | C65: 502.74 | D65: 2014.39 | E65: 3316.79 | F65: 6056.15 | G65: 3199.65
B66: e) Loans | C66: 1082.81 | D66: 1302.42 | E66: 408.1 | F66: =64+205.01 -> 269.01 | G66: =70.6+102.57 -> 173.17
B67: f) Derivative Instruments | C67: 0 | D67: 0 | E67: 0 | F67: 0 | G67: 0
B68: g) Other Financial Assets | C68: 1162.48 | D68: 824.69 | E68: 1962.97 | F68: 3441.08 | G68: 4471.8
B69: Other Current Assets | C69: 1013.2 | D69: 730.09 | E69: 1164.08 | F69: 1177.4 | G69: 1800.39
B71: Total Current Assets | C71: =ROUND(SUM(C60:C70),2) -> 12475.78 | D71: =ROUND(SUM(D60:D70),2) -> 16189.94 | E71: =ROUND(SUM(E60:E70),2) -> 15506.26 | F71: =ROUND(SUM(F60:F70),2) -> 17285.61 | G71: =ROUND(SUM(G60:G70),2) -> 18757.37
B72: Assets classified as held for sale and discontinued operations | C72: 354.86 | D72: 1898.48 | E72: 1941.26 | F72: 186.75 | G72: 186.75
B73: Total Assets | C73: =ROUND(SUM(C57,C71,C72),2) -> 75323.78 | D73: =ROUND(SUM(D57,D71,D72),2) -> 99685.82 | E73: =ROUND(SUM(E57,E71,E72),2) -> 114905.13 | F73: =ROUND(SUM(F57,F71,F72),2) -> 118917.87 | G73: =ROUND(SUM(G57,G71,G72),2) -> 135332.23
B75: EQUITY AND LIABILITIES
B76: Equity
B77: Equity Share Capital | C77: 406.35 | D77: 422.47 | E77: 432.03 | F77: 432.03 | G77: 432.03
B78: Other Equity | C78: 30221.91 | D78: 41565.75 | E78: 45151.55 | F78: 52512.74 | G78: 62003.36
B79: Equity Attributable to the Owners of the Company | C79: =ROUND(SUM(C77:C78),2) -> 30628.26 | D79: =ROUND(SUM(D77:D78),2) -> 41988.22 | E79: =ROUND(SUM(E77:E78),2) -> 45583.58 | F79: =ROUND(SUM(F77:F78),2) -> 52944.77 | G79: =ROUND(SUM(G77:G78),2) -> 62435.39
B80: Non-Controlling Interests | C80: 1468.47 | D80: 392.77 | E80: 1338.51 | F80: 1598.23 | G80: 2537.95
B81: Total Equity | C81: =ROUND(SUM(C79:C80),2) -> 32096.73 | D81: =ROUND(SUM(D79:D80),2) -> 42380.99 | E81: =ROUND(SUM(E79:E80),2) -> 46922.09 | F81: =ROUND(SUM(F79:F80),2) -> 54543 | G81: =ROUND(SUM(G79:G80),2) -> 64973.34
B83: Non-current Liabilities
B84: Financial Liabilities
B85: a) Borrowings | C85: 32935.53 | D85: 39691.48 | E85: 46516.94 | F85: 37662.93 | G85: 35830.68
B86: b) Lease Liabilities | C86: 572.33 | D86: 1983.78 | E86: 2681.74 | F86: 2953.28 | G86: 5389.61
B87: c) Other Financial Liabilities | C87: =I87-C86 -> 207.61 | D87: 227.56 | E87: 322.84 | F87: 360.11 | G87: 207.45 | I87: 779.94
B88: d) Derivative Instruments | C88: 0 | D88: 0 | E88: 0 | F88: 0 | G88: 0
B89: Other Non-Current Liabilities | C89: 1065.79 | D89: 988.21 | E89: 1148.84 | F89: 1664.99 | G89: 2142.54
B90: Provisions | C90: 26.68 | D90: 34.23 | E90: 1201.75 | F90: 1100.75 | G90: 1149.36
B91: Government Grants | C91: 0 | D91: 0 | E91: 0 | F91: 0 | G91: 0
B92: Deferred Tax Liabilities (Net) | C92: 1203.16 | D92: 3010.86 | E92: 3186.37 | F92: 4169.87 | G92: 4653.26
B93: Total Non-current Liabilities | C93: =ROUND(SUM(C85:C92),2) -> 36011.1 | D93: =ROUND(SUM(D85:D92),2) -> 45936.12 | E93: =ROUND(SUM(E85:E92),2) -> 55058.48 | F93: =ROUND(SUM(F85:F92),2) -> 47911.93 | G93: =ROUND(SUM(G85:G92),2) -> 49372.9
B95: Current Liabilities
B96: Financial liabilities
B97: a) Borrowings | C97: 400 | D97: 5761.56 | E97: 3302.37 | F97: 8616.3 | G97: 9979.35
B98: b) Lease Liabilities | C98: 32.26 | D98: 32.16 | E98: 61.97 | F98: 71.2 | G98: 254.56 | I98: 3292.34
B99: c) Trade payables
B100: Total outstanding dues of Micro Enterprises and Small Enterprises | C100: 11.5 | D100: 41.86 | E100: 98.88 | F100: 152.5 | G100: 166.73
B101: Total outstanding dues of Creditors other than Micro Enterprises and Small Enterprises | C101: 1002.35 | D101: 1117.71 | E101: 1729.35 | F101: 1759.6 | G101: 2553.77
B102: d) Other Financial Liabilities | C102: =I98-C98 -> 3260.08 | D102: =1954.51+299.24 -> 2253.75 | E102: =2620.76+699.12 -> 3319.88 | F102: 3756.8 | G102: 5359.74
B103: e) Derivative Instruments | C103: 0 | D103: 0 | E103: 0 | F103: 0 | G103: 0
B104: Other Current Liabilities | C104: =1721.19+539.81 -> 2261 | D104: 1654.87 | E104: 1814.19 | F104: 1832.45 | G104: 2242.68
B105: Provisions | C105: 95.73 | D105: 107.52 | E105: 548.03 | F105: 193.44 | G105: 236.77
B106: Government Grants | C106: 0 | D106: 0 | E106: 0 | F106: 0 | G106: 0
B107: Current Tax Liabilities (Net) | C107: 38.49 | D107: 93.92 | E107: 528.43 | F107: 33.1 | G107: 144.84
B108: Total Current Liabilities | C108: =ROUND(SUM(C97:C107),2) -> 7101.41 | D108: =ROUND(SUM(D97:D107),2) -> 11063.35 | E108: =ROUND(SUM(E97:E107),2) -> 11403.1 | F108: =ROUND(SUM(F97:F107),2) -> 16415.39 | G108: =ROUND(SUM(G97:G107),2) -> 20938.44
B109: Assets classified as held for sale and discontinued operations | C109: 114.54 | D109: 305.36 | E109: 1521.46 | F109: 47.55 | G109: 47.55
B110: Total Equity and Liabilities | C110: =ROUND(SUM(C81,C93,C108,C109),2) -> 75323.78 | D110: =ROUND(SUM(D81,D93,D108,D109),2) -> 99685.82 | E110: =ROUND(SUM(E81,E93,E108,E109),2) -> 114905.13 | F110: =ROUND(SUM(F81,F93,F108,F109),2) -> 118917.87 | G110: =ROUND(SUM(G81,G93,G108,G109),2) -> 135332.23
B112: Check | C112: =C73-C110 -> 0 | D112: =D73-D110 -> 0 | E112: =E73-E110 -> 0 | F112: =F73-F110 -> 0 | G112: =G73-G110 -> 0
A114: # | B114: Cash Flow Statement
...

Sheet Consol. Common Size FS
B2: COMMON SIZE FINANCIAL STATEMENTS
C3: ='Consol. Historical FS'!C3 -> FY21A | D3: ='Consol. Historical FS'!D3 -> FY22A | E3: ='Consol. Historical FS'!E3 -> FY23A | F3: ='Consol. Historical FS'!F3 -> FY24A | G3: ='Consol. Historical FS'!G3 -> FY25A
A5: # | B5: Profit & Loss Statement - as a % of Total Revenue
B7: Revenue from Operations | C7: =ROUND('Consol. Historical FS'!C7/'Consol. Historical FS'!C$9,3) -> 1 | D7: =ROUND('Consol. Historical FS'!D7/'Consol. Historical FS'!D$9,3) -> 1 | E7: =ROUND('Consol. Historical FS'!E7/'Consol. Historical FS'!E$9,3) -> 1 | F7: =ROUND('Consol. Historical FS'!F7/'Consol. Historical FS'!F$9,3) -> 1 | G7: =ROUND('Consol. Historical FS'!G7/'Consol. Historical FS'!G$9,3) -> 1
B8: Other Operating Revenues | C8: =ROUND('Consol. Historical FS'!C8/'Consol. Historical FS'!C$9,3) -> 0 | D8: =ROUND('Consol. Historical FS'!D8/'Consol. Historical FS'!D$9,3) -> 0 | E8: =ROUND('Consol. Historical FS'!E8/'Consol. Historical FS'!E$9,3) -> 0 | F8: =ROUND('Consol. Historical FS'!F8/'Consol. Historical FS'!F$9,3) -> 0 | G8: =ROUND('Consol. Historical FS'!G8/'Consol. Historical FS'!G$9,3) -> 0
B9: Total Revenue | C9: =ROUND('Consol. Historical FS'!C9/'Consol. Historical FS'!C$9,3) -> 1 | D9: =ROUND('Consol. Historical FS'!D9/'Consol. Historical FS'!D$9,3) -> 1 | E9: =ROUND('Consol. Historical FS'!E9/'Consol. Historical FS'!E$9,3) -> 1 | F9: =ROUND('Consol. Historical FS'!F9/'Consol. Historical FS'!F$9,3) -> 1 | G9: =ROUND('Consol. Historical FS'!G9/'Consol. Historical FS'!G$9,3) -> 1
B10: Operating Expenses | C10: ='Consol. Historical FS'!C10/'Consol. Historical FS'!C$7 -> 0.2597286 | D10: =ROUND('Consol. Historical FS'!D10/'Consol. Historical FS'!D$9,3) -> 0.284 | E10: =ROUND('Consol. Historical FS'!E10/'Consol. Historical FS'!E$9,3) -> 0.271 | F10: =ROUND('Consol. Historical FS'!F10/'Consol. Historical FS'!F$9,3) -> 0.266 | G10: =ROUND('Consol. Historical FS'!G10/'Consol. Historical FS'!G$9,3) -> 0.265
B11: Gross Profit | C11: =ROUND('Consol. Historical FS'!C13/'Consol. Historical FS'!C$9,3) -> 0.74 | D11: =ROUND('Consol. Historical FS'!D13/'Consol. Historical FS'!D$9,3) -> 0.716 | E11: =ROUND('Consol. Historical FS'!E13/'Consol. Historical FS'!E$9,3) -> 0.729 | F11: =ROUND('Consol. Historical FS'!F13/'Consol. Historical FS'!F$9,3) -> 0.734 | G11: =ROUND('Consol. Historical FS'!G13/'Consol. Historical FS'!G$9,3) -> 0.735
B12: Employee Benefits Expense | C12: =ROUND('Consol. Historical FS'!C14/'Consol. Historical FS'!C$9,3) -> 0.049 | D12: =ROUND('Consol. Historical FS'!D14/'Consol. Historical FS'!D$9,3) -> 0.046 | E12: =ROUND('Consol. Historical FS'!E14/'Consol. Historical FS'!E$9,3) -> 0.057 | F12: =ROUND('Consol. Historical FS'!F14/'Consol. Historical FS'!F$9,3) -> 0.071 | G12: =ROUND('Consol. Historical FS'!G14/'Consol. Historical FS'!G$9,3) -> 0.066
B13: Loss on fair valuation of Compulsorily Convertible Preference Shares | C13: =ROUND('Consol. Historical FS'!C15/'Consol. Historical FS'!C$9,3) -> 0 | D13: =ROUND('Consol. Historical FS'!D15/'Consol. Historical FS'!D$9,3) -> 0 | E13: =ROUND('Consol. Historical FS'!E15/'Consol. Historical FS'!E$9,3) -> 0 | F13: =ROUND('Consol. Historical FS'!F15/'Consol. Historical FS'!F$9,3) -> 0 | G13: =ROUND('Consol. Historical FS'!G15/'Consol. Historical FS'!G$9,3) -> 0
B14: Other Expenses | C14: =ROUND('Consol. Historical FS'!C16/'Consol. Historical FS'!C$9,3) -> -0.002 | D14: =ROUND('Consol. Historical FS'!D16/'Consol. Historical FS'!D$9,3) -> 0.114 | E14: =ROUND('Consol. Historical FS'!E16/'Consol. Historical FS'!E$9,3) -> 0.147 | F14: =ROUND('Consol. Historical FS'!F16/'Consol. Historical FS'!F$9,3) -> 0.073 | G14: =ROUND('Consol. Historical FS'!G16/'Consol. Historical FS'!G$9,3) -> 0.074
B15: EBITDA | C15: =ROUND('Consol. Historical FS'!C17/'Consol. Historical FS'!C$9,3) -> 0.693 | D15: =ROUND('Consol. Historical FS'!D17/'Consol. Historical FS'!D$9,3) -> 0.556 | E15: =ROUND('Consol. Historical FS'!E17/'Consol. Historical FS'!E$9,3) -> 0.525 | F15: =ROUND('Consol. Historical FS'!F17/'Consol. Historical FS'!F$9,3) -> 0.59 | G15: =ROUND('Consol. Historical FS'!G17/'Consol. Historical FS'!G$9,3) -> 0.595
B16: Depreciation and Amortisation Expense | C16: =ROUND('Consol. Historical FS'!C18/'Consol. Historical FS'!C$9,3) -> 0.168 | D16: =ROUND('Consol. Historical FS'!D18/'Consol. Historical FS'!D$9,3) -> 0.181 | E16: =ROUND('Consol. Historical FS'!E18/'Consol. Historical FS'!E$9,3) -> 0.164 | F16: =ROUND('Consol. Historical FS'!F18/'Consol. Historical FS'!F$9,3) -> 0.146 | G16: =ROUND('Consol. Historical FS'!G18/'Consol. Historical FS'!G$9,3) -> 0.144
B17: EBIT | C17: =ROUND('Consol. Historical FS'!C19/'Consol. Historical FS'!C$9,3) -> 0.525 | D17: =ROUND('Consol. Historical FS'!D19/'Consol. Historical FS'!D$9,3) -> 0.375 | E17: =ROUND('Consol. Historical FS'!E19/'Consol. Historical FS'!E$9,3) -> 0.361 | F17: =ROUND('Consol. Historical FS'!F19/'Consol. Historical FS'!F$9,3) -> 0.444 | G17: =ROUND('Consol. Historical FS'!G19/'Consol. Historical FS'!G$9,3) -> 0.452
B18: Finance Costs | C18: =ROUND('Consol. Historical FS'!C20/'Consol. Historical FS'!C$9,3) -> 0.18 | D18: =ROUND('Consol. Historical FS'!D20/'Consol. Historical FS'!D$9,3) -> 0.149 | E18: =ROUND('Consol. Historical FS'!E20/'Consol. Historical FS'!E$9,3) -> 0.113 | F18: =ROUND('Consol. Historical FS'!F20/'Consol. Historical FS'!F$9,3) -> 0.102 | G18: =ROUND('Consol. Historical FS'!G20/'Consol. Historical FS'!G$9,3) -> 0.083
B19: Other Income | C19: =ROUND('Consol. Historical FS'!C21/'Consol. Historical FS'!C$9,3) -> 0.157 | D19: =ROUND('Consol. Historical FS'!D21/'Consol. Historical FS'!D$9,3) -> 0.13 | E19: =ROUND('Consol. Historical FS'!E21/'Consol. Historical FS'!E$9,3) -> 0.075 | F19: =ROUND('Consol. Historical FS'!F21/'Consol. Historical FS'!F$9,3) -> 0.056 | G19: =ROUND('Consol. Historical FS'!G21/'Consol. Historical FS'!G$9,3) -> 0.063
B20: Profit before share of Profit / (Loss) of Associate / Joint Ventures | C20: =ROUND('Consol. Historical FS'!C22/'Consol. Historical FS'!C$9,3) -> 0.503 | D20: =ROUND('Consol. Historical FS'!D22/'Consol. Historical FS'!D$9,3) -> 0.357 | E20: =ROUND('Consol. Historical FS'!E22/'Consol. Historical FS'!E$9,3) -> 0.322 | F20: =ROUND('Consol. Historical FS'!F22/'Consol. Historical FS'!F$9,3) -> 0.398 | G20: =ROUND('Consol. Historical FS'!G22/'Consol. Historical FS'!G$9,3) -> 0.431
B21: Share of Profit / (Loss) from Associate /Joint Ventures (net of tax) | C21: =ROUND('Consol. Historical FS'!C23/'Consol. Historical FS'!C$9,3) -> -0.001 | D21: =ROUND('Consol. Historical FS'!D23/'Consol. Historical FS'!D$9,3) -> 0.001 | E21: =ROUND('Consol. Historical FS'!E23/'Consol. Historical FS'!E$9,3) -> 0.002 | F21: =ROUND('Consol. Historical FS'!F23/'Consol. Historical FS'!F$9,3) -> -0.006 | G21: =ROUND('Consol. Historical FS'!G23/'Consol. Historical FS'!G$9,3) -> 0.005
B22: Profit before Exceptional Items and Tax | C22: =ROUND('Consol. Historical FS'!C24/'Consol. Historical FS'!C$9,3) -> 0.501 | D22: =ROUND('Consol. Historical FS'!D24/'Consol. Historical FS'!D$9,3) -> 0.358 | E22: =ROUND('Consol. Historical FS'!E24/'Consol. Historical FS'!E$9,3) -> 0.324 | F22: =ROUND('Consol. Historical FS'!F24/'Consol. Historical FS'!F$9,3) -> 0.392 | G22: =ROUND('Consol. Historical FS'!G24/'Consol. Historical FS'!G$9,3) -> 0.436
... B32: Net Profit | C32: =ROUND('Consol. Historical FS'!C34/'Consol. Historical FS'!C$9,3) -> 0.402 | D32: =ROUND('Consol. Historical FS'!D34/'Consol. Historical FS'!D$9,3) -> 0.289 | E32: =ROUND('Consol. Historical FS'!E34/'Consol. Historical FS'!E$9,3) -> 0.259 | F32: =ROUND('Consol. Historical FS'!F34/'Consol. Historical FS'!F$9,3) -> 0.303 | G32: =ROUND('Consol. Historical FS'!G34/'Consol. Historical FS'!G$9,3) -> 0.363
B33: Net Profit attributable to:
B34: Owners of the company | C34: =ROUND('Consol. Historical FS'!C36/'Consol. Historical FS'!C$9,3) -> 0.398 | D34: =ROUND('Consol. Historical FS'!D36/'Consol. Historical FS'!D$9,3) -> 0.285 | E34: =ROUND('Consol. Historical FS'!E36/'Consol. Historical FS'!E$9,3) -> 0.255 | F34: =ROUND('Consol. Historical FS'!F36/'Consol. Historical FS'!F$9,3) -> 0.304 | G34: =ROUND('Consol. Historical FS'!G36/'Consol. Historical FS'!G$9,3) -> 0.364
B35: Non-Controlling Interest | C35: =ROUND('Consol. Historical FS'!C37/'Consol. Historical FS'!C$9,3) -> 0.004 | D35: =ROUND('Consol. Historical FS'!D37/'Consol. Historical FS'!D$9,3) -> 0.004 | E35: =ROUND('Consol. Historical FS'!E37/'Consol. Historical FS'!E$9,3) -> 0.004 | F35: =ROUND('Consol. Historical FS'!F37/'Consol. Historical FS'!F$9,3) -> 0 | G35: =ROUND('Consol. Historical FS'!G37/'Consol. Historical FS'!G$9,3) -> -0.001
A37: # | B37: Balance Sheet - as a % of Total Assets
B39: ASSETS
B40: Non-current Assets
B41: Property, Plant and Equipment | C41: =ROUND('Consol. Historical FS'!C43/'Consol. Historical FS'!C$73,3) -> 0.488 | D41: =ROUND('Consol. Historical FS'!D43/'Consol. Historical FS'!D$73,3) -> 0.416 | E41: =ROUND('Consol. Historical FS'!E43/'Consol. Historical FS'!E$73,3) -> 0.421 | F41: =ROUND('Consol. Historical FS'!F43/'Consol. Historical FS'!F$73,3) -> 0.436 | G41: =ROUND('Consol. Historical FS'!G43/'Consol. Historical FS'!G$73,3) -> 0.461
B42: Right of Use Assets | C42: =ROUND('Consol. Historical FS'!C44/'Consol. Historical FS'!C$73,3) -> 0.024 | D42: =ROUND('Consol. Historical FS'!D44/'Consol. Historical FS'!D$73,3) -> 0.028 | E42: =ROUND('Consol. Historical FS'!E44/'Consol. Historical FS'!E$73,3) -> 0.031 | F42: =ROUND('Consol. Historical FS'!F44/'Consol. Historical FS'!F$73,3) -> 0.032 | G42: =ROUND('Consol. Historical FS'!G44/'Consol. Historical FS'!G$73,3) -> 0.046
B43: Capital work-in-progress | C43: =ROUND('Consol. Historical FS'!C45/'Consol. Historical FS'!C$73,3) -> 0.049 | D43: =ROUND('Consol. Historical FS'!D45/'Consol. Historical FS'!D$73,3) -> 0.04 | E43: =ROUND('Consol. Historical FS'!E45/'Consol. Historical FS'!E$73,3) -> 0.059 | F43: =ROUND('Consol. Historical FS'!F45/'Consol. Historical FS'!F$73,3) -> 0.092 | G43: =ROUND('Consol. Historical FS'!G45/'Consol. Historical FS'!G$73,3) -> 0.086
B44: Investment Property | C44: =ROUND('Consol. Historical FS'!C46/'Consol. Historical FS'!C$73,3) -> 0 | D44: =ROUND('Consol. Historical FS'!D46/'Consol. Historical FS'!D$73,3) -> 0 | E44: =ROUND('Consol. Historical FS'!E46/'Consol. Historical FS'!E$73,3) -> 0.022 | F44: =ROUND('Consol. Historical FS'!F46/'Consol. Historical FS'!F$73,3) -> 0.011 | G44: =ROUND('Consol. Historical FS'!G46/'Consol. Historical FS'!G$73,3) -> 0.011
B45: Goodwill | C45: =ROUND('Consol. Historical FS'!C47/'Consol. Historical FS'!C$73,3) -> 0.054 | D45: =ROUND('Consol. Historical FS'!D47/'Consol. Historical FS'!D$73,3) -> 0.067 | E45: =ROUND('Consol. Historical FS'!E47/'Consol. Historical FS'!E$73,3) -> 0.061 | F45: =ROUND('Consol. Historical FS'!F47/'Consol. Historical FS'!F$73,3) -> 0.058 | G45: =ROUND('Consol. Historical FS'!G47/'Consol. Historical FS'!G$73,3) -> 0.052
B46: Other Intangible Assets | C46: =ROUND('Consol. Historical FS'!C48/'Consol. Historical FS'!C$73,3) -> 0.073 | D46: =ROUND('Consol. Historical FS'!D48/'Consol. Historical FS'!D$73,3) -> 0.116 | E46: =ROUND('Consol. Historical FS'!E48/'Consol. Historical FS'!E$73,3) -> 0.1 | F46: =ROUND('Consol. Historical FS'!F48/'Consol. Historical FS'!F$73,3) -> 0.095 | G46: =ROUND('Consol. Historical FS'!G48/'Consol. Historical FS'!G$73,3) -> 0.092
B47: Intangible Assets under Development | C47: =ROUND('Consol. Historical FS'!C49/'Consol. Historical FS'!C$73,3) -> 0 | D47: =ROUND('Consol. Historical FS'!D49/'Consol. Historical FS'!D$73,3) -> 0 | E47: =ROUND('Consol. Historical FS'!E49/'Consol. Historical FS'!E$73,3) -> 0 | F47: =ROUND('Consol. Historical FS'!F49/'Consol. Historical FS'!F$73,3) -> 0 | G47: =ROUND('Consol. Historical FS'!G49/'Consol. Historical FS'!G$73,3) -> 0.001
B48: Investments accounted for using the equity method | C48: =ROUND('Consol. Historical FS'!C50/'Consol. Historical FS'!C$73,3) -> 0.009 | D48: =ROUND('Consol. Historical FS'!D50/'Consol. Historical FS'!D$73,3) -> 0.012 | E48: =ROUND('Consol. Historical FS'!E50/'Consol. Historical FS'!E$73,3) -> 0.022 | F48: =ROUND('Consol. Historical FS'!F50/'Consol. Historical FS'!F$73,3) -> 0.023 | G48: =ROUND('Consol. Historical FS'!G50/'Consol. Historical FS'!G$73,3) -> 0.023
B49: Financial assets | C49: =ROUND('Consol. Historical FS'!C51/'Consol. Historical FS'!C$73,3) -> 0 | D49: =ROUND('Consol. Historical FS'!D51/'Consol. Historical FS'!D$73,3) -> 0 | E49: =ROUND('Consol. Historical FS'!E51/'Consol. Historical FS'!E$73,3) -> 0 | F49: =ROUND('Consol. Historical FS'!F51/'Consol. Historical FS'!F$73,3) -> 0 | G49: =ROUND('Consol. Historical FS'!G51/'Consol. Historical FS'!G$73,3) -> 0
B50: a) Other Investments | C50: =ROUND('Consol. Historical FS'!C52/'Consol. Historical FS'!C$73,3) -> 0.006 | D50: =ROUND('Consol. Historical FS'!D52/'Consol. Historical FS'!D$73,3) -> 0.019 | E50: =ROUND('Consol. Historical FS'!E52/'Consol. Historical FS'!E$73,3) -> 0.009 | F50: =ROUND('Consol. Historical FS'!F52/'Consol. Historical FS'!F$73,3) -> 0.008 | G50: =ROUND('Consol. Historical FS'!G52/'Consol. Historical FS'!G$73,3) -> 0.006
B51: b) Other Financial Assets | C51: =ROUND('Consol. Historical FS'!C53/'Consol. Historical FS'!C$73,3) -> 0.081 | D51: =ROUND('Consol. Historical FS'!D53/'Consol. Historical FS'!D$73,3) -> 0.083 | E51: =ROUND('Consol. Historical FS'!E53/'Consol. Historical FS'!E$73,3) -> 0.067 | F51: =ROUND('Consol. Historical FS'!F53/'Consol. Historical FS'!F$73,3) -> 0.04 | G51: =ROUND('Consol. Historical FS'!G53/'Consol. Historical FS'!G$73,3) -> 0.042
B52: Deferred Tax Assets (Net) | C52: =ROUND('Consol. Historical FS'!C54/'Consol. Historical FS'!C$73,3) -> 0.012 | D52: =ROUND('Consol. Historical FS'!D54/'Consol. Historical FS'!D$73,3) -> 0.014 | E52: =ROUND('Consol. Historical FS'!E54/'Consol. Historical FS'!E$73,3) -> 0.019 | F52: =ROUND('Consol. Historical FS'!F54/'Consol. Historical FS'!F$73,3) -> 0.016 | G52: =ROUND('Consol. Historical FS'!G54/'Consol. Historical FS'!G$73,3) -> 0.014
... B55: Total Non-current Assets | C55: =ROUND('Consol. Historical FS'!C57/'Consol. Historical FS'!C$73,3) -> 0.83 | D55: =ROUND('Consol. Historical FS'!D57/'Consol. Historical FS'!D$73,3) -> 0.819 | E55: =ROUND('Consol. Historical FS'!E57/'Consol. Historical FS'!E$73,3) -> 0.848 | F55: =ROUND('Consol. Historical FS'!F57/'Consol. Historical FS'!F$73,3) -> 0.853 | G55: =ROUND('Consol. Historical FS'!G57/'Consol. Historical FS'!G$73,3) -> 0.86
B57: Current assets
B58: Inventories | C58: =ROUND('Consol. Historical FS'!C60/'Consol. Historical FS'!C$73,3) -> 0.013 | D58: =ROUND('Consol. Historical FS'!D60/'Consol. Historical FS'!D$73,3) -> 0.004 | E58: =ROUND('Consol. Historical FS'!E60/'Consol. Historical FS'!E$73,3) -> 0.004 | F58: =ROUND('Consol. Historical FS'!F60/'Consol. Historical FS'!F$73,3) -> 0.004 | G58: =ROUND('Consol. Historical FS'!G60/'Consol. Historical FS'!G$73,3) -> 0.004
B59: Financial assets | C59: =ROUND('Consol. Historical FS'!C61/'Consol. Historical FS'!C$73,3) -> 0 | D59: =ROUND('Consol. Historical FS'!D61/'Consol. Historical FS'!D$73,3) -> 0 | E59: =ROUND('Consol. Historical FS'!E61/'Consol. Historical FS'!E$73,3) -> 0 | F59: =ROUND('Consol. Historical FS'!F61/'Consol. Historical FS'!F$73,3) -> 0 | G59: =ROUND('Consol. Historical FS'!G61/'Consol. Historical FS'!G$73,3) -> 0
B60: a) Investments | C60: =ROUND('Consol. Historical FS'!C62/'Consol. Historical FS'!C$73,3) -> 0.015 | D60: =ROUND('Consol. Historical FS'!D62/'Consol. Historical FS'!D$73,3) -> 0 | E60: =ROUND('Consol. Historical FS'!E62/'Consol. Historical FS'!E$73,3) -> 0.035 | F60: =ROUND('Consol. Historical FS'!F62/'Consol. Historical FS'!F$73,3) -> 0.006 | G60: =ROUND('Consol. Historical FS'!G62/'Consol. Historical FS'!G$73,3) -> 0.006
B61: b) Trade receivables | C61: =ROUND('Consol. Historical FS'!C63/'Consol. Historical FS'!C$73,3) -> 0.032 | D61: =ROUND('Consol. Historical FS'!D63/'Consol. Historical FS'!D$73,3) -> 0.022 | E61: =ROUND('Consol. Historical FS'!E63/'Consol. Historical FS'!E$73,3) -> 0.028 | F61: =ROUND('Consol. Historical FS'!F63/'Consol. Historical FS'!F$73,3) -> 0.031 | G61: =ROUND('Consol. Historical FS'!G63/'Consol. Historical FS'!G$73,3) -> 0.033
B62: c) Cash and Cash Equivalents | C62: =ROUND('Consol. Historical FS'!C64/'Consol. Historical FS'!C$73,3) -> 0.056 | D62: =ROUND('Consol. Historical FS'!D64/'Consol. Historical FS'!D$73,3) -> 0.087 | E62: =ROUND('Consol. Historical FS'!E64/'Consol. Historical FS'!E$73,3) -> 0.008 | F62: =ROUND('Consol. Historical FS'!F64/'Consol. Historical FS'!F$73,3) -> 0.013 | G62: =ROUND('Consol. Historical FS'!G64/'Consol. Historical FS'!G$73,3) -> 0.025
B63: d) Bank Balances other than Cash and Cash Equivalents | C63: =ROUND('Consol. Historical FS'!C65/'Consol. Historical FS'!C$73,3) -> 0.007 | D63: =ROUND('Consol. Historical FS'!D65/'Consol. Historical FS'!D$73,3) -> 0.02 | E63: =ROUND('Consol. Historical FS'!E65/'Consol. Historical FS'!E$73,3) -> 0.029 | F63: =ROUND('Consol. Historical FS'!F65/'Consol. Historical FS'!F$73,3) -> 0.051 | G63: =ROUND('Consol. Historical FS'!G65/'Consol. Historical FS'!G$73,3) -> 0.024
B64: e) Loans | C64: =ROUND('Consol. Historical FS'!C66/'Consol. Historical FS'!C$73,3) -> 0.014 | D64: =ROUND('Consol. Historical FS'!D66/'Consol. Historical FS'!D$73,3) -> 0.013 | E64: =ROUND('Consol. Historical FS'!E66/'Consol. Historical FS'!E$73,3) -> 0.004 | F64: =ROUND('Consol. Historical FS'!F66/'Consol. Historical FS'!F$73,3) -> 0.002 | G64: =ROUND('Consol. Historical FS'!G66/'Consol. Historical FS'!G$73,3) -> 0.001
B65: f) Derivative Instruments | C65: =ROUND('Consol. Historical FS'!C67/'Consol. Historical FS'!C$73,3) -> 0 | D65: =ROUND('Consol. Historical FS'!D67/'Consol. Historical FS'!D$73,3) -> 0 | E65: =ROUND('Consol. Historical FS'!E67/'Consol. Historical FS'!E$73,3) -> 0 | F65: =ROUND('Consol. Historical FS'!F67/'Consol. Historical FS'!F$73,3) -> 0 | G65: =ROUND('Consol. Historical FS'!G67/'Consol. Historical FS'!G$73,3) -> 0
B66: g) Other Financial Assets | C66: =ROUND('Consol. Historical FS'!C68/'Consol. Historical FS'!C$73,3) -> 0.015 | D66: =ROUND('Consol. Historical FS'!D68/'Consol. Historical FS'!D$73,3) -> 0.008 | E66: =ROUND('Consol. Historical FS'!E68/'Consol. Historical FS'!E$73,3) -> 0.017 | F66: =ROUND('Consol. Historical FS'!F68/'Consol. Historical FS'!F$73,3) -> 0.029 | G66: =ROUND('Consol. Historical FS'!G68/'Consol. Historical FS'!G$73,3) -> 0.033
B67: Other Current Assets | C67: =ROUND('Consol. Historical FS'!C69/'Consol. Historical FS'!C$73,3) -> 0.013 | D67: =ROUND('Consol. Historical FS'!D69/'Consol. Historical FS'!D$73,3) -> 0.007 | E67: =ROUND('Consol. Historical FS'!E69/'Consol. Historical FS'!E$73,3) -> 0.01 | F67: =ROUND('Consol. Historical FS'!F69/'Consol. Historical FS'!F$73,3) -> 0.01 | G67: =ROUND('Consol. Historical FS'!G69/'Consol. Historical FS'!G$73,3) -> 0.013
B68: Current Tax Assets | C68: =ROUND('Consol. Historical FS'!C70/'Consol. Historical FS'!C$73,3) -> 0 | D68: =ROUND('Consol. Historical FS'!D70/'Consol. Historical FS'!D$73,3) -> 0 | E68: =ROUND('Consol. Historical FS'!E70/'Consol. Historical FS'!E$73,3) -> 0 | F68: =ROUND('Consol. Historical FS'!F70/'Consol. Historical FS'!F$73,3) -> 0 | G68: =ROUND('Consol. Historical FS'!G70/'Consol. Historical FS'!G$73,3) -> 0
B69: Total Current Assets | C69: =ROUND('Consol. Historical FS'!C71/'Consol. Historical FS'!C$73,3) -> 0.166 | D69: =ROUND('Consol. Historical FS'!D71/'Consol. Historical FS'!D$73,3) -> 0.162 | E69: =ROUND('Consol. Historical FS'!E71/'Consol. Historical FS'!E$73,3) -> 0.135 | F69: =ROUND('Consol. Historical FS'!F71/'Consol. Historical FS'!F$73,3) -> 0.145 | G69: =ROUND('Consol. Historical FS'!G71/'Consol. Historical FS'!G$73,3) -> 0.139
... B71: Total Assets | C71: =ROUND('Consol. Historical FS'!C73/'Consol. Historical FS'!C$73,3) -> 1 | D71: =ROUND('Consol. Historical FS'!D73/'Consol. Historical FS'!D$73,3) -> 1 | E71: =ROUND('Consol. Historical FS'!E73/'Consol. Historical FS'!E$73,3) -> 1 | F71: =ROUND('Consol. Historical FS'!F73/'Consol. Historical FS'!F$73,3) -> 1 | G71: =ROUND('Consol. Historical FS'!G73/'Consol. Historical FS'!G$73,3) -> 1
B73: EQUITY AND LIABILITIES
B74: Equity
B75: Equity Share Capital | C75: =ROUND('Consol. Historical FS'!C77/'Consol. Historical FS'!C$73,3) -> 0.005 | D75: =ROUND('Consol. Historical FS'!D77/'Consol. Historical FS'!D$73,3) -> 0.004 | E75: =ROUND('Consol. Historical FS'!E77/'Consol. Historical FS'!E$73,3) -> 0.004 | F75: =ROUND('Consol. Historical FS'!F77/'Consol. Historical FS'!F$73,3) -> 0.004 | G75: =ROUND('Consol. Historical FS'!G77/'Consol. Historical FS'!G$73,3) -> 0.003
B76: Other Equity | C76: =ROUND('Consol. Historical FS'!C78/'Consol. Historical FS'!C$73,3) -> 0.401 | D76: =ROUND('Consol. Historical FS'!D78/'Consol. Historical FS'!D$73,3) -> 0.417 | E76: =ROUND('Consol. Historical FS'!E78/'Consol. Historical FS'!E$73,3) -> 0.393 | F76: =ROUND('Consol. Historical FS'!F78/'Consol. Historical FS'!F$73,3) -> 0.442 | G76: =ROUND('Consol. Historical FS'!G78/'Consol. Historical FS'!G$73,3) -> 0.458
B77: Equity Attributable to the Owners of the Company | C77: =ROUND('Consol. Historical FS'!C79/'Consol. Historical FS'!C$73,3) -> 0.407 | D77: =ROUND('Consol. Historical FS'!D79/'Consol. Historical FS'!D$73,3) -> 0.421 | E77: =ROUND('Consol. Historical FS'!E79/'Consol. Historical FS'!E$73,3) -> 0.397 | F77: =ROUND('Consol. Historical FS'!F79/'Consol. Historical FS'!F$73,3) -> 0.445 | G77: =ROUND('Consol. Historical FS'!G79/'Consol. Historical FS'!G$73,3) -> 0.461
B78: Non-Controlling Interests | C78: =ROUND('Consol. Historical FS'!C80/'Consol. Historical FS'!C$73,3) -> 0.019 | D78: =ROUND('Consol. Historical FS'!D80/'Consol. Historical FS'!D$73,3) -> 0.004 | E78: =ROUND('Consol. Historical FS'!E80/'Consol. Historical FS'!E$73,3) -> 0.012 | F78: =ROUND('Consol. Historical FS'!F80/'Consol. Historical FS'!F$73,3) -> 0.013 | G78: =ROUND('Consol. Historical FS'!G80/'Consol. Historical FS'!G$73,3) -> 0.019
B79: Total Equity | C79: =ROUND('Consol. Historical FS'!C81/'Consol. Historical FS'!C$73,3) -> 0.426 | D79: =ROUND('Consol. Historical FS'!D81/'Consol. Historical FS'!D$73,3) -> 0.425 | E79: =ROUND('Consol. Historical FS'!E81/'Consol. Historical FS'!E$73,3) -> 0.408 | F79: =ROUND('Consol. Historical FS'!F81/'Consol. Historical FS'!F$73,3) -> 0.459 | G79: =ROUND('Consol. Historical FS'!G81/'Consol. Historical FS'!G$73,3) -> 0.48
B81: Non-current Liabilities
B82: Financial Liabilities
B83: a) Borrowings | C83: =ROUND('Consol. Historical FS'!C85/'Consol. Historical FS'!C$73,3) -> 0.437 | D83: =ROUND('Consol. Historical FS'!D85/'Consol. Historical FS'!D$73,3) -> 0.398 | E83: =ROUND('Consol. Historical FS'!E85/'Consol. Historical FS'!E$73,3) -> 0.405 | F83: =ROUND('Consol. Historical FS'!F85/'Consol. Historical FS'!F$73,3) -> 0.317 | G83: =ROUND('Consol. Historical FS'!G85/'Consol. Historical FS'!G$73,3) -> 0.265
B84: b) Lease Liabilities | C84: =ROUND('Consol. Historical FS'!C86/'Consol. Historical FS'!C$73,3) -> 0.008 | D84: =ROUND('Consol. Historical FS'!D86/'Consol. Historical FS'!D$73,3) -> 0.02 | E84: =ROUND('Consol. Historical FS'!E86/'Consol. Historical FS'!E$73,3) -> 0.023 | F84: =ROUND('Consol. Historical FS'!F86/'Consol. Historical FS'!F$73,3) -> 0.025 | G84: =ROUND('Consol. Historical FS'!G86/'Consol. Historical FS'!G$73,3) -> 0.04
B85: c) Other Financial Liabilities | C85: =ROUND('Consol. Historical FS'!C87/'Consol. Historical FS'!C$73,3) -> 0.003 | D85: =ROUND('Consol. Historical FS'!D87/'Consol. Historical FS'!D$73,3) -> 0.002 | E85: =ROUND('Consol. Historical FS'!E87/'Consol. Historical FS'!E$73,3) -> 0.003 | F85: =ROUND('Consol. Historical FS'!F87/'Consol. Historical FS'!F$73,3) -> 0.003 | G85: =ROUND('Consol. Historical FS'!G87/'Consol. Historical FS'!G$73,3) -> 0.002
B86: d) Derivative Instruments | C86: =ROUND('Consol. Historical FS'!C88/'Consol. Historical FS'!C$73,3) -> 0 | D86: =ROUND('Consol. Historical FS'!D88/'Consol. Historical FS'!D$73,3) -> 0 | E86: =ROUND('Consol. Historical FS'!E88/'Consol. Historical FS'!E$73,3) -> 0 | F86: =ROUND('Consol. Historical FS'!F88/'Consol. Historical FS'!F$73,3) -> 0 | G86: =ROUND('Consol. Historical FS'!G88/'Consol. Historical FS'!G$73,3) -> 0
B87: Other Non-Current Liabilities | C87: =ROUND('Consol. Historical FS'!C89/'Consol. Historical FS'!C$73,3) -> 0.014 | D87: =ROUND('Consol. Historical FS'!D89/'Consol. Historical FS'!D$73,3) -> 0.01 | E87: =ROUND('Consol. Historical FS'!E89/'Consol. Historical FS'!E$73,3) -> 0.01 | F87: =ROUND('Consol. Historical FS'!F89/'Consol. Historical FS'!F$73,3) -> 0.014 | G87: =ROUND('Consol. Historical FS'!G89/'Consol. Historical FS'!G$73,3) -> 0.016
B88: Provisions | C88: =ROUND('Consol. Historical FS'!C90/'Consol. Historical FS'!C$73,3) -> 0 | D88: =ROUND('Consol. Historical FS'!D90/'Consol. Historical FS'!D$73,3) -> 0 | E88: =ROUND('Consol. Historical FS'!E90/'Consol. Historical FS'!E$73,3) -> 0.01 | F88: =ROUND('Consol. Historical FS'!F90/'Consol. Historical FS'!F$73,3) -> 0.009 | G88: =ROUND('Consol. Historical FS'!G90/'Consol. Historical FS'!G$73,3) -> 0.008
B89: Government Grants | C89: =ROUND('Consol. Historical FS'!C91/'Consol. Historical FS'!C$73,3) -> 0 | D89: =ROUND('Consol. Historical FS'!D91/'Consol. Historical FS'!D$73,3) -> 0 | E89: =ROUND('Consol. Historical FS'!E91/'Consol. Historical FS'!E$73,3) -> 0 | F89: =ROUND('Consol. Historical FS'!F91/'Consol. Historical FS'!F$73,3) -> 0 | G89: =ROUND('Consol. Historical FS'!G91/'Consol. Historical FS'!G$73,3) -> 0
B90: Deferred Tax Liabilities (Net) | C90: =ROUND('Consol. Historical FS'!C92/'Consol. Historical FS'!C$73,3) -> 0.016 | D90: =ROUND('Consol. Historical FS'!D92/'Consol. Historical FS'!D$73,3) -> 0.03 | E90: =ROUND('Consol. Historical FS'!E92/'Consol. Historical FS'!E$73,3) -> 0.028 | F90: =ROUND('Consol. Historical FS'!F92/'Consol. Historical FS'!F$73,3) -> 0.035 | G90: =ROUND('Consol. Historical FS'!G92/'Consol. Historical FS'!G$73,3) -> 0.034
B91: Total Non-current Liabilities | C91: =ROUND('Consol. Historical FS'!C93/'Consol. Historical FS'!C$73,3) -> 0.478 | D91: =ROUND('Consol. Historical FS'!D93/'Consol. Historical FS'!D$73,3) -> 0.461 | E91: =ROUND('Consol. Historical FS'!E93/'Consol. Historical FS'!E$73,3) -> 0.479 | F91: =ROUND('Consol. Historical FS'!F93/'Consol. Historical FS'!F$73,3) -> 0.403 | G91: =ROUND('Consol. Historical FS'!G93/'Consol. Historical FS'!G$73,3) -> 0.365
B93: Current Liabilities
B94: Financial liabilities
B95: a) Borrowings | C95: =ROUND('Consol. Historical FS'!C97/'Consol. Historical FS'!C$73,3) -> 0.005 | D95: =ROUND('Consol. Historical FS'!D97/'Consol. Historical FS'!D$73,3) -> 0.058 | E95: =ROUND('Consol. Historical FS'!E97/'Consol. Historical FS'!E$73,3) -> 0.029 | F95: =ROUND('Consol. Historical FS'!F97/'Consol. Historical FS'!F$73,3) -> 0.072 | G95: =ROUND('Consol. Historical FS'!G97/'Consol. Historical FS'!G$73,3) -> 0.074
B96: b) Lease Liabilities | C96: =ROUND('Consol. Historical FS'!C98/'Consol. Historical FS'!C$73,3) -> 0 | D96: =ROUND('Consol. Historical FS'!D98/'Consol. Historical FS'!D$73,3) -> 0 | E96: =ROUND('Consol. Historical FS'!E98/'Consol. Historical FS'!E$73,3) -> 0.001 | F96: =ROUND('Consol. Historical FS'!F98/'Consol. Historical FS'!F$73,3) -> 0.001 | G96: =ROUND('Consol. Historical FS'!G98/'Consol. Historical FS'!G$73,3) -> 0.002
B97: c) Trade payables | C97: =ROUND('Consol. Historical FS'!C99/'Consol. Historical FS'!C$73,3) -> 0 | D97: =ROUND('Consol. Historical FS'!D99/'Consol. Historical FS'!D$73,3) -> 0 | E97: =ROUND('Consol. Historical FS'!E99/'Consol. Historical FS'!E$73,3) -> 0 | F97: =ROUND('Consol. Historical FS'!F99/'Consol. Historical FS'!F$73,3) -> 0 | G97: =ROUND('Consol. Historical FS'!G99/'Consol. Historical FS'!G$73,3) -> 0
B98: Total outstanding dues of Micro Enterprises and Small Enterprises | C98: =ROUND('Consol. Historical FS'!C100/'Consol. Historical FS'!C$73,3) -> 0 | D98: =ROUND('Consol. Historical FS'!D100/'Consol. Historical FS'!D$73,3) -> 0 | E98: =ROUND('Consol. Historical FS'!E100/'Consol. Historical FS'!E$73,3) -> 0.001 | F98: =ROUND('Consol. Historical FS'!F100/'Consol. Historical FS'!F$73,3) -> 0.001 | G98: =ROUND('Consol. Historical FS'!G100/'Consol. Historical FS'!G$73,3) -> 0.001
B99: Total outstanding dues of Creditors other than Micro Enterprises and Small Enterprises | C99: =ROUND('Consol. Historical FS'!C101/'Consol. Historical FS'!C$73,3) -> 0.013 | D99: =ROUND('Consol. Historical FS'!D101/'Consol. Historical FS'!D$73,3) -> 0.011 | E99: =ROUND('Consol. Historical FS'!E101/'Consol. Historical FS'!E$73,3) -> 0.015 | F99: =ROUND('Consol. Historical FS'!F101/'Consol. Historical FS'!F$73,3) -> 0.015 | G99: =ROUND('Consol. Historical FS'!G101/'Consol. Historical FS'!G$73,3) -> 0.019
B100: d) Other Financial Liabilities | C100: =ROUND('Consol. Historical FS'!C102/'Consol. Historical FS'!C$73,3) -> 0.043 | D100: =ROUND('Consol. Historical FS'!D102/'Consol. Historical FS'!D$73,3) -> 0.023 | E100: =ROUND('Consol. Historical FS'!E102/'Consol. Historical FS'!E$73,3) -> 0.029 | F100: =ROUND('Consol. Historical FS'!F102/'Consol. Historical FS'!F$73,3) -> 0.032 | G100: =ROUND('Consol. Historical FS'!G102/'Consol. Historical FS'!G$73,3) -> 0.04
B101: e) Derivative Instruments | C101: =ROUND('Consol. Historical FS'!C103/'Consol. Historical FS'!C$73,3) -> 0 | D101: =ROUND('Consol. Historical FS'!D103/'Consol. Historical FS'!D$73,3) -> 0 | E101: =ROUND('Consol. Historical FS'!E103/'Consol. Historical FS'!E$73,3) -> 0 | F101: =ROUND('Consol. Historical FS'!F103/'Consol. Historical FS'!F$73,3) -> 0 | G101: =ROUND('Consol. Historical FS'!G103/'Consol. Historical FS'!G$73,3) -> 0
B102: Other Current Liabilities | C102: =ROUND('Consol. Historical FS'!C104/'Consol. Historical FS'!C$73,3) -> 0.03 | D102: =ROUND('Consol. Historical FS'!D104/'Consol. Historical FS'!D$73,3) -> 0.017 | E102: =ROUND('Consol. Historical FS'!E104/'Consol. Historical FS'!E$73,3) -> 0.016 | F102: =ROUND('Consol. Historical FS'!F104/'Consol. Historical FS'!F$73,3) -> 0.015 | G102: =ROUND('Consol. Historical FS'!G104/'Consol. Historical FS'!G$73,3) -> 0.017
B103: Provisions | C103: =ROUND('Consol. Historical FS'!C105/'Consol. Historical FS'!C$73,3) -> 0.001 | D103: =ROUND('Consol. Historical FS'!D105/'Consol. Historical FS'!D$73,3) -> 0.001 | E103: =ROUND('Consol. Historical FS'!E105/'Consol. Historical FS'!E$73,3) -> 0.005 | F103: =ROUND('Consol. Historical FS'!F105/'Consol. Historical FS'!F$73,3) -> 0.002 | G103: =ROUND('Consol. Historical FS'!G105/'Consol. Historical FS'!G$73,3) -> 0.002
B104: Government Grants | C104: =ROUND('Consol. Historical FS'!C106/'Consol. Historical FS'!C$73,3) -> 0 | D104: =ROUND('Consol. Historical FS'!D106/'Consol. Historical FS'!D$73,3) -> 0 | E104: =ROUND('Consol. Historical FS'!E106/'Consol. Historical FS'!E$73,3) -> 0 | F104: =ROUND('Consol. Historical FS'!F106/'Consol. Historical FS'!F$73,3) -> 0 | G104: =ROUND('Consol. Historical FS'!G106/'Consol. Historical FS'!G$73,3) -> 0
B105: Current Tax Liabilities (Net) | C105: =ROUND('Consol. Historical FS'!C107/'Consol. Historical FS'!C$73,3) -> 0.001 | D105: =ROUND('Consol. Historical FS'!D107/'Consol. Historical FS'!D$73,3) -> 0.001 | E105: =ROUND('Consol. Historical FS'!E107/'Consol. Historical FS'!E$73,3) -> 0.005 | F105: =ROUND('Consol. Historical FS'!F107/'Consol. Historical FS'!F$73,3) -> 0 | G105: =ROUND('Consol. Historical FS'!G107/'Consol. Historical FS'!G$73,3) -> 0.001
B106: Total Current Liabilities | C106: =ROUND('Consol. Historical FS'!C108/'Consol. Historical FS'!C$73,3) -> 0.094 | D106: =ROUND('Consol. Historical FS'!D108/'Consol. Historical FS'!D$73,3) -> 0.111 | E106: =ROUND('Consol. Historical FS'!E108/'Consol. Historical FS'!E$73,3) -> 0.099 | F106: =ROUND('Consol. Historical FS'!F108/'Consol. Historical FS'!F$73,3) -> 0.138 | G106: =ROUND('Consol. Historical FS'!G108/'Consol. Historical FS'!G$73,3) -> 0.155
... B108: Total Equity and Liabilities | C108: =ROUND('Consol. Historical FS'!C110/'Consol. Historical FS'!C$73,3) -> 1 | D108: =ROUND('Consol. Historical FS'!D110/'Consol. Historical FS'!D$73,3) -> 1 | E108: =ROUND('Consol. Historical FS'!E110/'Consol. Historical FS'!E$73,3) -> 1 | F108: =ROUND('Consol. Historical FS'!F110/'Consol. Historical FS'!F$73,3) -> 1 | G108: =ROUND('Consol. Historical FS'!G110/'Consol. Historical FS'!G$73,3) -> 1
A112: # | B112: Cash Flow Statement - as a % of Net Cash Flow from Operating Activities
B114: Cash Flow from Operating Activities
B115: Profit Before Tax
B116: Profit Before Tax on Continued Operations | C116: =ROUND('Consol. Historical FS'!C118/'Consol. Historical FS'!C$153,3) -> 0.833 | D116: =ROUND('Consol. Historical FS'!D118/'Consol. Historical FS'!D$153,3) -> 0.549 | E116: =ROUND('Consol. Historical FS'!E118/'Consol. Historical FS'!E$153,3) -> 0.46 | F116: =ROUND('Consol. Historical FS'!F118/'Consol. Historical FS'!F$153,3) -> 0.672 | G116: =ROUND('Consol. Historical FS'!G118/'Consol. Historical FS'!G$153,3) -> 0.756
B117: Profit / (Loss) Before Tax on Discontinued Operations | C117: =ROUND('Consol. Historical FS'!C119/'Consol. Historical FS'!C$153,3) -> 0 | D117: =ROUND('Consol. Historical FS'!D119/'Consol. Historical FS'!D$153,3) -> 0 | E117: =ROUND('Consol. Historical FS'!E119/'Consol. Historical FS'!E$153,3) -> 0 | F117: =ROUND('Consol. Historical FS'!F119/'Consol. Historical FS'!F$153,3) -> 0 | G117: =ROUND('Consol. Historical FS'!G119/'Consol. Historical FS'!G$153,3) -> 0
B118: Adjustments for:
B119: Depreciation and Amortisation Expense | C119: =ROUND('Consol. Historical FS'!C121/'Consol. Historical FS'!C$153,3) -> 0.279 | D119: =ROUND('Consol. Historical FS'!D121/'Consol. Historical FS'!D$153,3) -> 0.298 | E119: =ROUND('Consol. Historical FS'!E121/'Consol. Historical FS'!E$153,3) -> 0.287 | F119: =ROUND('Consol. Historical FS'!F121/'Consol. Historical FS'!F$153,3) -> 0.259 | G119: =ROUND('Consol. Historical FS'!G121/'Consol. Historical FS'!G$153,3) -> 0.254
B120: Exceptional Items (Net) | C120: =ROUND('Consol. Historical FS'!C122/'Consol. Historical FS'!C$153,3) -> 0 | D120: =ROUND('Consol. Historical FS'!D122/'Consol. Historical FS'!D$153,3) -> 0.039 | E120: =ROUND('Consol. Historical FS'!E122/'Consol. Historical FS'!E$153,3) -> 0.107 | F120: =ROUND('Consol. Historical FS'!F122/'Consol. Historical FS'!F$153,3) -> 0.025 | G120: =ROUND('Consol. Historical FS'!G122/'Consol. Historical FS'!G$153,3) -> 0.014
B121: Intangible assets written off | C121: =ROUND('Consol. Historical FS'!C123/'Consol. Historical FS'!C$153,3) -> 0 | D121: =ROUND('Consol. Historical FS'!D123/'Consol. Historical FS'!D$153,3) -> 0 | E121: =ROUND('Consol. Historical FS'!E123/'Consol. Historical FS'!E$153,3) -> 0 | F121: =ROUND('Consol. Historical FS'!F123/'Consol. Historical FS'!F$153,3) -> 0 | G121: =ROUND('Consol. Historical FS'!G123/'Consol. Historical FS'!G$153,3) -> 0
B122: Share Based Payment Expenses | C122: =ROUND('Consol. Historical FS'!C124/'Consol. Historical FS'!C$153,3) -> 0 | D122: =ROUND('Consol. Historical FS'!D124/'Consol. Historical FS'!D$153,3) -> 0 | E122: =ROUND('Consol. Historical FS'!E124/'Consol. Historical FS'!E$153,3) -> 0 | F122: =ROUND('Consol. Historical FS'!F124/'Consol. Historical FS'!F$153,3) -> 0 | G122: =ROUND('Consol. Historical FS'!G124/'Consol. Historical FS'!G$153,3) -> 0
B123: Loss / (Profit) on Property Plant and Equipment and ROU Assets sold/discarded, (Net) | C123: =ROUND('Consol. Historical FS'!C125/'Consol. Historical FS'!C$153,3) -> -0.012 | D123: =ROUND('Consol. Historical FS'!D125/'Consol. Historical FS'!D$153,3) -> 0 | E123: =ROUND('Consol. Historical FS'!E125/'Consol. Historical FS'!E$153,3) -> -0.005 | F123: =ROUND('Consol. Historical FS'!F125/'Consol. Historical FS'!F$153,3) -> -0.001 | G123: =ROUND('Consol. Historical FS'!G125/'Consol. Historical FS'!G$153,3) -> 0
B124: Loss/ (Profit) on Sale of Investments carried at FWPL {including unrealised fair value gain) | C124: =ROUND('Consol. Historical FS'!C126/'Consol. Historical FS'!C$153,3) -> -0.01 | D124: =ROUND('Consol. Historical FS'!D126/'Consol. Historical FS'!D$153,3) -> -0.008 | E124: =ROUND('Consol. Historical FS'!E126/'Consol. Historical FS'!E$153,3) -> -0.007 | F124: =ROUND('Consol. Historical FS'!F126/'Consol. Historical FS'!F$153,3) -> -0.006 | G124: =ROUND('Consol. Historical FS'!G126/'Consol. Historical FS'!G$153,3) -> -0.041
B125: Impairment allowance for receivables and advances (includes bad debts written off) (Net) | C125: =ROUND('Consol. Historical FS'!C127/'Consol. Historical FS'!C$153,3) -> 0 | D125: =ROUND('Consol. Historical FS'!D127/'Consol. Historical FS'!D$153,3) -> 0 | E125: =ROUND('Consol. Historical FS'!E127/'Consol. Historical FS'!E$153,3) -> 0 | F125: =ROUND('Consol. Historical FS'!F127/'Consol. Historical FS'!F$153,3) -> 0 | G125: =ROUND('Consol. Historical FS'!G127/'Consol. Historical FS'!G$153,3) -> 0
B126: Net unrealised Foreign Exchange differences including impact of Foreign Currency Translation | C126: =ROUND('Consol. Historical FS'!C128/'Consol. Historical FS'!C$153,3) -> -0.097 | D126: =ROUND('Consol. Historical FS'!D128/'Consol. Historical FS'!D$153,3) -> 0.088 | E126: =ROUND('Consol. Historical FS'!E128/'Consol. Historical FS'!E$153,3) -> 0.212 | F126: =ROUND('Consol. Historical FS'!F128/'Consol. Historical FS'!F$153,3) -> 0.022 | G126: =ROUND('Consol. Historical FS'!G128/'Consol. Historical FS'!G$153,3) -> 0.042
...

Sheet 2Q26 Performance
C3: 2Q'26 Financial Performance (Consolidated):
C5: ₹'cr unless stated otherwise | D5: Q2 FY26 | E5: Q1 FY26 | F5: Q-o-Q | G5: Q2 FY25 | H5: Y-o-Y | I5: H1 FY26 | J5: H1 FY25 | K5: Y-o-Y
C6: Revenue from Operations | D6: 9167.46 | E6: 9126.14 | F6: =D6/E6-1 -> 0.0045276535 | G6: 7067.02 | H6: =D6/G6-1 -> 0.29721721 | I6: =D6+E6 -> 18293.6 | J6: 14023.34 | K6: =I6/J6-1 -> 0.30451091
C7: Gross Profit | D7: =D6-2496.35 -> 6671.11 | E7: =E6-2526.29 -> 6599.85 | F7: =D7/E7-1 -> 0.010797215 | G7: =G6-1762.82 -> 5304.2 | H7: =D7/G7-1 -> 0.25770333 | I7: =I6-5022.64 -> 13270.96 | J7: =J6-3629.39 -> 10393.95 | K7: =I7/J7-1 -> 0.2767966
C8: Gross Profit Margin | D8: =D7/D$6 -> 0.72769448 | E8: =E7/E$6 -> 0.72318088 | F8: =D8-E8 -> 0.0045135911 | G8: =G7/G$6 -> 0.75055681 | H8: =D8-G8 -> -0.022862336 | I8: =I7/I$6 -> 0.72544278 | J8: =J7/J$6 -> 0.74118933 | K8: =I8-J8 -> -0.015746554
C9: EBITDA | D9: =D7-585.51-535.33 -> 5550.27 | E9: =E7-569.21-535.31 -> 5495.33 | F9: =D9/E9-1 -> 0.0099975798 | G9: =G7-506.06-429.27 -> 4368.87 | H9: =D9/G9-1 -> 0.27041317 | I9: =I7-1154.72-1070.64 -> 11045.6 | J9: =J7-975.33-805.27 -> 8613.35 | K9: =I9/J9-1 -> 0.28238142
C10: EBITDA Margin | D10: =D9/D$6 -> 0.6054316 | E10: =E9/E$6 -> 0.60215272 | F10: =D10-E10 -> 0.0032788853 | G10: =G9/G$6 -> 0.61820541 | H10: =D10-G10 -> -0.012773808 | I10: =I9/I$6 -> 0.60379586 | J10: =J9/J$6 -> 0.6142153 | K10: =I10-J10 -> -0.010419438
C11: PAT | D11: 3120.2 | E11: 3310.6 | F11: =D11/E11-1 -> -0.057512233 | G11: 2412.54 | H11: =D11/G11-1 -> 0.29332571 | I11: 6430.8 | J11: 5519.77 | K11: =I11/J11-1 -> 0.16504854
C12: PAT Margin | D12: =D11/D$6 -> 0.340356 | E12: =E11/E$6 -> 0.36276016 | F12: =D12-E12 -> -0.022404161 | G12: =G11/G$6 -> 0.3413801 | H12: =D12-G12 -> -0.0010241025 | I12: =I11/I$6 -> 0.35153278 | J12: =J11/J$6 -> 0.39361308 | K12: =I12-J12 -> -0.0420803
C13: Owners of the Company | D13: 3109.05 | E13: 3314.59 | F13: =D13/E13-1 -> -0.062010686 | G13: 2445 | H13: =D13/G13-1 -> 0.27159509 | I13: 6423.64 | J13: 5557.83 | K13: =I13/J13-1 -> 0.15578202
C14: Non-controlling interests | D14: =D11-D13 -> 11.15 | E14: =E11-E13 -> -3.99 | F14: =D14/E14-1 -> -3.7944862 | G14: =G11-G13 -> -32.46 | H14: =D14/G14-1 -> -1.3434997 | I14: =I11-I13 -> 7.16 | J14: =J11-J13 -> -38.06 | K14: =I14/J14-1 -> -1.188124
C15: EPS | D15: 14.39 | E15: 15.34 | F15: =D15/E15-1 -> -0.061929596 | G15: 11.32 | H15: =D15/G15-1 -> 0.27120141 | I15: 29.74 | J15: 25.73 | K15: =I15/J15-1 -> 0.1558492
C17: Segmental Data
C18: Revenue from Operations
C19: Ports and SEZ Activities | D19: 8054.13 | E19: 7652.89 | F19: =D19/E19-1 -> 0.052429866 | G19: 6421.03 | H19: =D19/G19-1 -> 0.25433614 | I19: =D19+E19 -> 15707.02 | J19: 13360.37 | K19: =I19/J19-1 -> 0.17564259
C20: Others | D20: 1196.35 | E20: 1515.71 | F20: =D20/E20-1 -> -0.21069994 | G20: 678.88 | H20: =D20/G20-1 -> 0.76224075 | I20: =D20+E20 -> 2712.06 | J20: 1334.55 | K20: =I20/J20-1 -> 1.0321906
C21: Less: Inter-Segment Revenue | D21: -83.02 | E21: -42.46 | F21: =D21/E21-1 -> 0.955252 | G21: -32.89 | H21: =D21/G21-1 -> 1.5241715 | I21: =D21+E21 -> -125.48 | J21: -68.31 | K21: =I21/J21-1 -> 0.83691992
C22: Total Revenue | D22: =SUM(D19:D21) -> 9167.46 | E22: =SUM(E19:E21) -> 9126.14 | F22: =D22/E22-1 -> 0.0045276535 | G22: =SUM(G19:G21) -> 7067.02 | H22: =D22/G22-1 -> 0.29721721 | I22: =D22+E22 -> 18293.6 | J22: =SUM(J19:J21) -> 14626.61 | K22: =I22/J22-1 -> 0.25070676
C24: EBITDA Margin
C25: Domestic Ports | D25: 0.738 | E25: 0.746 | F25: =D25-E25 -> -0.008 | G25: 0.729 | H25: =D25-G25 -> 0.009 | I25: 0.742 | J25: 0.727 | K25: =I25-J25 -> 0.015
C26: International Ports | D26: 0.242 | E26: 0.211 | F26: =D26-E26 -> 0.031 | G26: 0.145 | H26: =D26-G26 -> 0.097 | I26: 0.227 | J26: 0.136 | K26: =I26-J26 -> 0.091
C27: Logistics | D27: 0.209 | E27: 0.181 | F27: =D27-E27 -> 0.028 | G27: 0.265 | H27: =D27-G27 -> -0.056 | I27: 0.194 | J27: 0.259 | K27: =I27-J27 -> -0.065
C28: Marine | D28: 0.527 | E28: 0.55 | F28: =D28-E28 -> -0.023 | G28: 0.463 | H28: =D28-G28 -> 0.064 | I28: 0.537 | J28: 0.431 | K28: =I28-J28 -> 0.106
C29: Port development & SEZ | D29: 1 | E29: 0.593 | F29: =D29-E29 -> 0.407 | G29: 1 | H29: =D29-G29 -> 0 | I29: 0.655 | J29: 1 | K29: =I29-J29 -> -0.345

Sheet Projected Financials
A13: Projected Financials -->>

Sheet 3 Model Projected FS
I1: =[2]Scenarios!L1 -> Currently Running: Base Case Scenario
B2: CONSOLIDATED - PROJECTED FINANCIAL STATEMENTS
B3: ₹'cr, unless otherwise stated | C3: ='Consol. Historical FS'!C3 -> FY21A | D3: ='Consol. Historical FS'!D3 -> FY22A | E3: ='Consol. Historical FS'!E3 -> FY23A | F3: ='Consol. Historical FS'!F3 -> FY24A | G3: ='Consol. Historical FS'!G3 -> FY25A | H3: FY26E | I3: FY27E
A5: # | B5: Profit & Loss Statement
B7: Revenue from Operations | C7: ='Consol. Historical FS'!C7 -> 12549.6 | D7: ='Consol. Historical FS'!D7 -> 17118.79 | E7: ='Consol. Historical FS'!E7 -> 20851.91 | F7: ='Consol. Historical FS'!F7 -> 26710.56 | G7: ='Consol. Historical FS'!G7 -> 30475.33
B8: Other Operating Revenues | C8: ='Consol. Historical FS'!C8 -> 0 | D8: ='Consol. Historical FS'!D8 -> 0 | E8: ='Consol. Historical FS'!E8 -> 0 | F8: ='Consol. Historical FS'!F8 -> 0 | G8: ='Consol. Historical FS'!G8 -> 0
B9: Total Revenue | C9: =ROUND(SUM(C7:C8),2) -> 12549.6 | D9: =SUM(D7:D8) -> 17118.79 | E9: =SUM(E7:E8) -> 20851.91 | F9: =SUM(F7:F8) -> 26710.56 | G9: =SUM(G7:G8) -> 30475.33 | H9: =Scenarios!K11 -> 37803.28 | I9: =Scenarios!L11 -> 46945.27
B10: Revenue Growth YoY | D10: =ROUND(D9/C9-1,3) -> 0.364 | E10: =ROUND(E9/D9-1,3) -> 0.218 | F10: =ROUND(F9/E9-1,3) -> 0.281 | G10: =ROUND(G9/F9-1,3) -> 0.141 | H10: =ROUND(H9/G9-1,3) -> 0.24 | I10: =ROUND(I9/H9-1,3) -> 0.242 | T10: ='3 Model Projected FS'!G84/'3 Model Projected FS'!G113*#REF!+('3 Model Projected FS'!G96+'3 Model Projected FS'!G111)/'3 Model Projected FS'!G113 -> #REF!
B13: Operating Expenses | C13: ='Consol. Historical FS'!C10 -> 3259.49 | D13: ='Consol. Historical FS'!D10 -> 4865.11 | E13: ='Consol. Historical FS'!E10 -> 5654.56 | F13: ='Consol. Historical FS'!F10 -> 7116.34 | G13: ='Consol. Historical FS'!G10 -> 8069.75 | H13: =Scenarios!K156 -> 10017.87 | I13: =Scenarios!L156 -> 12299.66
B14: Gross Profit | C14: =ROUND(C9-SUM(C13:C13),2) -> 9290.11 | D14: =ROUND(D9-SUM(D13:D13),2) -> 12253.68 | E14: =ROUND(E9-SUM(E13:E13),2) -> 15197.35 | F14: =ROUND(F9-SUM(F13:F13),2) -> 19594.22 | G14: =ROUND(G9-SUM(G13:G13),2) -> 22405.58 | H14: =ROUND(H9-SUM(H13:H13),2) -> 27785.41 | I14: =ROUND(I9-SUM(I13:I13),2) -> 34645.61
B15: Gross Profit Margin | C15: =ROUND(C14/C9,3) -> 0.74 | D15: =ROUND(D14/D9,3) -> 0.716 | E15: =ROUND(E14/E9,3) -> 0.729 | F15: =ROUND(F14/F9,3) -> 0.734 | G15: =ROUND(G14/G9,3) -> 0.735 | H15: =ROUND(H14/H9,3) -> 0.735 | I15: =ROUND(I14/I9,3) -> 0.738
B16: Employee Benefits Expense | C16: ='Consol. Historical FS'!C14 -> 615.05 | D16: ='Consol. Historical FS'!D14 -> 779.43 | E16: ='Consol. Historical FS'!E14 -> 1178.17 | F16: ='Consol. Historical FS'!F14 -> 1896.4 | G16: ='Consol. Historical FS'!G14 -> 2008.66 | H16: =Scenarios!K182 -> 2381.61 | I16: =Scenarios!L182 -> 3051.44
B17: Loss on fair valuation of Compulsorily Convertible Preference Shares | C17: ='Consol. Historical FS'!C15 -> 0 | D17: ='Consol. Historical FS'!D15 -> 0 | E17: ='Consol. Historical FS'!E15 -> 0 | F17: ='Consol. Historical FS'!F15 -> 0 | G17: ='Consol. Historical FS'!G15 -> 0 | H17: =Scenarios!K190 -> 0 | I17: =Scenarios!L190 -> 0
B18: Other Expenses | C18: ='Consol. Historical FS'!C16 -> -23.62 | D18: ='Consol. Historical FS'!D16 -> 1949.81 | E18: ='Consol. Historical FS'!E16 -> 3072.05 | F18: ='Consol. Historical FS'!F16 -> 1946.72 | G18: ='Consol. Historical FS'!G16 -> 2256.4 | H18: =Scenarios!K198 -> 2721.84 | I18: =Scenarios!L198 -> 3380.06
B19: EBITDA | C19: =ROUND(C14-SUM(C16:C18),2) -> 8698.68 | D19: =ROUND(D14-SUM(D16:D18),2) -> 9524.44 | E19: =ROUND(E14-SUM(E16:E18),2) -> 10947.13 | F19: =ROUND(F14-SUM(F16:F18),2) -> 15751.1 | G19: =ROUND(G14-SUM(G16:G18),2) -> 18140.52 | H19: =ROUND(H14-SUM(H16:H18),2) -> 22681.96 | I19: =ROUND(I14-SUM(I16:I18),2) -> 28214.11
B20: EBITDA Margin | C20: =ROUND(C19/C9,3) -> 0.693 | D20: =ROUND(D19/D9,3) -> 0.556 | E20: =ROUND(E19/E9,3) -> 0.525 | F20: =ROUND(F19/F9,3) -> 0.59 | G20: =ROUND(G19/G9,3) -> 0.595 | H20: =ROUND(H19/H9,3) -> 0.6 | I20: =ROUND(I19/I9,3) -> 0.601
B21: Depreciation and Amortisation Expense | C21: ='Consol. Historical FS'!C18 -> 2107.34 | D21: ='Consol. Historical FS'!D18 -> 3099.3 | E21: ='Consol. Historical FS'!E18 -> 3423.24 | F21: ='Consol. Historical FS'!F18 -> 3888.46 | G21: ='Consol. Historical FS'!G18 -> 4378.93 | H21: =Scenarios!K427 -> 5229.0037 | I21: =Scenarios!L427 -> 5925.2319
B22: EBIT | C22: =ROUND(C19-C21,2) -> 6591.34 | D22: =ROUND(D19-D21,2) -> 6425.14 | E22: =ROUND(E19-E21,2) -> 7523.89 | F22: =ROUND(F19-F21,2) -> 11862.64 | G22: =ROUND(G19-G21,2) -> 13761.59 | H22: =ROUND(H19-H21,2) -> 17452.96 | I22: =ROUND(I19-I21,2) -> 22288.88
B23: Finance Costs | C23: ='Consol. Historical FS'!C20 -> 2255.29 | D23: ='Consol. Historical FS'!D20 -> 2543.92 | E23: ='Consol. Historical FS'!E20 -> 2362.64 | F23: ='Consol. Historical FS'!F20 -> 2732.94 | G23: ='Consol. Historical FS'!G20 -> 2531.82 | H23: =Scenarios!K418 -> 3063.5022 | I23: =Scenarios!L418 -> 3706.8377
B24: Other Income | C24: ='Consol. Historical FS'!C21 -> 1970.23 | D24: ='Consol. Historical FS'!D21 -> 2223.72 | E24: ='Consol. Historical FS'!E21 -> 1553.48 | F24: ='Consol. Historical FS'!F21 -> 1499.42 | G24: ='Consol. Historical FS'!G21 -> 1907.75 | H24: =Scenarios!K212 -> 2268.2 | I24: =Scenarios!L212 -> 2910.61
B25: Profit before share of Profit / (Loss) of Associate / Joint Ventures | C25: =ROUND(C22-C23+C24,2) -> 6306.28 | D25: =ROUND(D22-D23+D24,2) -> 6104.94 | E25: =ROUND(E22-E23+E24,2) -> 6714.73 | F25: =ROUND(F22-F23+F24,2) -> 10629.12 | G25: =ROUND(G22-G23+G24,2) -> 13137.52 | H25: =ROUND(H22-H23+H24,2) -> 16657.66 | I25: =ROUND(I22-I23+I24,2) -> 21492.65
B26: Share of Profit / (Loss) from Associate /Joint Ventures (net of tax) | C26: ='Consol. Historical FS'!C23 -> -14.27 | D26: ='Consol. Historical FS'!D23 -> 17.39 | E26: ='Consol. Historical FS'!E23 -> 47.78 | F26: ='Consol. Historical FS'!F23 -> -161.69 | G26: ='Consol. Historical FS'!G23 -> 141.56 | H26: =Scenarios!K220 -> 0 | I26: =Scenarios!L220 -> 0
B27: Profit before Exceptional Items and Tax | C27: =ROUND(SUM(C25:C26),2) -> 6292.01 | D27: =ROUND(SUM(D25:D26),2) -> 6122.33 | E27: =ROUND(SUM(E25:E26),2) -> 6762.51 | F27: =ROUND(SUM(F25:F26),2) -> 10467.43 | G27: =ROUND(SUM(G25:G26),2) -> 13279.08 | H27: =ROUND(SUM(H25:H26),2) -> 16657.66 | I27: =ROUND(SUM(I25:I26),2) -> 21492.65
B28: Exceptional Items | C28: ='Consol. Historical FS'!C25 -> 0 | D28: ='Consol. Historical FS'!D25 -> -405.19 | E28: ='Consol. Historical FS'!E25 -> -1273.38 | F28: ='Consol. Historical FS'!F25 -> -373.7 | G28: ='Consol. Historical FS'!G25 -> -249.46 | H28: =Scenarios!K228 -> -37.8 | I28: =Scenarios!L228 -> -46.95
B29: Profit before Tax | C29: =ROUND(SUM(C27:C28),2) -> 6292.01 | D29: =ROUND(SUM(D27:D28),2) -> 5717.14 | E29: =ROUND(SUM(E27:E28),2) -> 5489.13 | F29: =ROUND(SUM(F27:F28),2) -> 10093.73 | G29: =ROUND(SUM(G27:G28),2) -> 13029.62 | H29: =ROUND(SUM(H27:H28),2) -> 16619.86 | I29: =ROUND(SUM(I27:I28),2) -> 21445.7
B30: Tax | C30: ='Consol. Historical FS'!C27+'Consol. Historical FS'!C28+'Consol. Historical FS'!C29 -> 1243.27 | D30: ='Consol. Historical FS'!D27+'Consol. Historical FS'!D28+'Consol. Historical FS'!D29 -> 763.96 | E30: ='Consol. Historical FS'!E27+'Consol. Historical FS'!E28+'Consol. Historical FS'!E29 -> 96.38 | F30: ='Consol. Historical FS'!F27+'Consol. Historical FS'!F28+'Consol. Historical FS'!F29 -> 1989.74 | G30: ='Consol. Historical FS'!G27+'Consol. Historical FS'!G28+'Consol. Historical FS'!G29 -> 1968.36 | H30: =ROUND(H29*Scenarios!K252,2) -> 2659.18 | I30: =ROUND(I29*Scenarios!L252,2) -> 3431.31
B31: Tax Burden | C31: =ROUND(C30/C29,3) -> 0.198 | D31: =ROUND(D30/D29,3) -> 0.134 | E31: =ROUND(E30/E29,3) -> 0.018 | F31: =ROUND(F30/F29,3) -> 0.197 | G31: =ROUND(G30/G29,3) -> 0.151 | H31: =ROUND(H30/H29,3) -> 0.16 | I31: =ROUND(I30/I29,3) -> 0.16
B32: Net profit from continuing operations | C32: =ROUND(C29-C30,2) -> 5048.74 | D32: =ROUND(D29-D30,2) -> 4953.18 | E32: =ROUND(E29-E30,2) -> 5392.75 | F32: =ROUND(F29-F30,2) -> 8103.99 | G32: =ROUND(G29-G30,2) -> 11061.26 | H32: =ROUND(H29-H30,2) -> 13960.68 | I32: =ROUND(I29-I30,2) -> 18014.39
B33: Profit before tax from discontinued operations | C33: ='Consol. Historical FS'!C31 -> 0 | D33: ='Consol. Historical FS'!D31 -> 0 | E33: ='Consol. Historical FS'!E31 -> 0 | F33: ='Consol. Historical FS'!F31 -> 0 | G33: ='Consol. Historical FS'!G31 -> 0 | H33: =Scenarios!K236 -> 0 | I33: =Scenarios!L236 -> 0
B34: Tax income / (expense) of discontinued operations | C34: ='Consol. Historical FS'!C32 -> 0 | D34: ='Consol. Historical FS'!D32 -> 0 | E34: ='Consol. Historical FS'!E32 -> 0 | F34: ='Consol. Historical FS'!F32 -> 0 | G34: ='Consol. Historical FS'!G32 -> 0 | H34: =Scenarios!K244 -> 0 | I34: =Scenarios!L244 -> 0
B35: Net profit from discontinuing operations | C35: =ROUND(SUM(C33:C34),2) -> 0 | D35: =ROUND(SUM(D33:D34),2) -> 0 | E35: =ROUND(SUM(E33:E34),2) -> 0 | F35: =ROUND(SUM(F33:F34),2) -> 0 | G35: =ROUND(SUM(G33:G34),2) -> 0 | H35: =ROUND(SUM(H33:H34),2) -> 0 | I35: =ROUND(SUM(I33:I34),2) -> 0
B36: Net Profit | C36: =ROUND(SUM(C32,C35),2) -> 5048.74 | D36: =ROUND(SUM(D32,D35),2) -> 4953.18 | E36: =ROUND(SUM(E32,E35),2) -> 5392.75 | F36: =ROUND(SUM(F32,F35),2) -> 8103.99 | G36: =ROUND(SUM(G32,G35),2) -> 11061.26 | H36: =ROUND(SUM(H32,H35),2) -> 13960.68 | I36: =ROUND(SUM(I32,I35),2) -> 18014.39
B37: Net Profit Margin | C37: =ROUND(C36/C9,3) -> 0.402 | D37: =ROUND(D36/D9,3) -> 0.289 | E37: =ROUND(E36/E9,3) -> 0.259 | F37: =ROUND(F36/F9,3) -> 0.303 | G37: =ROUND(G36/G9,3) -> 0.363 | H37: =ROUND(H36/H9,3) -> 0.369 | I37: =ROUND(I36/I9,3) -> 0.384
B38: Net Profit attributable to:
B39: Owners of the company | C39: ='Consol. Historical FS'!C36 -> 4994.3 | D39: ='Consol. Historical FS'!D36 -> 4886.03 | E39: ='Consol. Historical FS'!E36 -> 5310.18 | F39: ='Consol. Historical FS'!F36 -> 8110.64 | G39: ='Consol. Historical FS'!G36 -> 11092.31 | H39: =ROUND(H36*Scenarios!K256,2) -> 13999.87 | I39: =ROUND(I36*Scenarios!L256,2) -> 18064.96
B40: Non-Controlling Interest | C40: ='Consol. Historical FS'!C37 -> 54.44 | D40: ='Consol. Historical FS'!D37 -> 67.15 | E40: ='Consol. Historical FS'!E37 -> 82.57 | F40: ='Consol. Historical FS'!F37 -> -6.65 | G40: ='Consol. Historical FS'!G37 -> -31.05 | H40: =ROUND(H36*Scenarios!K259,2) -> -39.19 | I40: =ROUND(I36*Scenarios!L259,2) -> -50.57
A42: # | B42: Balance Sheet
B44: ASSETS
B45: Non-current Assets
B46: Property, Plant and Equipment | C46: ='Consol. Historical FS'!C43 -> 36791.51 | D46: ='Consol. Historical FS'!D43 -> 41488.7 | E46: ='Consol. Historical FS'!E43 -> 48414 | F46: ='Consol. Historical FS'!F43 -> 51803.83 | G46: ='Consol. Historical FS'!G43 -> 62394.43 | H46: =G46/Scenarios!J$426*Scenarios!K$426 -> 74595.961 | I46: =H46/Scenarios!K$426*Scenarios!L$426 -> 84528.219
B47: Right of Use Assets | C47: ='Consol. Historical FS'!C44 -> 1775.95 | D47: ='Consol. Historical FS'!D44 -> 2772.25 | E47: ='Consol. Historical FS'!E44 -> 3541.9 | F47: ='Consol. Historical FS'!F44 -> 3809.11 | G47: ='Consol. Historical FS'!G44 -> 6177.54 | H47: =G47/Scenarios!J$426*Scenarios!K$426 -> 7385.5877 | I47: =H47/Scenarios!K$426*Scenarios!L$426 -> 8368.9595
B48: Capital work-in-progress | C48: ='Consol. Historical FS'!C45 -> 3697.13 | D48: ='Consol. Historical FS'!D45 -> 4022.9 | E48: ='Consol. Historical FS'!E45 -> 6814.03 | F48: ='Consol. Historical FS'!F45 -> 10936.09 | G48: ='Consol. Historical FS'!G45 -> 11592.19 | H48: =Scenarios!K429 -> 7454.473 | I48: =Scenarios!L429 -> 9318.0912
B49: Investment Property | C49: ='Consol. Historical FS'!C46 -> 0 | D49: ='Consol. Historical FS'!D46 -> 0 | E49: ='Consol. Historical FS'!E46 -> 2473.38 | F49: ='Consol. Historical FS'!F46 -> 1345.3 | G49: ='Consol. Historical FS'!G46 -> 1459.16 | H49: =G49/Scenarios!J$426*Scenarios!K$426 -> 1744.5058 | I49: =H49/Scenarios!K$426*Scenarios!L$426 -> 1976.7822
B50: Goodwill | C50: ='Consol. Historical FS'!C47 -> 4036.43 | D50: ='Consol. Historical FS'!D47 -> 6711.43 | E50: ='Consol. Historical FS'!E47 -> 6963.4 | F50: ='Consol. Historical FS'!F47 -> 6906.93 | G50: ='Consol. Historical FS'!G47 -> 7093.59 | H50: =Scenarios!K263 -> 7093.59 | I50: =Scenarios!L263 -> 7093.59
B51: Other Intangible Assets | C51: ='Consol. Historical FS'!C48 -> 5533.03 | D51: ='Consol. Historical FS'!D48 -> 11580.54 | E51: ='Consol. Historical FS'!E48 -> 11445.51 | F51: ='Consol. Historical FS'!F48 -> 11282.64 | G51: ='Consol. Historical FS'!G48 -> 12491.6 | H51: =Scenarios!K264 -> 113.91 | I51: =Scenarios!L264 -> 113.91
B52: Intangible Assets under Development | C52: ='Consol. Historical FS'!C49 -> 0 | D52: ='Consol. Historical FS'!D49 -> 0 | E52: ='Consol. Historical FS'!E49 -> 0 | F52: ='Consol. Historical FS'!F49 -> 0 | G52: ='Consol. Historical FS'!G49 -> 113.91 | H52: =Scenarios!K264 -> 113.91 | I52: =Scenarios!L264 -> 113.91
B53: Investments accounted for using the equity method | C53: ='Consol. Historical FS'!C50 -> 649.53 | D53: ='Consol. Historical FS'!D50 -> 1189.85 | E53: ='Consol. Historical FS'!E50 -> 2498.38 | F53: ='Consol. Historical FS'!F50 -> 2707.26 | G53: ='Consol. Historical FS'!G50 -> 3082.64 | H53: =Scenarios!K265 -> 3082.64 | I53: =Scenarios!L265 -> 3082.64
B54: Financial assets
B55: a) Other Investments | C55: ='Consol. Historical FS'!C52 -> 447.86 | D55: ='Consol. Historical FS'!D52 -> 1923.1 | E55: ='Consol. Historical FS'!E52 -> 1059.47 | F55: ='Consol. Historical FS'!F52 -> 919.61 | G55: ='Consol. Historical FS'!G52 -> 824.93 | H55: =Scenarios!K266 -> 824.93 | I55: =Scenarios!L266 -> 824.93
B56: b) Other Financial Assets | C56: ='Consol. Historical FS'!C53 -> 6086.53 | D56: ='Consol. Historical FS'!D53 -> 8251.44 | E56: ='Consol. Historical FS'!E53 -> 7709.6 | F56: ='Consol. Historical FS'!F53 -> 4750.7 | G56: ='Consol. Historical FS'!G53 -> 5685.33 | H56: =Scenarios!K267 -> 5685.33 | I56: =Scenarios!L267 -> 5685.33
B57: Deferred Tax Assets (Net) | C57: ='Consol. Historical FS'!C54 -> 881.73 | D57: ='Consol. Historical FS'!D54 -> 1357.83 | E57: ='Consol. Historical FS'!E54 -> 2199.9 | F57: ='Consol. Historical FS'!F54 -> 1918.67 | G57: ='Consol. Historical FS'!G54 -> 1889.58 | H57: =Scenarios!K268 -> 1889.58 | I57: =Scenarios!L268 -> 1889.58
B58: Income Tax Asset (Net) | C58: ='Consol. Historical FS'!C55 -> 0 | D58: ='Consol. Historical FS'!D55 -> 0 | E58: ='Consol. Historical FS'!E55 -> 0 | F58: ='Consol. Historical FS'!F55 -> 0 | G58: ='Consol. Historical FS'!G55 -> 0 | H58: =Scenarios!K269 -> 0 | I58: =Scenarios!L269 -> 0
B59: Other Non-Current Assets | C59: ='Consol. Historical FS'!C56 -> 2593.44 | D59: ='Consol. Historical FS'!D56 -> 2299.36 | E59: ='Consol. Historical FS'!E56 -> 4338.04 | F59: ='Consol. Historical FS'!F56 -> 5065.37 | G59: ='Consol. Historical FS'!G56 -> 3583.21 | H59: =Scenarios!K270 -> 3583.21 | I59: =Scenarios!L270 -> 3583.21
B60: Total Non-current Assets | C60: =SUM(C46:C59) -> 62493.14 | D60: =SUM(D46:D59) -> 81597.4 | E60: =SUM(E46:E59) -> 97457.61 | F60: =SUM(F46:F59) -> 101445.51 | G60: =SUM(G46:G59) -> 116388.11 | H60: =SUM(H46:H59) -> 113567.63 | I60: =SUM(I46:I59) -> 126579.15
B62: Current assets
B63: Inventories | C63: ='Consol. Historical FS'!C60 -> 991.85 | D63: ='Consol. Historical FS'!D60 -> 395.64 | E63: ='Consol. Historical FS'!E60 -> 451.97 | F63: ='Consol. Historical FS'!F60 -> 437.51 | G63: ='Consol. Historical FS'!G60 -> 521.8 | H63: =ROUND(SUM(H13:H13)/(365/Scenarios!K305),2) -> 631.26 | I63: =ROUND(SUM(I13:I13)/(365/Scenarios!L305),2) -> 775.05
B64: Financial assets
B65: a) Investments | C65: ='Consol. Historical FS'!C62 -> 1138.76 | D65: ='Consol. Historical FS'!D62 -> 47.79 | E65: ='Consol. Historical FS'!E62 -> 4028.69 | F65: ='Consol. Historical FS'!F62 -> 661.79 | G65: ='Consol. Historical FS'!G62 -> 751.88 | H65: =Scenarios!K275 -> 1251.88 | I65: =Scenarios!L275 -> 1751.88
B66: b) Trade receivables | C66: ='Consol. Historical FS'!C63 -> 2385.9 | D66: ='Consol. Historical FS'!D63 -> 2221.9 | E66: ='Consol. Historical FS'!E63 -> 3241.67 | F66: ='Consol. Historical FS'!F63 -> 3666.94 | G66: ='Consol. Historical FS'!G63 -> 4432.36 | H66: =ROUND(H9/(365/Scenarios!K311),2) -> 4971.39 | I66: =ROUND(I9/(365/Scenarios!L311),2) -> 6045.01
B67: c) Cash and Cash Equivalents | C67: ='Consol. Historical FS'!C64 -> 4198.04 | D67: ='Consol. Historical FS'!D64 -> 8653.02 | E67: ='Consol. Historical FS'!E64 -> 931.99 | F67: ='Consol. Historical FS'!F64 -> 1575.73 | G67: ='Consol. Historical FS'!G64 -> 3406.32 | H67: =H201 -> 11346.39 | I67: =I201 -> 20842.202
B68: d) Bank Balances other than Cash and Cash Equivalents | C68: ='Consol. Historical FS'!C65 -> 502.74 | D68: ='Consol. Historical FS'!D65 -> 2014.39 | E68: ='Consol. Historical FS'!E65 -> 3316.79 | F68: ='Consol. Historical FS'!F65 -> 6056.15 | G68: ='Consol. Historical FS'!G65 -> 3199.65 | H68: =G68 -> 3199.65 | I68: =H68 -> 3199.65
B69: e) Loans | C69: ='Consol. Historical FS'!C66 -> 1082.81 | D69: ='Consol. Historical FS'!D66 -> 1302.42 | E69: ='Consol. Historical FS'!E66 -> 408.1 | F69: ='Consol. Historical FS'!F66 -> 269.01 | G69: ='Consol. Historical FS'!G66 -> 173.17 | H69: =Scenarios!K276 -> 173.17 | I69: =Scenarios!L276 -> 173.17
B70: f) Derivative Instruments | C70: ='Consol. Historical FS'!C67 -> 0 | D70: ='Consol. Historical FS'!D67 -> 0 | E70: ='Consol. Historical FS'!E67 -> 0 | F70: ='Consol. Historical FS'!F67 -> 0 | G70: ='Consol. Historical FS'!G67 -> 0 | H70: =Scenarios!K277 -> 0 | I70: =Scenarios!L277 -> 0
B71: g) Other Financial Assets | C71: ='Consol. Historical FS'!C68 -> 1162.48 | D71: ='Consol. Historical FS'!D68 -> 824.69 | E71: ='Consol. Historical FS'!E68 -> 1962.97 | F71: ='Consol. Historical FS'!F68 -> 3441.08 | G71: ='Consol. Historical FS'!G68 -> 4471.8 | H71: =Scenarios!K278 -> 4471.8 | I71: =Scenarios!L278 -> 4471.8
B72: Other Current Assets | C72: ='Consol. Historical FS'!C69 -> 1013.2 | D72: ='Consol. Historical FS'!D69 -> 730.09 | E72: ='Consol. Historical FS'!E69 -> 1164.08 | F72: ='Consol. Historical FS'!F69 -> 1177.4 | G72: ='Consol. Historical FS'!G69 -> 1800.39 | H72: =Scenarios!K279 -> 1800.39 | I72: =Scenarios!L279 -> 1800.39
B73: Current Tax Assets | C73: ='Consol. Historical FS'!C70 -> 0 | D73: ='Consol. Historical FS'!D70 -> 0 | E73: ='Consol. Historical FS'!E70 -> 0 | F73: ='Consol. Historical FS'!F70 -> 0 | G73: ='Consol. Historical FS'!G70 -> 0 | H73: =Scenarios!K280 -> 0 | I73: =Scenarios!L280 -> 0
B74: Total Current Assets | C74: =SUM(C63:C73) -> 12475.78 | D74: =SUM(D63:D73) -> 16189.94 | E74: =SUM(E63:E73) -> 15506.26 | F74: =SUM(F63:F73) -> 17285.61 | G74: =SUM(G63:G73) -> 18757.37 | H74: =SUM(H63:H73) -> 27845.93 | I74: =SUM(I63:I73) -> 39059.152
B75: Assets classified as held for sale and discontinued operations | C75: ='Consol. Historical FS'!C72 -> 354.86 | D75: ='Consol. Historical FS'!D72 -> 1898.48 | E75: ='Consol. Historical FS'!E72 -> 1941.26 | F75: ='Consol. Historical FS'!F72 -> 186.75 | G75: ='Consol. Historical FS'!G72 -> 186.75 | H75: =Scenarios!K271 -> 186.75 | I75: =Scenarios!L271 -> 186.75
B76: Total Assets | C76: =SUM(C60,C74,C75) -> 75323.78 | D76: =SUM(D60,D74,D75) -> 99685.82 | E76: =SUM(E60,E74,E75) -> 114905.13 | F76: =SUM(F60,F74,F75) -> 118917.87 | G76: =SUM(G60,G74,G75) -> 135332.23 | H76: =SUM(H60,H74,H75) -> 141600.31 | I76: =SUM(I60,I74,I75) -> 165825.05
B78: EQUITY AND LIABILITIES
B79: Equity
B80: Equity Share Capital | C80: ='Consol. Historical FS'!C77 -> 406.35 | D80: ='Consol. Historical FS'!D77 -> 422.47 | E80: ='Consol. Historical FS'!E77 -> 432.03 | F80: ='Consol. Historical FS'!F77 -> 432.03 | G80: ='Consol. Historical FS'!G77 -> 432.03 | H80: =G80 -> 432.03 | I80: =H80 -> 432.03
B81: Other Equity | C81: ='Consol. Historical FS'!C78 -> 30221.91 | D81: ='Consol. Historical FS'!D78 -> 41565.75 | E81: ='Consol. Historical FS'!E78 -> 45151.55 | F81: ='Consol. Historical FS'!F78 -> 52512.74 | G81: ='Consol. Historical FS'!G78 -> 62003.36 | H81: =H76-H80-H83-H96-H111-H112 -> 59606.48 | I81: =I76-I80-I83-I96-I111-I112 -> 75510.353
B82: Equity Attributable to the Owners of the Company | C82: =SUM(C80:C81) -> 30628.26 | D82: =SUM(D80:D81) -> 41988.22 | E82: =SUM(E80:E81) -> 45583.58 | F82: =SUM(F80:F81) -> 52944.77 | G82: =SUM(G80:G81) -> 62435.39 | H82: =SUM(H80:H81) -> 60038.51 | I82: =SUM(I80:I81) -> 75942.383
B83: Non-Controlling Interests | C83: ='Consol. Historical FS'!C80 -> 1468.47 | D83: ='Consol. Historical FS'!D80 -> 392.77 | E83: ='Consol. Historical FS'!E80 -> 1338.51 | F83: ='Consol. Historical FS'!F80 -> 1598.23 | G83: ='Consol. Historical FS'!G80 -> 2537.95 | H83: =G83 -> 2537.95 | I83: =H83 -> 2537.95
B84: Total Equity | C84: =SUM(C82:C83) -> 32096.73 | D84: =SUM(D82:D83) -> 42380.99 | E84: =SUM(E82:E83) -> 46922.09 | F84: =SUM(F82:F83) -> 54543 | G84: =SUM(G82:G83) -> 64973.34 | H84: =SUM(H82:H83) -> 62576.46 | I84: =SUM(I82:I83) -> 78480.333
B86: Non-current Liabilities
B87: Financial Liabilities
B88: a) Borrowings | C88: ='Consol. Historical FS'!C85 -> 32935.53 | D88: ='Consol. Historical FS'!D85 -> 39691.48 | E88: ='Consol. Historical FS'!E85 -> 46516.94 | F88: ='Consol. Historical FS'!F85 -> 37662.93 | G88: ='Consol. Historical FS'!G85 -> 35830.68 | H88: ='3 Model Projected FS'!G88/Scenarios!J$413*Scenarios!K$413 -> 39413.748 | I88: ='3 Model Projected FS'!H88/Scenarios!K413*Scenarios!L413 -> 43355.123 | J88: =H19/((H88+H89+H100+H101)-H67) -> 0.48584096 | K88: =I19/((I88+I89+I100+I101)-I67) -> 0.62984406
B89: b) Lease Liabilities | C89: ='Consol. Historical FS'!C86 -> 572.33 | D89: ='Consol. Historical FS'!D86 -> 1983.78 | E89: ='Consol. Historical FS'!E86 -> 2681.74 | F89: ='Consol. Historical FS'!F86 -> 2953.28 | G89: ='Consol. Historical FS'!G86 -> 5389.61 | H89: ='3 Model Projected FS'!G89/Scenarios!J$413*Scenarios!K$413 -> 5928.571 | I89: ='3 Model Projected FS'!H89/Scenarios!K$413*Scenarios!L$413 -> 6521.4281
B90: c) Other Financial Liabilities | C90: ='Consol. Historical FS'!C87 -> 207.61 | D90: ='Consol. Historical FS'!D87 -> 227.56 | E90: ='Consol. Historical FS'!E87 -> 322.84 | F90: ='Consol. Historical FS'!F87 -> 360.11 | G90: ='Consol. Historical FS'!G87 -> 207.45 | H90: =Scenarios!K284 -> 2242.68 | I90: =Scenarios!L284 -> 2242.68
B91: d) Derivative Instruments | C91: ='Consol. Historical FS'!C88 -> 0 | D91: ='Consol. Historical FS'!D88 -> 0 | E91: ='Consol. Historical FS'!E88 -> 0 | F91: ='Consol. Historical FS'!F88 -> 0 | G91: ='Consol. Historical FS'!G88 -> 0 | H91: =Scenarios!K285 -> 0 | I91: =Scenarios!L285 -> 0
B92: Other Non-Current Liabilities | C92: ='Consol. Historical FS'!C89 -> 1065.79 | D92: ='Consol. Historical FS'!D89 -> 988.21 | E92: ='Consol. Historical FS'!E89 -> 1148.84 | F92: ='Consol. Historical FS'!F89 -> 1664.99 | G92: ='Consol. Historical FS'!G89 -> 2142.54 | H92: =Scenarios!K286 -> 2142.54 | I92: =Scenarios!L286 -> 2142.54
B93: Provisions | C93: ='Consol. Historical FS'!C90 -> 26.68 | D93: ='Consol. Historical FS'!D90 -> 34.23 | E93: ='Consol. Historical FS'!E90 -> 1201.75 | F93: ='Consol. Historical FS'!F90 -> 1100.75 | G93: ='Consol. Historical FS'!G90 -> 1149.36 | H93: =Scenarios!K287 -> 1149.36 | I93: =Scenarios!L287 -> 1149.36
B94: Government Grants | C94: ='Consol. Historical FS'!C91 -> 0 | D94: ='Consol. Historical FS'!D91 -> 0 | E94: ='Consol. Historical FS'!E91 -> 0 | F94: ='Consol. Historical FS'!F91 -> 0 | G94: ='Consol. Historical FS'!G91 -> 0 | H94: =Scenarios!K288 -> 0 | I94: =Scenarios!L288 -> 0
B95: Deferred Tax Liabilities (Net) | C95: ='Consol. Historical FS'!C92 -> 1203.16 | D95: ='Consol. Historical FS'!D92 -> 3010.86 | E95: ='Consol. Historical FS'!E92 -> 3186.37 | F95: ='Consol. Historical FS'!F92 -> 4169.87 | G95: ='Consol. Historical FS'!G92 -> 4653.26 | H95: =Scenarios!K289 -> 4653.26 | I95: =Scenarios!L289 -> 4653.26
B96: Total Non-current Liabilities | C96: =SUM(C88:C95) -> 36011.1 | D96: =SUM(D88:D95) -> 45936.12 | E96: =SUM(E88:E95) -> 55058.48 | F96: =SUM(F88:F95) -> 47911.93 | G96: =SUM(G88:G95) -> 49372.9 | H96: =SUM(H88:H95) -> 55530.159 | I96: =SUM(I88:I95) -> 60064.391
B98: Current Liabilities
B99: Financial liabilities
B100: a) Borrowings | C100: ='Consol. Historical FS'!C97 -> 400 | D100: ='Consol. Historical FS'!D97 -> 5761.56 | E100: ='Consol. Historical FS'!E97 -> 3302.37 | F100: ='Consol. Historical FS'!F97 -> 8616.3 | G100: ='Consol. Historical FS'!G97 -> 9979.35 | H100: =G100/Scenarios!J$407*Scenarios!K$407 -> 12374.394 | I100: =H100/Scenarios!K$407*Scenarios!L$407 -> 15368.997
B101: b) Lease Liabilities | C101: ='Consol. Historical FS'!C98 -> 32.26 | D101: ='Consol. Historical FS'!D98 -> 32.16 | E101: ='Consol. Historical FS'!E98 -> 61.97 | F101: ='Consol. Historical FS'!F98 -> 71.2 | G101: ='Consol. Historical FS'!G98 -> 254.56 | H101: =G101/Scenarios!J$407*Scenarios!K$407 -> 315.6544 | I101: =H101/Scenarios!K$407*Scenarios!L$407 -> 392.04276
B102: c) Trade payables
B103: Total outstanding dues of Micro Enterprises and Small Enterprises | C103: ='Consol. Historical FS'!C100 -> 11.5 | D103: ='Consol. Historical FS'!D100 -> 41.86 | E103: ='Consol. Historical FS'!E100 -> 98.88 | F103: ='Consol. Historical FS'!F100 -> 152.5 | G103: ='Consol. Historical FS'!G100 -> 166.73 | H103: =ROUND(SUM(H13:H13)/(365/Scenarios!K318),2) -> 192.12 | I103: =ROUND(SUM(I13:I13)/(365/Scenarios!L318),2) -> 252.73
B104: Total outstanding dues of Creditors other than Micro Enterprises and Small Enterprises | C104: ='Consol. Historical FS'!C101 -> 1002.35 | D104: ='Consol. Historical FS'!D101 -> 1117.71 | E104: ='Consol. Historical FS'!E101 -> 1729.35 | F104: ='Consol. Historical FS'!F101 -> 1759.6 | G104: ='Consol. Historical FS'!G101 -> 2553.77 | H104: =ROUND(SUM(H13:H13)/(365/Scenarios!K324),2) -> 2579.94 | I104: =ROUND(SUM(I13:I13)/(365/Scenarios!L324),2) -> 3234.98
B105: d) Other Financial Liabilities | C105: ='Consol. Historical FS'!C102 -> 3260.08 | D105: ='Consol. Historical FS'!D102 -> 2253.75 | E105: ='Consol. Historical FS'!E102 -> 3319.88 | F105: ='Consol. Historical FS'!F102 -> 3756.8 | G105: ='Consol. Historical FS'!G102 -> 5359.74 | H105: =Scenarios!K293 -> 5359.74 | I105: =Scenarios!L293 -> 5359.74
B106: e) Derivative Instruments | C106: ='Consol. Historical FS'!C103 -> 0 | D106: ='Consol. Historical FS'!D103 -> 0 | E106: ='Consol. Historical FS'!E103 -> 0 | F106: ='Consol. Historical FS'!F103 -> 0 | G106: ='Consol. Historical FS'!G103 -> 0 | H106: =Scenarios!K294 -> 0 | I106: =Scenarios!L294 -> 0
B107: Other Current Liabilities | C107: ='Consol. Historical FS'!C104 -> 2261 | D107: ='Consol. Historical FS'!D104 -> 1654.87 | E107: ='Consol. Historical FS'!E104 -> 1814.19 | F107: ='Consol. Historical FS'!F104 -> 1832.45 | G107: ='Consol. Historical FS'!G104 -> 2242.68 | H107: =Scenarios!K295 -> 2242.68 | I107: =Scenarios!L295 -> 2242.68
B108: Provisions | C108: ='Consol. Historical FS'!C105 -> 95.73 | D108: ='Consol. Historical FS'!D105 -> 107.52 | E108: ='Consol. Historical FS'!E105 -> 548.03 | F108: ='Consol. Historical FS'!F105 -> 193.44 | G108: ='Consol. Historical FS'!G105 -> 236.77 | H108: =Scenarios!K296 -> 236.77 | I108: =Scenarios!L296 -> 236.77
B109: Government Grants | C109: ='Consol. Historical FS'!C106 -> 0 | D109: ='Consol. Historical FS'!D106 -> 0 | E109: ='Consol. Historical FS'!E106 -> 0 | F109: ='Consol. Historical FS'!F106 -> 0 | G109: ='Consol. Historical FS'!G106 -> 0 | H109: =Scenarios!K297 -> 0 | I109: =Scenarios!L297 -> 0
B110: Current Tax Liabilities (Net) | C110: ='Consol. Historical FS'!C107 -> 38.49 | D110: ='Consol. Historical FS'!D107 -> 93.92 | E110: ='Consol. Historical FS'!E107 -> 528.43 | F110: ='Consol. Historical FS'!F107 -> 33.1 | G110: ='Consol. Historical FS'!G107 -> 144.84 | H110: =Scenarios!K298 -> 144.84 | I110: =Scenarios!L298 -> 144.84
...

Sheet Financial Ratios
G1: =[2]Scenarios!L1 -> Currently Running: Base Case Scenario
B2: FINANCIAL RATIOS
C3: ='3 Model Projected FS'!E3 -> FY23A | D3: ='3 Model Projected FS'!F3 -> FY24A | E3: ='3 Model Projected FS'!G3 -> FY25A | F3: FY26E | G3: FY27E
B4: Key Ratios
B5: Revenue Growth | C5: =ROUND('3 Model Projected FS'!E9/'3 Model Projected FS'!D9-1,3) -> 0.218 | D5: =ROUND('3 Model Projected FS'!F9/'3 Model Projected FS'!E9-1,3) -> 0.281 | E5: =ROUND('3 Model Projected FS'!G9/'3 Model Projected FS'!F9-1,3) -> 0.141 | F5: =ROUND('3 Model Projected FS'!H9/'3 Model Projected FS'!G9-1,3) -> 0.24 | G5: =ROUND('3 Model Projected FS'!I9/'3 Model Projected FS'!H9-1,3) -> 0.242
B6: Gross Profit Growth | C6: =ROUND('3 Model Projected FS'!E14/'3 Model Projected FS'!D14-1,3) -> 0.24 | D6: =ROUND('3 Model Projected FS'!F14/'3 Model Projected FS'!E14-1,3) -> 0.289 | E6: =ROUND('3 Model Projected FS'!G14/'3 Model Projected FS'!F14-1,3) -> 0.143 | F6: =ROUND('3 Model Projected FS'!H14/'3 Model Projected FS'!G14-1,3) -> 0.24 | G6: =ROUND('3 Model Projected FS'!I14/'3 Model Projected FS'!H14-1,3) -> 0.247
B7: EBITDA Growth | C7: =ROUND('3 Model Projected FS'!E19/'3 Model Projected FS'!D19-1,3) -> 0.149 | D7: =ROUND('3 Model Projected FS'!F19/'3 Model Projected FS'!E19-1,3) -> 0.439 | E7: =ROUND('3 Model Projected FS'!G19/'3 Model Projected FS'!F19-1,3) -> 0.152 | F7: =ROUND('3 Model Projected FS'!H19/'3 Model Projected FS'!G19-1,3) -> 0.25 | G7: =ROUND('3 Model Projected FS'!I19/'3 Model Projected FS'!H19-1,3) -> 0.244
B8: Net Profit Growth | C8: =ROUND('3 Model Projected FS'!E36/'3 Model Projected FS'!D36-1,3) -> 0.089 | D8: =ROUND('3 Model Projected FS'!F36/'3 Model Projected FS'!E36-1,3) -> 0.503 | E8: =ROUND('3 Model Projected FS'!G36/'3 Model Projected FS'!F36-1,3) -> 0.365 | F8: =ROUND('3 Model Projected FS'!H36/'3 Model Projected FS'!G36-1,3) -> 0.262 | G8: =ROUND('3 Model Projected FS'!I36/'3 Model Projected FS'!H36-1,3) -> 0.29
B9: RoCE | C9: =Graphs!D23 -> 0.082 | D9: =Graphs!E23 -> 0.12 | E9: =Graphs!F23 -> 0.13 | F9: =Graphs!G23 -> 0.155 | G9: =Graphs!H23 -> 0.177
B10: RoE | C10: =Graphs!D24 -> 0.121 | D10: =Graphs!E24 -> 0.165 | E10: =Graphs!F24 -> 0.192 | F10: =Graphs!G24 -> 0.229 | G10: =Graphs!H24 -> 0.266
B11: Dividend Payout Ratio | C11: =ROUND(Scenarios!H393/'3 Model Projected FS'!E39,3) -> 0.203 | D11: =ROUND(Scenarios!I393/'3 Model Projected FS'!F39,3) -> 0.16 | E11: =ROUND(Scenarios!J393/'3 Model Projected FS'!G39,3) -> 0.14 | F11: =ROUND(Scenarios!K393/'3 Model Projected FS'!H39,3) -> 0.15 | G11: =ROUND(Scenarios!L393/'3 Model Projected FS'!I39,3) -> 0.155
B12: EPS (₹) | C12: =Scenarios!H395 -> 24.58 | D12: =Scenarios!I395 -> 37.55 | E12: =Scenarios!J395 -> 51.35 | F12: =Scenarios!K395 -> 64.81 | G12: =Scenarios!L395 -> 83.63
B13: Gross Fixed Asset Turnover (x) | C13: =Graphs!D10 -> 0.5 | D13: =Graphs!E10 -> 0.3 | E13: =Graphs!F10 -> 0.3 | F13: =Graphs!G10 -> 0.4 | G13: =Graphs!H10 -> 0.4
B14: Net Working Capital Days | C14: =C15+C16-C17 -> -22 | D14: =D15+D16-D17 -> -25 | E14: =E15+E16-E17 -> -34 | F14: =F15+F16-F17 -> -30 | G14: =G15+G16-G17 -> -34
B15: Debtor Days | C15: =Graphs!D17 -> 48 | D15: =Graphs!E17 -> 47 | E15: =Graphs!F17 -> 49 | F15: =Graphs!G17 -> 48 | G15: =Graphs!H17 -> 47
B16: Inventory Days | C16: =Graphs!D21 -> 27 | D16: =Graphs!E21 -> 23 | E16: =Graphs!F21 -> 22 | F16: =Graphs!G21 -> 23 | G16: =Graphs!H21 -> 23
B17: Payable Days | C17: =Graphs!D19 -> 97 | D17: =Graphs!E19 -> 95 | E17: =Graphs!F19 -> 105 | F17: =Graphs!G19 -> 101 | G17: =Graphs!H19 -> 104
B18: Net Debt to Equity (x) | C18: =ROUND((SUM('3 Model Projected FS'!E88,'3 Model Projected FS'!E100)-SUM('3 Model Projected FS'!E67:E68))/'3 Model Projected FS'!E82,1) -> 1 | D18: =ROUND((SUM('3 Model Projected FS'!F88,'3 Model Projected FS'!F100)-SUM('3 Model Projected FS'!F67:F68))/'3 Model Projected FS'!F82,1) -> 0.7 | E18: =ROUND((SUM('3 Model Projected FS'!G88,'3 Model Projected FS'!G100)-SUM('3 Model Projected FS'!G67:G68))/'3 Model Projected FS'!G82,1) -> 0.6 | F18: =ROUND((SUM('3 Model Projected FS'!H88,'3 Model Projected FS'!H100)-SUM('3 Model Projected FS'!H67:H68))/'3 Model Projected FS'!H82,1) -> 0.6 | G18: =ROUND((SUM('3 Model Projected FS'!I88,'3 Model Projected FS'!I100)-SUM('3 Model Projected FS'!I67:I68))/'3 Model Projected FS'!I82,1) -> 0.5
B19: Interest Coverage (x) | C19: =ROUND('3 Model Projected FS'!E22/'3 Model Projected FS'!E23,1) -> 3.2 | D19: =ROUND('3 Model Projected FS'!F22/'3 Model Projected FS'!F23,1) -> 4.3 | E19: =ROUND('3 Model Projected FS'!G22/'3 Model Projected FS'!G23,1) -> 5.4 | F19: =ROUND('3 Model Projected FS'!H22/'3 Model Projected FS'!H23,1) -> 5.7 | G19: =ROUND('3 Model Projected FS'!I22/'3 Model Projected FS'!I23,1) -> 6
B20: CFO / EBITDA | C20: =ROUND('3 Model Projected FS'!E156/'3 Model Projected FS'!E19,3) -> 1.09 | D20: =ROUND('3 Model Projected FS'!F156/'3 Model Projected FS'!F19,3) -> 0.953 | E20: =ROUND('3 Model Projected FS'!G156/'3 Model Projected FS'!G19,3) -> 0.95 | F20: =ROUND('3 Model Projected FS'!H156/'3 Model Projected FS'!H19,3) -> 0.926 | G20: =ROUND('3 Model Projected FS'!I156/'3 Model Projected FS'!I19,3) -> 0.937

Sheet Summary_3 Model Projected FS
I1: =[2]Scenarios!L1 -> Currently Running: Base Case Scenario
B2: CONSOLIDATED - SUMMARY PROJECTED FINANCIAL STATEMENTS
B3: ₹'cr, unless otherwise stated | C3: =[2]Consol!C3 -> #VALUE! | D3: =[2]Consol!D3 -> #VALUE! | E3: =[2]Consol!E3 -> #VALUE! | F3: FY24A | G3: FY25A | H3: FY26E | I3: FY27E
A5: # | B5: Profit & Loss Statement
B7: Total Revenue | C7: ='3 Model Projected FS'!C9 -> 12549.6 | D7: ='3 Model Projected FS'!D9 -> 17118.79 | E7: ='3 Model Projected FS'!E9 -> 20851.91 | F7: ='3 Model Projected FS'!F9 -> 26710.56 | G7: ='3 Model Projected FS'!G9 -> 30475.33 | H7: ='3 Model Projected FS'!H9 -> 37803.28 | I7: ='3 Model Projected FS'!I9 -> 46945.27
B8: Revenue Growth YoY | D8: =ROUND(D7/C7-1,3) -> 0.364 | E8: =ROUND(E7/D7-1,3) -> 0.218 | F8: =ROUND(F7/E7-1,3) -> 0.281 | G8: =ROUND(G7/F7-1,3) -> 0.141 | H8: =ROUND(H7/G7-1,3) -> 0.24 | I8: =ROUND(I7/H7-1,3) -> 0.242
B9: Cost of Goods Sold | C9: =ROUND(SUM('3 Model Projected FS'!C11:C13),2) -> 3259.49 | D9: =ROUND(SUM('3 Model Projected FS'!D11:D13),2) -> 4865.11 | E9: =ROUND(SUM('3 Model Projected FS'!E11:E13),2) -> 5654.56 | F9: =ROUND(SUM('3 Model Projected FS'!F11:F13),2) -> 7116.34 | G9: =ROUND(SUM('3 Model Projected FS'!G11:G13),2) -> 8069.75 | H9: =ROUND(SUM('3 Model Projected FS'!H11:H13),2) -> 10017.87 | I9: =ROUND(SUM('3 Model Projected FS'!I11:I13),2) -> 12299.66
B10: Gross Profit | C10: =ROUND(C7-SUM(C9:C9),2) -> 9290.11 | D10: =ROUND(D7-SUM(D9:D9),2) -> 12253.68 | E10: =ROUND(E7-SUM(E9:E9),2) -> 15197.35 | F10: =ROUND(F7-SUM(F9:F9),2) -> 19594.22 | G10: =ROUND(G7-SUM(G9:G9),2) -> 22405.58 | H10: =ROUND(H7-SUM(H9:H9),2) -> 27785.41 | I10: =ROUND(I7-SUM(I9:I9),2) -> 34645.61
B11: Gross Profit Margin | C11: =ROUND(C10/C7,3) -> 0.74 | D11: =ROUND(D10/D7,3) -> 0.716 | E11: =ROUND(E10/E7,3) -> 0.729 | F11: =ROUND(F10/F7,3) -> 0.734 | G11: =ROUND(G10/G7,3) -> 0.735 | H11: =ROUND(H10/H7,3) -> 0.735 | I11: =ROUND(I10/I7,3) -> 0.738
B12: Operating Expenses | C12: =ROUND(SUM('3 Model Projected FS'!C16,'3 Model Projected FS'!C18),2) -> 591.43 | D12: =ROUND(SUM('3 Model Projected FS'!D16,'3 Model Projected FS'!D18),2) -> 2729.24 | E12: =ROUND(SUM('3 Model Projected FS'!E16,'3 Model Projected FS'!E18),2) -> 4250.22 | F12: =ROUND(SUM('3 Model Projected FS'!F16,'3 Model Projected FS'!F18),2) -> 3843.12 | G12: =ROUND(SUM('3 Model Projected FS'!G16,'3 Model Projected FS'!G18),2) -> 4265.06 | H12: =ROUND(SUM('3 Model Projected FS'!H16,'3 Model Projected FS'!H18),2) -> 5103.45 | I12: =ROUND(SUM('3 Model Projected FS'!I16,'3 Model Projected FS'!I18),2) -> 6431.5
B13: Loss on fair valuation of Compulsorily Convertible Preference Shares | C13: ='3 Model Projected FS'!C17 -> 0 | D13: ='3 Model Projected FS'!D17 -> 0 | E13: ='3 Model Projected FS'!E17 -> 0 | F13: ='3 Model Projected FS'!F17 -> 0 | G13: ='3 Model Projected FS'!G17 -> 0 | H13: ='3 Model Projected FS'!H17 -> 0 | I13: ='3 Model Projected FS'!I17 -> 0
B14: EBITDA | C14: =ROUND(C10-SUM(C12:C13),2) -> 8698.68 | D14: =ROUND(D10-SUM(D12:D13),2) -> 9524.44 | E14: =ROUND(E10-SUM(E12:E13),2) -> 10947.13 | F14: =ROUND(F10-SUM(F12:F13),2) -> 15751.1 | G14: =ROUND(G10-SUM(G12:G13),2) -> 18140.52 | H14: =ROUND(H10-SUM(H12:H13),2) -> 22681.96 | I14: =ROUND(I10-SUM(I12:I13),2) -> 28214.11
B15: EBITDA Margin | C15: =ROUND(C14/C7,3) -> 0.693 | D15: =ROUND(D14/D7,3) -> 0.556 | E15: =ROUND(E14/E7,3) -> 0.525 | F15: =ROUND(F14/F7,3) -> 0.59 | G15: =ROUND(G14/G7,3) -> 0.595 | H15: =ROUND(H14/H7,3) -> 0.6 | I15: =ROUND(I14/I7,3) -> 0.601
B16: Depreciation and Amortisation Expense | C16: ='3 Model Projected FS'!C21 -> 2107.34 | D16: ='3 Model Projected FS'!D21 -> 3099.3 | E16: ='3 Model Projected FS'!E21 -> 3423.24 | F16: ='3 Model Projected FS'!F21 -> 3888.46 | G16: ='3 Model Projected FS'!G21 -> 4378.93 | H16: ='3 Model Projected FS'!H21 -> 5229.0037 | I16: ='3 Model Projected FS'!I21 -> 5925.2319
B17: EBIT | C17: =ROUND(C14-C16,2) -> 6591.34 | D17: =ROUND(D14-D16,2) -> 6425.14 | E17: =ROUND(E14-E16,2) -> 7523.89 | F17: =ROUND(F14-F16,2) -> 11862.64 | G17: =ROUND(G14-G16,2) -> 13761.59 | H17: =ROUND(H14-H16,2) -> 17452.96 | I17: =ROUND(I14-I16,2) -> 22288.88
B18: Finance Costs | C18: ='3 Model Projected FS'!C23 -> 2255.29 | D18: ='3 Model Projected FS'!D23 -> 2543.92 | E18: ='3 Model Projected FS'!E23 -> 2362.64 | F18: ='3 Model Projected FS'!F23 -> 2732.94 | G18: ='3 Model Projected FS'!G23 -> 2531.82 | H18: ='3 Model Projected FS'!H23 -> 3063.5022 | I18: ='3 Model Projected FS'!I23 -> 3706.8377
B19: Other Income | C19: ='3 Model Projected FS'!C24 -> 1970.23 | D19: ='3 Model Projected FS'!D24 -> 2223.72 | E19: ='3 Model Projected FS'!E24 -> 1553.48 | F19: ='3 Model Projected FS'!F24 -> 1499.42 | G19: ='3 Model Projected FS'!G24 -> 1907.75 | H19: ='3 Model Projected FS'!H24 -> 2268.2 | I19: ='3 Model Projected FS'!I24 -> 2910.61
B20: Profit before share of Profit / (Loss) of Associate / Joint Ventures | C20: =ROUND(C17-C18+C19,2) -> 6306.28 | D20: =ROUND(D17-D18+D19,2) -> 6104.94 | E20: =ROUND(E17-E18+E19,2) -> 6714.73 | F20: =ROUND(F17-F18+F19,2) -> 10629.12 | G20: =ROUND(G17-G18+G19,2) -> 13137.52 | H20: =ROUND(H17-H18+H19,2) -> 16657.66 | I20: =ROUND(I17-I18+I19,2) -> 21492.65
B21: Share of Profit / (Loss) from Associate /Joint Ventures (net of tax) | C21: ='3 Model Projected FS'!C26 -> -14.27 | D21: ='3 Model Projected FS'!D26 -> 17.39 | E21: ='3 Model Projected FS'!E26 -> 47.78 | F21: ='3 Model Projected FS'!F26 -> -161.69 | G21: ='3 Model Projected FS'!G26 -> 141.56 | H21: ='3 Model Projected FS'!H26 -> 0 | I21: ='3 Model Projected FS'!I26 -> 0
B22: Profit before Exceptional Items and Tax | C22: =ROUND(SUM(C20:C21),2) -> 6292.01 | D22: =ROUND(D19-D21,2) -> 2206.33 | E22: =ROUND(SUM(E20:E21),2) -> 6762.51 | F22: =ROUND(SUM(F20:F21),2) -> 10467.43 | G22: =ROUND(SUM(G20:G21),2) -> 13279.08 | H22: =ROUND(SUM(H20:H21),2) -> 16657.66 | I22: =ROUND(SUM(I20:I21),2) -> 21492.65
B23: Exceptional Items | C23: ='3 Model Projected FS'!C28 -> 0 | D23: ='3 Model Projected FS'!D28 -> -405.19 | E23: ='3 Model Projected FS'!E28 -> -1273.38 | F23: ='3 Model Projected FS'!F28 -> -373.7 | G23: ='3 Model Projected FS'!G28 -> -249.46 | H23: ='3 Model Projected FS'!H28 -> -37.8 | I23: ='3 Model Projected FS'!I28 -> -46.95
B24: Profit before Tax | C24: =ROUND(SUM(C22:C23),2) -> 6292.01 | D24: =ROUND(SUM(D22:D23),2) -> 1801.14 | E24: =ROUND(SUM(E22:E23),2) -> 5489.13 | F24: =ROUND(SUM(F22:F23),2) -> 10093.73 | G24: =ROUND(SUM(G22:G23),2) -> 13029.62 | H24: =ROUND(SUM(H22:H23),2) -> 16619.86 | I24: =ROUND(SUM(I22:I23),2) -> 21445.7
B25: Tax | C25: ='3 Model Projected FS'!C30 -> 1243.27 | D25: ='3 Model Projected FS'!D30 -> 763.96 | E25: ='3 Model Projected FS'!E30 -> 96.38 | F25: ='3 Model Projected FS'!F30 -> 1989.74 | G25: ='3 Model Projected FS'!G30 -> 1968.36 | H25: ='3 Model Projected FS'!H30 -> 2659.18 | I25: ='3 Model Projected FS'!I30 -> 3431.31
B26: Tax Burden | C26: =ROUND(C25/C24,3) -> 0.198 | D26: =ROUND(D25/D24,3) -> 0.424 | E26: =ROUND(E25/E24,3) -> 0.018 | F26: =ROUND(F25/F24,3) -> 0.197 | G26: =ROUND(G25/G24,3) -> 0.151 | H26: =ROUND(H25/H24,3) -> 0.16 | I26: =ROUND(I25/I24,3) -> 0.16
B27: Net Profit | C27: ='3 Model Projected FS'!C36 -> 5048.74 | D27: ='3 Model Projected FS'!D36 -> 4953.18 | E27: ='3 Model Projected FS'!E36 -> 5392.75 | F27: ='3 Model Projected FS'!F36 -> 8103.99 | G27: ='3 Model Projected FS'!G36 -> 11061.26 | H27: ='3 Model Projected FS'!H36 -> 13960.68 | I27: ='3 Model Projected FS'!I36 -> 18014.39
B28: Net Profit Margin | C28: =ROUND(C27/C7,3) -> 0.402 | D28: =ROUND(D27/D7,3) -> 0.289 | E28: =ROUND(E27/E7,3) -> 0.259 | F28: =ROUND(F27/F7,3) -> 0.303 | G28: =ROUND(G27/G7,3) -> 0.363 | H28: =ROUND(H27/H7,3) -> 0.369 | I28: =ROUND(I27/I7,3) -> 0.384
B29: Net Profit attributable to:
B30: Owners of the company | C30: ='3 Model Projected FS'!C39 -> 4994.3 | D30: ='3 Model Projected FS'!D39 -> 4886.03 | E30: ='3 Model Projected FS'!E39 -> 5310.18 | F30: ='3 Model Projected FS'!F39 -> 8110.64 | G30: ='3 Model Projected FS'!G39 -> 11092.31 | H30: ='3 Model Projected FS'!H39 -> 13999.87 | I30: ='3 Model Projected FS'!I39 -> 18064.96
B31: Non-Controlling Interest | C31: ='3 Model Projected FS'!C40 -> 54.44 | D31: ='3 Model Projected FS'!D40 -> 67.15 | E31: ='3 Model Projected FS'!E40 -> 82.57 | F31: ='3 Model Projected FS'!F40 -> -6.65 | G31: ='3 Model Projected FS'!G40 -> -31.05 | H31: ='3 Model Projected FS'!H40 -> -39.19 | I31: ='3 Model Projected FS'!I40 -> -50.57
A33: # | B33: Balance Sheet
B35: ASSETS
B36: Non-current Assets
B37: Property, Plant and Equipment | C37: ='3 Model Projected FS'!C46 -> 36791.51 | D37: ='3 Model Projected FS'!D46 -> 41488.7 | E37: ='3 Model Projected FS'!E46 -> 48414 | F37: ='3 Model Projected FS'!F46 -> 51803.83 | G37: ='3 Model Projected FS'!G46 -> 62394.43 | H37: ='3 Model Projected FS'!H46 -> 74595.961 | I37: ='3 Model Projected FS'!I46 -> 84528.219
B38: Right of Use Assets | C38: ='3 Model Projected FS'!C47 -> 1775.95 | D38: ='3 Model Projected FS'!D47 -> 2772.25 | E38: ='3 Model Projected FS'!E47 -> 3541.9 | F38: ='3 Model Projected FS'!F47 -> 3809.11 | G38: ='3 Model Projected FS'!G47 -> 6177.54 | H38: ='3 Model Projected FS'!H47 -> 7385.5877 | I38: ='3 Model Projected FS'!I47 -> 8368.9595
B39: Capital work-in-progress | C39: ='3 Model Projected FS'!C48 -> 3697.13 | D39: ='3 Model Projected FS'!D48 -> 4022.9 | E39: ='3 Model Projected FS'!E48 -> 6814.03 | F39: ='3 Model Projected FS'!F48 -> 10936.09 | G39: ='3 Model Projected FS'!G48 -> 11592.19 | H39: ='3 Model Projected FS'!H48 -> 7454.473 | I39: ='3 Model Projected FS'!I48 -> 9318.0912
B40: Investment Property | C40: ='3 Model Projected FS'!C49 -> 0 | D40: ='3 Model Projected FS'!D49 -> 0 | E40: ='3 Model Projected FS'!E49 -> 2473.38 | F40: ='3 Model Projected FS'!F49 -> 1345.3 | G40: ='3 Model Projected FS'!G49 -> 1459.16 | H40: ='3 Model Projected FS'!H49 -> 1744.5058 | I40: ='3 Model Projected FS'!I49 -> 1976.7822
B41: Goodwill | C41: ='3 Model Projected FS'!C50 -> 4036.43 | D41: ='3 Model Projected FS'!D50 -> 6711.43 | E41: ='3 Model Projected FS'!E50 -> 6963.4 | F41: ='3 Model Projected FS'!F50 -> 6906.93 | G41: ='3 Model Projected FS'!G50 -> 7093.59 | H41: ='3 Model Projected FS'!H50 -> 7093.59 | I41: ='3 Model Projected FS'!I50 -> 7093.59
B42: Other Intangible Assets | C42: ='3 Model Projected FS'!C51 -> 5533.03 | D42: ='3 Model Projected FS'!D51 -> 11580.54 | E42: ='3 Model Projected FS'!E51 -> 11445.51 | F42: ='3 Model Projected FS'!F51 -> 11282.64 | G42: ='3 Model Projected FS'!G51 -> 12491.6 | H42: ='3 Model Projected FS'!H51 -> 113.91 | I42: ='3 Model Projected FS'!I51 -> 113.91
B43: Intangible Assets under Development | C43: ='3 Model Projected FS'!C52 -> 0 | D43: ='3 Model Projected FS'!D52 -> 0 | E43: ='3 Model Projected FS'!E52 -> 0 | F43: ='3 Model Projected FS'!F52 -> 0 | G43: ='3 Model Projected FS'!G52 -> 113.91 | H43: ='3 Model Projected FS'!H52 -> 113.91 | I43: ='3 Model Projected FS'!I52 -> 113.91
B44: Other Non-Current Assets | C44: =ROUND(SUM('3 Model Projected FS'!C53:C59),2) -> 10659.09 | D44: =ROUND(SUM('3 Model Projected FS'!D53:D59),2) -> 15021.58 | E44: =ROUND(SUM('3 Model Projected FS'!E53:E59),2) -> 17805.39 | F44: =ROUND(SUM('3 Model Projected FS'!F53:F59),2) -> 15361.61 | G44: =ROUND(SUM('3 Model Projected FS'!G53:G59),2) -> 15065.69 | H44: =ROUND(SUM('3 Model Projected FS'!H53:H59),2) -> 15065.69 | I44: =ROUND(SUM('3 Model Projected FS'!I53:I59),2) -> 15065.69
B45: Total Non-current Assets | C45: =SUM(C37:C44) -> 62493.14 | D45: =SUM(D37:D44) -> 81597.4 | E45: =SUM(E37:E44) -> 97457.61 | F45: =SUM(F37:F44) -> 101445.51 | G45: =SUM(G37:G44) -> 116388.11 | H45: =SUM(H37:H44) -> 113567.63 | I45: =SUM(I37:I44) -> 126579.15
B47: Current assets
B48: Inventories | C48: ='3 Model Projected FS'!C63 -> 991.85 | D48: ='3 Model Projected FS'!D63 -> 395.64 | E48: ='3 Model Projected FS'!E63 -> 451.97 | F48: ='3 Model Projected FS'!F63 -> 437.51 | G48: ='3 Model Projected FS'!G63 -> 521.8 | H48: ='3 Model Projected FS'!H63 -> 631.26 | I48: ='3 Model Projected FS'!I63 -> 775.05
B49: Investments | C49: ='3 Model Projected FS'!C65 -> 1138.76 | D49: ='3 Model Projected FS'!D65 -> 47.79 | E49: ='3 Model Projected FS'!E65 -> 4028.69 | F49: ='3 Model Projected FS'!F65 -> 661.79 | G49: ='3 Model Projected FS'!G65 -> 751.88 | H49: ='3 Model Projected FS'!H65 -> 1251.88 | I49: ='3 Model Projected FS'!I65 -> 1751.88
B50: Trade receivables | C50: ='3 Model Projected FS'!C66 -> 2385.9 | D50: ='3 Model Projected FS'!D66 -> 2221.9 | E50: ='3 Model Projected FS'!E66 -> 3241.67 | F50: ='3 Model Projected FS'!F66 -> 3666.94 | G50: ='3 Model Projected FS'!G66 -> 4432.36 | H50: ='3 Model Projected FS'!H66 -> 4971.39 | I50: ='3 Model Projected FS'!I66 -> 6045.01
B51: Cash and Cash Equivalents | C51: ='3 Model Projected FS'!C67 -> 4198.04 | D51: ='3 Model Projected FS'!D67 -> 8653.02 | E51: ='3 Model Projected FS'!E67 -> 931.99 | F51: ='3 Model Projected FS'!F67 -> 1575.73 | G51: ='3 Model Projected FS'!G67 -> 3406.32 | H51: ='3 Model Projected FS'!H67 -> 11346.39 | I51: ='3 Model Projected FS'!I67 -> 20842.202
B52: Bank Balances other than Cash and Cash Equivalents | C52: ='3 Model Projected FS'!C68 -> 502.74 | D52: ='3 Model Projected FS'!D68 -> 2014.39 | E52: ='3 Model Projected FS'!E68 -> 3316.79 | F52: ='3 Model Projected FS'!F68 -> 6056.15 | G52: ='3 Model Projected FS'!G68 -> 3199.65 | H52: ='3 Model Projected FS'!H68 -> 3199.65 | I52: ='3 Model Projected FS'!I68 -> 3199.65
B53: Other Current Assets | C53: =ROUND(SUM('3 Model Projected FS'!C69:C73),2) -> 3258.49 | D53: =ROUND(SUM('3 Model Projected FS'!D69:D73),2) -> 2857.2 | E53: =ROUND(SUM('3 Model Projected FS'!E69:E73),2) -> 3535.15 | F53: =ROUND(SUM('3 Model Projected FS'!F69:F73),2) -> 4887.49 | G53: =ROUND(SUM('3 Model Projected FS'!G69:G73),2) -> 6445.36 | H53: =ROUND(SUM('3 Model Projected FS'!H69:H73),2) -> 6445.36 | I53: =ROUND(SUM('3 Model Projected FS'!I69:I73),2) -> 6445.36
B54: Total Current Assets | C54: =SUM(C48:C53) -> 12475.78 | D54: =SUM(D48:D53) -> 16189.94 | E54: =SUM(E48:E53) -> 15506.26 | F54: =SUM(F48:F53) -> 17285.61 | G54: =SUM(G48:G53) -> 18757.37 | H54: =SUM(H48:H53) -> 27845.93 | I54: =SUM(I48:I53) -> 39059.152
B55: Assets classified as held for sale and discontinued operations | C55: ='3 Model Projected FS'!C75 -> 354.86 | D55: ='3 Model Projected FS'!D75 -> 1898.48 | E55: ='3 Model Projected FS'!E75 -> 1941.26 | F55: ='3 Model Projected FS'!F75 -> 186.75 | G55: ='3 Model Projected FS'!G75 -> 186.75 | H55: ='3 Model Projected FS'!H75 -> 186.75 | I55: ='3 Model Projected FS'!I75 -> 186.75
B56: Total Assets | C56: =SUM(C45,C54,C55) -> 75323.78 | D56: =SUM(D45,D54,D55) -> 99685.82 | E56: =SUM(E45,E54,E55) -> 114905.13 | F56: =SUM(F45,F54,F55) -> 118917.87 | G56: =SUM(G45,G54,G55) -> 135332.23 | H56: =SUM(H45,H54,H55) -> 141600.31 | I56: =SUM(I45,I54,I55) -> 165825.05
B58: EQUITY AND LIABILITIES
B59: Equity
B60: Equity Share Capital | C60: ='3 Model Projected FS'!C80 -> 406.35 | D60: ='3 Model Projected FS'!D80 -> 422.47 | E60: ='3 Model Projected FS'!E80 -> 432.03 | F60: ='3 Model Projected FS'!F80 -> 432.03 | G60: ='3 Model Projected FS'!G80 -> 432.03 | H60: ='3 Model Projected FS'!H80 -> 432.03 | I60: ='3 Model Projected FS'!I80 -> 432.03
B61: Other Equity | C61: ='3 Model Projected FS'!C81 -> 30221.91 | D61: ='3 Model Projected FS'!D81 -> 41565.75 | E61: ='3 Model Projected FS'!E81 -> 45151.55 | F61: ='3 Model Projected FS'!F81 -> 52512.74 | G61: ='3 Model Projected FS'!G81 -> 62003.36 | H61: ='3 Model Projected FS'!H81 -> 59606.48 | I61: ='3 Model Projected FS'!I81 -> 75510.353
B62: Equity Attributable to the Owners of the Company | C62: =SUM(C60:C61) -> 30628.26 | D62: =SUM(D60:D61) -> 41988.22 | E62: =SUM(E60:E61) -> 45583.58 | F62: =SUM(F60:F61) -> 52944.77 | G62: =SUM(G60:G61) -> 62435.39 | H62: =SUM(H60:H61) -> 60038.51 | I62: =SUM(I60:I61) -> 75942.383
B63: Non-Controlling Interests | C63: ='3 Model Projected FS'!C83 -> 1468.47 | D63: ='3 Model Projected FS'!D83 -> 392.77 | E63: ='3 Model Projected FS'!E83 -> 1338.51 | F63: ='3 Model Projected FS'!F83 -> 1598.23 | G63: ='3 Model Projected FS'!G83 -> 2537.95 | H63: ='3 Model Projected FS'!H83 -> 2537.95 | I63: ='3 Model Projected FS'!I83 -> 2537.95
B64: Total Equity | C64: =SUM(C62:C63) -> 32096.73 | D64: =SUM(D62:D63) -> 42380.99 | E64: =SUM(E62:E63) -> 46922.09 | F64: =SUM(F62:F63) -> 54543 | G64: =SUM(G62:G63) -> 64973.34 | H64: =SUM(H62:H63) -> 62576.46 | I64: =SUM(I62:I63) -> 78480.333
B66: Non-current Liabilities
B67: Borrowings | C67: ='3 Model Projected FS'!C88 -> 32935.53 | D67: ='3 Model Projected FS'!D88 -> 39691.48 | E67: ='3 Model Projected FS'!E88 -> 46516.94 | F67: ='3 Model Projected FS'!F88 -> 37662.93 | G67: ='3 Model Projected FS'!G88 -> 35830.68 | H67: ='3 Model Projected FS'!H88 -> 39413.748 | I67: ='3 Model Projected FS'!I88 -> 43355.123
B68: Lease Liabilities | C68: ='3 Model Projected FS'!C89 -> 572.33 | D68: ='3 Model Projected FS'!D89 -> 1983.78 | E68: ='3 Model Projected FS'!E89 -> 2681.74 | F68: ='3 Model Projected FS'!F89 -> 2953.28 | G68: ='3 Model Projected FS'!G89 -> 5389.61 | H68: ='3 Model Projected FS'!H89 -> 5928.571 | I68: ='3 Model Projected FS'!I89 -> 6521.4281
B69: Other Financial Liabilities | C69: ='3 Model Projected FS'!C90 -> 207.61 | D69: ='3 Model Projected FS'!D90 -> 227.56 | E69: ='3 Model Projected FS'!E90 -> 322.84 | F69: ='3 Model Projected FS'!F90 -> 360.11 | G69: ='3 Model Projected FS'!G90 -> 207.45 | H69: ='3 Model Projected FS'!H90 -> 2242.68 | I69: ='3 Model Projected FS'!I90 -> 2242.68
B70: Other Non-Current Liabilities | C70: =ROUND(SUM('3 Model Projected FS'!C91:C95),2) -> 2295.63 | D70: =ROUND(SUM('3 Model Projected FS'!D91:D95),2) -> 4033.3 | E70: =ROUND(SUM('3 Model Projected FS'!E91:E95),2) -> 5536.96 | F70: =ROUND(SUM('3 Model Projected FS'!F91:F95),2) -> 6935.61 | G70: =ROUND(SUM('3 Model Projected FS'!G91:G95),2) -> 7945.16 | H70: =ROUND(SUM('3 Model Projected FS'!H91:H95),2) -> 7945.16 | I70: =ROUND(SUM('3 Model Projected FS'!I91:I95),2) -> 7945.16
B71: Total Non-current Liabilities | C71: =SUM(C67:C70) -> 36011.1 | D71: =SUM(D67:D70) -> 45936.12 | E71: =SUM(E67:E70) -> 55058.48 | F71: =SUM(F67:F70) -> 47911.93 | G71: =SUM(G67:G70) -> 49372.9 | H71: =SUM(H67:H70) -> 55530.159 | I71: =SUM(I67:I70) -> 60064.391
B73: Current Liabilities
B74: Borrowings | C74: ='3 Model Projected FS'!C100 -> 400 | D74: ='3 Model Projected FS'!D100 -> 5761.56 | E74: ='3 Model Projected FS'!E100 -> 3302.37 | F74: ='3 Model Projected FS'!F100 -> 8616.3 | G74: ='3 Model Projected FS'!G100 -> 9979.35 | H74: ='3 Model Projected FS'!H100 -> 12374.394 | I74: ='3 Model Projected FS'!I100 -> 15368.997
B75: Lease Liabilities | C75: ='3 Model Projected FS'!C101 -> 32.26 | D75: ='3 Model Projected FS'!D101 -> 32.16 | E75: ='3 Model Projected FS'!E101 -> 61.97 | F75: ='3 Model Projected FS'!F101 -> 71.2 | G75: ='3 Model Projected FS'!G101 -> 254.56 | H75: ='3 Model Projected FS'!H101 -> 315.6544 | I75: ='3 Model Projected FS'!I101 -> 392.04276
B76: Trade payables | C76: =ROUND(SUM('3 Model Projected FS'!C103:C104),2) -> 1013.85 | D76: =ROUND(SUM('3 Model Projected FS'!D103:D104),2) -> 1159.57 | E76: =ROUND(SUM('3 Model Projected FS'!E103:E104),2) -> 1828.23 | F76: =ROUND(SUM('3 Model Projected FS'!F103:F104),2) -> 1912.1 | G76: =ROUND(SUM('3 Model Projected FS'!G103:G104),2) -> 2720.5 | H76: =ROUND(SUM('3 Model Projected FS'!H103:H104),2) -> 2772.06 | I76: =ROUND(SUM('3 Model Projected FS'!I103:I104),2) -> 3487.71
B77: Other Financial Liabilities | C77: ='3 Model Projected FS'!C105 -> 3260.08 | D77: ='3 Model Projected FS'!D105 -> 2253.75 | E77: ='3 Model Projected FS'!E105 -> 3319.88 | F77: ='3 Model Projected FS'!F105 -> 3756.8 | G77: ='3 Model Projected FS'!G105 -> 5359.74 | H77: ='3 Model Projected FS'!H105 -> 5359.74 | I77: ='3 Model Projected FS'!I105 -> 5359.74
B78: Other Current Liabilities | C78: =ROUND(SUM('3 Model Projected FS'!C106:C110),2) -> 2395.22 | D78: =ROUND(SUM('3 Model Projected FS'!D106:D110),2) -> 1856.31 | E78: =ROUND(SUM('3 Model Projected FS'!E106:E110),2) -> 2890.65 | F78: =ROUND(SUM('3 Model Projected FS'!F106:F110),2) -> 2058.99 | G78: =ROUND(SUM('3 Model Projected FS'!G106:G110),2) -> 2624.29 | H78: =ROUND(SUM('3 Model Projected FS'!H106:H110),2) -> 2624.29 | I78: =ROUND(SUM('3 Model Projected FS'!I106:I110),2) -> 2624.29
B79: Total Current Liabilities | C79: =SUM(C74:C78) -> 7101.41 | D79: =SUM(D74:D78) -> 11063.35 | E79: =SUM(E74:E78) -> 11403.1 | F79: =SUM(F74:F78) -> 16415.39 | G79: =SUM(G74:G78) -> 20938.44 | H79: =SUM(H74:H78) -> 23446.138 | I79: =SUM(I74:I78) -> 27232.78
B80: Assets classified as held for sale and discontinued operations | C80: ='3 Model Projected FS'!C112 -> 114.54 | D80: ='3 Model Projected FS'!D112 -> 305.36 | E80: ='3 Model Projected FS'!E112 -> 1521.46 | F80: ='3 Model Projected FS'!F112 -> 47.55 | G80: ='3 Model Projected FS'!G112 -> 47.55 | H80: ='3 Model Projected FS'!H112 -> 47.55 | I80: ='3 Model Projected FS'!I112 -> 47.55
B81: Total Equity and Liabilities | C81: =SUM(C64,C71,C79,C80) -> 75323.78 | D81: =SUM(D64,D71,D79,D80) -> 99685.82 | E81: =SUM(E64,E71,E79,E80) -> 114905.13 | F81: =SUM(F64,F71,F79,F80) -> 118917.87 | G81: =SUM(G64,G71,G79,G80) -> 135332.23 | H81: =SUM(H64,H71,H79,H80) -> 141600.31 | I81: =SUM(I64,I71,I79,I80) -> 165825.05
B83: Check | C83: =C56-C81 -> 0 | D83: =D56-D81 -> 0 | E83: =E56-E81 -> 0 | F83: =F56-F81 -> 0 | G83: =G56-G81 -> 0 | H83: =H56-H81 -> 0 | I83: =I56-I81 -> 0
A85: # | B85: Cash Flow Statement
B87: Cash Flow from Operating Activities | C87: =SUM(#REF!) -> #REF! | D87: =SUM(#REF!) -> #REF! | E87: =SUM(#REF!) -> #REF! | F87: ='3 Model Projected FS'!F156 -> 15017.58 | G87: ='3 Model Projected FS'!G156 -> 17226.28 | H87: ='3 Model Projected FS'!H156 -> 21005.786 | I87: ='3 Model Projected FS'!I156 -> 26440.08
B88: Cash Flow from Investing Activities | F88: ='3 Model Projected FS'!F172 -> -6946.55 | G88: ='3 Model Projected FS'!G172 -> -9787.27 | H88: ='3 Model Projected FS'!H172 -> -14149.893 | I88: ='3 Model Projected FS'!I172 -> -17669.249
B89: Cash Flow from Financing Activities | F89: ='3 Model Projected FS'!F192 -> 270.92 | G89: ='3 Model Projected FS'!G192 -> 523.49 | H89: ='3 Model Projected FS'!H192 -> 7940.0704 | I89: ='3 Model Projected FS'!I192 -> 9495.8113
B90: Net Increase / (Decrease) in Cash and Cash Equivalents | F90: ='3 Model Projected FS'!F192 -> 270.92 | G90: ='3 Model Projected FS'!G192 -> 523.49 | H90: ='3 Model Projected FS'!H192 -> 7940.0704 | I90: ='3 Model Projected FS'!I192 -> 9495.8113
B91: Cash and cash equivalents at the beginning of the year | C91: =[3]Consol!C191 -> #VALUE! | D91: =[3]Consol!D191 -> #VALUE! | E91: =[3]Consol!E191 -> #VALUE! | F91: ='3 Model Projected FS'!F194 -> 1125.82 | G91: ='3 Model Projected FS'!G194 -> 1575.73 | H91: ='3 Model Projected FS'!H194 -> 3406.32 | I91: ='3 Model Projected FS'!I194 -> 11346.39
B92: Addition on account of Business Combination | C92: =[3]Consol!C192 -> #VALUE! | D92: =[3]Consol!D192 -> #VALUE! | E92: =[3]Consol!E192 -> #VALUE! | F92: ='3 Model Projected FS'!F195 -> 178.99 | G92: ='3 Model Projected FS'!G195 -> 1307.1 | H92: ='3 Model Projected FS'!H195 -> 0 | I92: ='3 Model Projected FS'!I195 -> 0
B93: Cash and cash equivalents at the end of the year | C93: =[3]Consol!C193 -> #VALUE! | D93: =[3]Consol!D193 -> #VALUE! | E93: =[3]Consol!E193 -> #VALUE! | F93: ='3 Model Projected FS'!F196 -> 1575.73 | G93: ='3 Model Projected FS'!G196 -> 3406.32 | H93: ='3 Model Projected FS'!H196 -> 11346.39 | I93: ='3 Model Projected FS'!I196 -> 20842.202

Sheet Scenarios
L1: ="Currently Running: "&IF(C6=1,"Base Case Scenario",IF(C6=2,"Bull Case Scenario","Bear Case Scenario")) -> Currently Running: Base Case Scenario
B2: SCENARIOS
B3: ₹'cr, unless otherwise stated | F3: ='[2]3 Model Projected FS'!C3 -> FY21A | G3: ='[2]3 Model Projected FS'!D3 -> FY22A | H3: ='[2]3 Model Projected FS'!E3 -> FY23A | I3: ='[2]3 Model Projected FS'!F3 -> FY24A | J3: ='[2]3 Model Projected FS'!G3 -> FY25A | K3: ='[2]3 Model Projected FS'!H3 -> FY26E | L3: ='[2]3 Model Projected FS'!I3 -> FY27E
A6: # | B6: SCENARIO SWITCH: | C6: 1
A9: # | B9: REVENUE SCHEDULE
B11: Total Consolidated Revenue | I11: =SUM(I14,I95,I107,I119,I131,I143) -> 26710.56 | J11: =SUM(J14,J95,J107,J119,J131,J143) -> 30475.33 | K11: =SUM(K14,K95,K107,K119,K131,K143) -> 37803.28 | L11: =SUM(L14,L95,L107,L119,L131,L143) -> 46945.27
B12: YoY growth rate | J12: =ROUND(J11/I11-1,3) -> 0.141 | K12: =ROUND(K11/J11-1,3) -> 0.24 | L12: =ROUND(L11/K11-1,3) -> 0.242
B14: Total Standalone Revenue | I14: =SUM(I31,I47,I63,I79) -> 26710.56 | J14: =SUM(J31,J47,J63,J79) -> 30475.33 | K14: =SUM(K31,K47,K63,K79) -> 37803.28 | L14: =SUM(L31,L47,L63,L79) -> 46945.27
B15: YoY growth rate | J15: =ROUND(J14/I14-1,3) -> 0.141 | K15: =ROUND(K14/J14-1,3) -> 0.24 | L15: =ROUND(L14/K14-1,3) -> 0.242
B17: Net Profit | F17: ='Consol. Historical FS'!C30 -> 5048.74 | G17: ='Consol. Historical FS'!D30 -> 4953.18 | H17: ='Consol. Historical FS'!E30 -> 5392.75 | I17: ='Consol. Historical FS'!F30 -> 8103.99 | J17: ='Consol. Historical FS'!G30 -> 11061.26 | K17: =ROUND(K14*K21,2) -> 3137.67 | L17: =ROUND(L14*L21,2) -> 3896.46
B19: Net Profit Margin
B21: Net Profit Margin | F21: ='Consol. Common Size FS'!C28 -> 0.402 | G21: ='Consol. Common Size FS'!D28 -> 0.289 | H21: ='Consol. Common Size FS'!E28 -> 0.259 | I21: ='Consol. Common Size FS'!F28 -> 0.303 | J21: ='Consol. Common Size FS'!G28 -> 0.363 | K21: =CHOOSE($C$6,K23,K24,K25) -> 0.083 | L21: =CHOOSE($C$6,L23,L24,L25) -> 0.083
B23: Base Case | K23: 0.083 | L23: 0.083
B24: Bull Case | C24: ="+1%" -> +1% | K24: =K23+$C24 -> 0.093 | L24: =L23+$C24 -> 0.093
B25: Bear Case | C25: ="-1%" -> -1% | K25: =K23+$C25 -> 0.073 | L25: =L23+$C25 -> 0.073
B27: Ports
B29: Revenue from Operations | I29: =3152+413+20343 -> 23908 | J29: =3380+933+22740 -> 27053
B30: Other Operating Revenues | I30: 0 | J30: 0
B31: Total Revenue | I31: =SUM(I29:I30) -> 23908 | J31: =SUM(J29:J30) -> 27053 | K31: =ROUND(J31*(1+K36),2) -> 32463.6 | L31: =ROUND(K31*(1+L36),2) -> 38956.32
B33: Growth Rate
B34: Revenue from Operations
B35: Other Operating Revenues
B36: Total Revenue | J36: =ROUND(J31/I31-1,3) -> 0.132 | K36: =CHOOSE($C$6,K39,K40,K41) -> 0.2 | L36: =CHOOSE($C$6,L39,L40,L41) -> 0.2
B38: Total Revenue
B39: =B23 -> Base Case | K39: 0.2 | L39: 0.2
B40: =B24 -> Bull Case | C40: ="+3%" -> +3% | K40: =K39+$C40 -> 0.23 | L40: =L39+$C40 -> 0.23
B41: =B25 -> Bear Case | C41: ="-3%" -> -3% | K41: =K39+$C41 -> 0.17 | L41: =L39+$C41 -> 0.17
B43: Logistics
B45: Revenue from Operations | I45: 2079 | J45: 2881
B46: Other Operating Revenues | I46: 0 | J46: 0
B47: Total Revenue | I47: =SUM(I45:I46) -> 2079 | J47: =SUM(J45:J46) -> 2881 | K47: =ROUND(J47*(1+K52),2) -> 4091.02 | L47: =ROUND(K47*(1+L52),2) -> 5727.43
B49: Growth Rate
B50: Revenue from Operations
B51: Other Operating Revenues
B52: Total Revenue | J52: =ROUND(J47/I47-1,3) -> 0.386 | K52: =CHOOSE($C$6,K55,K56,K57) -> 0.42 | L52: =CHOOSE($C$6,L55,L56,L57) -> 0.4
B54: Total Revenue
B55: =B39 -> Base Case | K55: 0.42 | L55: 0.4
B56: =B40 -> Bull Case | C56: ="+10%" -> +10% | K56: =K55+$C56 -> 0.52 | L56: =L55+$C56 -> 0.5
B57: =B41 -> Bear Case | C57: ="-8%" -> -8% | K57: =K55+$C57 -> 0.34 | L57: =L55+$C57 -> 0.32
B59: Marine
B61: Revenue from Operations | I61: 629 | J61: 1144
B62: Other Operating Revenues | I62: 0 | J62: 0
B63: Total Revenue | I63: =SUM(I61:I62) -> 629 | J63: =SUM(J61:J62) -> 1144 | K63: =ROUND(J63*(1+K68),2) -> 2002 | L63: =ROUND(K63*(1+L68),2) -> 3203.2
B65: Growth Rate
B66: Revenue from Operations
B67: Other Operating Revenues
B68: Total Revenue | J68: =ROUND(J63/I63-1,3) -> 0.819 | K68: =CHOOSE($C$6,K71,K72,K73) -> 0.75 | L68: =CHOOSE($C$6,L71,L72,L73) -> 0.6
B70: Total Revenue
B71: =B55 -> Base Case | K71: 0.75 | L71: 0.6
B72: =B56 -> Bull Case | C72: ="+20%" -> +20% | K72: =K71+$C72 -> 0.95 | L72: =L71+$C72 -> 0.8
B73: =B57 -> Bear Case | C73: ="-10%" -> -10% | K73: =K71+$C73 -> 0.65 | L73: =L71+$C73 -> 0.5
B75: Others
B77: Revenue from Operations | I77: ='Consol. Historical FS'!F9-(Scenarios!I31+Scenarios!I47+Scenarios!I63) -> 94.56 | J77: ='Consol. Historical FS'!G9-(Scenarios!J31+Scenarios!J47+Scenarios!J63) -> -602.67
B78: Other Operating Revenues | I78: 0 | J78: 0
B79: Total Revenue | I79: =SUM(I77:I78) -> 94.56 | J79: =SUM(J77:J78) -> -602.67 | K79: =ROUND(J79*(1+K84),2) -> -753.34 | L79: =ROUND(K79*(1+L84),2) -> -941.68
B81: Growth Rate
B82: Revenue from Operations
B83: Other Operating Revenues
B84: Total Revenue | J84: =ROUND(J79/I79-1,3) -> -7.373 | K84: =CHOOSE($C$6,K87,K88,K89) -> 0.25 | L84: =CHOOSE($C$6,L87,L88,L89) -> 0.25
B86: Total Revenue
B87: =B71 -> Base Case | K87: 0.25 | L87: 0.25
B88: =B72 -> Bull Case | C88: ="+2%" -> +2% | K88: =K87+$C88 -> 0.27 | L88: =L87+$C88 -> 0.27
B89: =B73 -> Bear Case | C89: ="-2%" -> -2% | K89: =K87+$C89 -> 0.23 | L89: =L87+$C89 -> 0.23
B91: Subsidiaries
B95: Total Revenue | F95: 0 | G95: 0 | H95: 0 | I95: 0 | J95: 0 | K95: =ROUND(J95*(1+K98),3) -> 0 | L95: =ROUND(K95*(1+L98),3) -> 0
B97: Growth Rate
B98: Total Revenue | G98: =ROUND(G95/F95-1,3) -> #DIV/0! | H98: =ROUND(H95/G95-1,3) -> #DIV/0! | I98: =ROUND(I95/H95-1,3) -> #DIV/0! | J98: =ROUND(J95/I95-1,3) -> #DIV/0! | K98: =CHOOSE($C$6,K101,K102,K103) -> 0.2 | L98: =CHOOSE($C$6,L101,L102,L103) -> 0.2
B100: Total Revenue
B101: =B87 -> Base Case | K101: 0.2 | L101: 0.2
B102: =B88 -> Bull Case | C102: ="+3%" -> +3% | K102: =K101+$C102 -> 0.23 | L102: =L101+$C102 -> 0.23
B103: =B89 -> Bear Case | C103: ="-3%" -> -3% | K103: =K101+$C103 -> 0.17 | L103: =L101+$C103 -> 0.17
B105: Shanthi Gears
B107: Total Revenue | F107: 0 | G107: 0 | H107: 0 | I107: 0 | J107: 0 | K107: =ROUND(J107*(1+K110),3) -> 0 | L107: =ROUND(K107*(1+L110),3) -> 0
B109: Growth Rate
B110: Total Revenue | G110: =ROUND(G107/F107-1,3) -> #DIV/0! | H110: =ROUND(H107/G107-1,3) -> #DIV/0! | I110: =ROUND(I107/H107-1,3) -> #DIV/0! | J110: =ROUND(J107/I107-1,3) -> #DIV/0! | K110: =CHOOSE($C$6,K113,K114,K115) -> 0.17 | L110: =CHOOSE($C$6,L113,L114,L115) -> 0.19
B112: Total Revenue
B113: =B101 -> Base Case | K113: 0.17 | L113: 0.19
B114: =B102 -> Bull Case | C114: ="+2%" -> +2% | K114: =K113+$C114 -> 0.19 | L114: =L113+$C114 -> 0.21
B115: =B103 -> Bear Case | C115: ="-3%" -> -3% | K115: =K113+$C115 -> 0.14 | L115: =L113+$C115 -> 0.16
B117: Electric Vehicles
B119: Total Revenue | F119: 0 | G119: 0 | H119: 0 | I119: 0 | J119: 0 | K119: =ROUND(J119*(1+K122),3) -> 0 | L119: =ROUND(K119*(1+L122),3) -> 0
B121: Growth Rate
B122: Total Revenue | I122: =ROUND(I119/H119-1,3) -> #DIV/0! | J122: =ROUND(J119/I119-1,3) -> #DIV/0! | K122: =CHOOSE($C$6,K125,K126,K127) -> 0.75 | L122: =CHOOSE($C$6,L125,L126,L127) -> 0.65
B124: Total Revenue
B125: =B113 -> Base Case | K125: 0.75 | L125: 0.65
B126: =B114 -> Bull Case | C126: ="+10%" -> +10% | K126: =K125+$C126 -> 0.85 | L126: =L125+$C126 -> 0.75
B127: =B115 -> Bear Case | C127: ="-10%" -> -10% | K127: =K125+$C127 -> 0.65 | L127: =L125+$C127 -> 0.55
B129: Medical
B131: Total Revenue | F131: 0 | G131: 0 | H131: 0 | I131: 0 | J131: 0 | K131: =ROUND(J131*(1+K134),3) -> 0 | L131: =ROUND(K131*(1+L134),3) -> 0
B133: Growth Rate
B134: Total Revenue | J134: =ROUND(J131/I131-1,3) -> #DIV/0! | K134: =CHOOSE($C$6,K137,K138,K139) -> 0.22 | L134: =CHOOSE($C$6,L137,L138,L139) -> 0.25
B136: Total Revenue
B137: =B125 -> Base Case | K137: 0.22 | L137: 0.25
B138: =B126 -> Bull Case | C138: ="+2%" -> +2% | K138: =K137+$C138 -> 0.24 | L138: =L137+$C138 -> 0.27
B139: =B127 -> Bear Case | C139: ="-2%" -> -2% | K139: =K137+$C139 -> 0.2 | L139: =L137+$C139 -> 0.23
B141: Others
B143: Total Revenue | K143: =ROUND(J143*(1+K146),3) -> 0 | L143: =ROUND(K143*(1+L146),3) -> 0
B145: Growth Rate
B146: Total Revenue | G146: =ROUND(G143/F143-1,3) -> #DIV/0! | H146: =ROUND(H143/G143-1,3) -> #DIV/0! | I146: =ROUND(I143/H143-1,3) -> #DIV/0! | J146: =ROUND(J143/I143-1,3) -> #DIV/0! | K146: =CHOOSE($C$6,K149,K150,K151) -> 0.06 | L146: =CHOOSE($C$6,L149,L150,L151) -> 0.07
B148: Total Revenue
...

Sheet Other Data
A13: Other Data -->>

Sheet Graphs
H1: =[2]Scenarios!L1 -> Currently Running: Base Case Scenario
B2: CONSOLIDATED - GRAPHS
B3: ₹'cr, unless otherwise stated | C3: ='[2]3 Model Projected FS'!D3 -> FY22A | D3: ='[2]3 Model Projected FS'!E3 -> FY23A | E3: ='[2]3 Model Projected FS'!F3 -> FY24A | F3: ='[2]3 Model Projected FS'!G3 -> FY25A | G3: ='[2]3 Model Projected FS'!H3 -> FY26E | H3: ='[2]3 Model Projected FS'!I3 -> FY27E
B4: Revenue | C4: ='[2]3 Model Projected FS'!D9 -> 0 | D4: ='3 Model Projected FS'!E9 -> 20851.91 | E4: ='3 Model Projected FS'!F9 -> 26710.56 | F4: ='3 Model Projected FS'!G9 -> 30475.33 | G4: ='3 Model Projected FS'!H9 -> 37803.28 | H4: ='3 Model Projected FS'!I9 -> 46945.27
B5: EBITDA | D5: ='3 Model Projected FS'!E19 -> 10947.13 | E5: ='3 Model Projected FS'!F19 -> 15751.1 | F5: ='3 Model Projected FS'!G19 -> 18140.52 | G5: ='3 Model Projected FS'!H19 -> 22681.96 | H5: ='3 Model Projected FS'!I19 -> 28214.11
B6: Net Profit | D6: ='3 Model Projected FS'!E36 -> 5392.75 | E6: ='3 Model Projected FS'!F36 -> 8103.99 | F6: ='3 Model Projected FS'!G36 -> 11061.26 | G6: ='3 Model Projected FS'!H36 -> 13960.68 | H6: ='3 Model Projected FS'!I36 -> 18014.39
B7: Free Cash Flow | D7: ='3 Model Projected FS'!E156+'3 Model Projected FS'!E159 -> 3357.47 | E7: ='3 Model Projected FS'!F156+'3 Model Projected FS'!F159 -> 9637.91 | F7: ='3 Model Projected FS'!G156+'3 Model Projected FS'!G159 -> 8911.36 | G7: ='3 Model Projected FS'!H156+'3 Model Projected FS'!H159 -> 12985.298 | H7: ='3 Model Projected FS'!I156+'3 Model Projected FS'!I159 -> 16414.47
B8: Turnover Ratios
B9: Gross Fixed Assets | C9: ='[2]PP&E'!J13+'[2]Intangible Assets'!M13 -> 0 | D9: ='Summary_3 Model Projected FS'!E37+'Summary_3 Model Projected FS'!E38+'Summary_3 Model Projected FS'!E39+'Summary_3 Model Projected FS'!E40+'Summary_3 Model Projected FS'!E41+'Summary_3 Model Projected FS'!E42 -> 79652.22 | E9: ='Summary_3 Model Projected FS'!F37+'Summary_3 Model Projected FS'!F38+'Summary_3 Model Projected FS'!F39+'Summary_3 Model Projected FS'!F40+'Summary_3 Model Projected FS'!F41+'Summary_3 Model Projected FS'!F42 -> 86083.9 | F9: ='Summary_3 Model Projected FS'!G37+'Summary_3 Model Projected FS'!G38+'Summary_3 Model Projected FS'!G39+'Summary_3 Model Projected FS'!G40+'Summary_3 Model Projected FS'!G41+'Summary_3 Model Projected FS'!G42 -> 101208.51 | G9: ='Summary_3 Model Projected FS'!H37+'Summary_3 Model Projected FS'!H38+'Summary_3 Model Projected FS'!H39+'Summary_3 Model Projected FS'!H40+'Summary_3 Model Projected FS'!H41+'Summary_3 Model Projected FS'!H42 -> 98388.027 | H9: ='Summary_3 Model Projected FS'!I37+'Summary_3 Model Projected FS'!I38+'Summary_3 Model Projected FS'!I39+'Summary_3 Model Projected FS'!I40+'Summary_3 Model Projected FS'!I41+'Summary_3 Model Projected FS'!I42 -> 111399.55
B10: GFAT | C10: =ROUND(C4/AVERAGE(B9:C9),1) -> #DIV/0! | D10: =ROUND(D4/AVERAGE(C9:D9),1) -> 0.5 | E10: =ROUND(E4/AVERAGE(D9:E9),1) -> 0.3 | F10: =ROUND(F4/AVERAGE(E9:F9),1) -> 0.3 | G10: =ROUND(G4/AVERAGE(F9:G9),1) -> 0.4 | H10: =ROUND(H4/AVERAGE(G9:H9),1) -> 0.4
B11: ITR | D11: =ROUND(SUM('3 Model Projected FS'!E11:E13)/AVERAGE('3 Model Projected FS'!D63:E63),1) -> 13.3 | E11: =ROUND(SUM('3 Model Projected FS'!F11:F13)/AVERAGE('3 Model Projected FS'!E63:F63),1) -> 16 | F11: =ROUND(SUM('3 Model Projected FS'!G11:G13)/AVERAGE('3 Model Projected FS'!F63:G63),1) -> 16.8 | G11: =ROUND(SUM('3 Model Projected FS'!H11:H13)/AVERAGE('3 Model Projected FS'!G63:H63),1) -> 17.4 | H11: =ROUND(SUM('3 Model Projected FS'!I11:I13)/AVERAGE('3 Model Projected FS'!H63:I63),1) -> 17.5
B12: RTR | D12: =ROUND('3 Model Projected FS'!E9/AVERAGE('3 Model Projected FS'!D66:E66),1) -> 7.6 | E12: =ROUND('3 Model Projected FS'!F9/AVERAGE('3 Model Projected FS'!E66:F66),1) -> 7.7 | F12: =ROUND('3 Model Projected FS'!G9/AVERAGE('3 Model Projected FS'!F66:G66),1) -> 7.5 | G12: =ROUND('3 Model Projected FS'!H9/AVERAGE('3 Model Projected FS'!G66:H66),1) -> 8 | H12: =ROUND('3 Model Projected FS'!I9/AVERAGE('3 Model Projected FS'!H66:I66),1) -> 8.5
B13: Profit Margin Ratios
B14: EBITDA Margin | D14: ='3 Model Projected FS'!E20 -> 0.525 | E14: ='3 Model Projected FS'!F20 -> 0.59 | F14: ='3 Model Projected FS'!G20 -> 0.595 | G14: ='3 Model Projected FS'!H20 -> 0.6 | H14: ='3 Model Projected FS'!I20 -> 0.601
B15: Net Profit Margin | D15: ='3 Model Projected FS'!E37 -> 0.259 | E15: ='3 Model Projected FS'!F37 -> 0.303 | F15: ='3 Model Projected FS'!G37 -> 0.363 | G15: ='3 Model Projected FS'!H37 -> 0.369 | H15: ='3 Model Projected FS'!I37 -> 0.384
B16: Trade Receivables | D16: ='3 Model Projected FS'!E66 -> 3241.67 | E16: ='3 Model Projected FS'!F66 -> 3666.94 | F16: ='3 Model Projected FS'!G66 -> 4432.36 | G16: ='3 Model Projected FS'!H66 -> 4971.39 | H16: ='3 Model Projected FS'!I66 -> 6045.01
B17: DSO | D17: =Scenarios!H311 -> 48 | E17: =Scenarios!I311 -> 47 | F17: =Scenarios!J311 -> 49 | G17: =Scenarios!K311 -> 48 | H17: =Scenarios!L311 -> 47
B18: Trade Payables | D18: =SUM('3 Model Projected FS'!E103:E104) -> 1828.23 | E18: =SUM('3 Model Projected FS'!F103:F104) -> 1912.1 | F18: =SUM('3 Model Projected FS'!G103:G104) -> 2720.5 | G18: =SUM('3 Model Projected FS'!H103:H104) -> 2772.06 | H18: =SUM('3 Model Projected FS'!I103:I104) -> 3487.71
B19: DPO | D19: =ROUND(SUM(Scenarios!H318,Scenarios!H324),0) -> 97 | E19: =ROUND(SUM(Scenarios!I318,Scenarios!I324),0) -> 95 | F19: =ROUND(SUM(Scenarios!J318,Scenarios!J324),0) -> 105 | G19: =ROUND(SUM(Scenarios!K318,Scenarios!K324),0) -> 101 | H19: =ROUND(SUM(Scenarios!L318,Scenarios!L324),0) -> 104
B20: Inventories | D20: ='3 Model Projected FS'!E63 -> 451.97 | E20: ='3 Model Projected FS'!F63 -> 437.51 | F20: ='3 Model Projected FS'!G63 -> 521.8 | G20: ='3 Model Projected FS'!H63 -> 631.26 | H20: ='3 Model Projected FS'!I63 -> 775.05
B21: DOH | D21: =Scenarios!H305 -> 27 | E21: =Scenarios!I305 -> 23 | F21: =Scenarios!J305 -> 22 | G21: =Scenarios!K305 -> 23 | H21: =Scenarios!L305 -> 23
B22: Return Ratios
B23: RoCE | C23: =ROUND('[2]3 Model Projected FS'!D22/AVERAGE(SUM('[2]3 Model Projected FS'!C84,'[2]3 Model Projected FS'!C88,'[2]3 Model Projected FS'!C100),SUM('[2]3 Model Projected FS'!D84,'[2]3 Model Projected FS'!D88,'[2]3 Model Projected FS'!D100)),3) -> 0 | D23: =ROUND('3 Model Projected FS'!E22/AVERAGE(SUM('3 Model Projected FS'!D84,'3 Model Projected FS'!D88,'3 Model Projected FS'!D100),SUM('3 Model Projected FS'!E84,'3 Model Projected FS'!E88,'3 Model Projected FS'!E100)),3) -> 0.082 | E23: =ROUND('3 Model Projected FS'!F22/AVERAGE(SUM('3 Model Projected FS'!E84,'3 Model Projected FS'!E88,'3 Model Projected FS'!E100),SUM('3 Model Projected FS'!F84,'3 Model Projected FS'!F88,'3 Model Projected FS'!F100)),3) -> 0.12 | F23: =ROUND('3 Model Projected FS'!G22/AVERAGE(SUM('3 Model Projected FS'!F84,'3 Model Projected FS'!F88,'3 Model Projected FS'!F100),SUM('3 Model Projected FS'!G84,'3 Model Projected FS'!G88,'3 Model Projected FS'!G100)),3) -> 0.13 | G23: =ROUND('3 Model Projected FS'!H22/AVERAGE(SUM('3 Model Projected FS'!G84,'3 Model Projected FS'!G88,'3 Model Projected FS'!G100),SUM('3 Model Projected FS'!H84,'3 Model Projected FS'!H88,'3 Model Projected FS'!H100)),3) -> 0.155 | H23: =ROUND('3 Model Projected FS'!I22/AVERAGE(SUM('3 Model Projected FS'!H84,'3 Model Projected FS'!H88,'3 Model Projected FS'!H100),SUM('3 Model Projected FS'!I84,'3 Model Projected FS'!I88,'3 Model Projected FS'!I100)),3) -> 0.177
B24: RoE | C24: =ROUND('[2]3 Model Projected FS'!D39/AVERAGE('[2]3 Model Projected FS'!C82:D82),3) -> 0.286 | D24: =ROUND('3 Model Projected FS'!E39/AVERAGE('3 Model Projected FS'!D82:E82),3) -> 0.121 | E24: =ROUND('3 Model Projected FS'!F39/AVERAGE('3 Model Projected FS'!E82:F82),3) -> 0.165 | F24: =ROUND('3 Model Projected FS'!G39/AVERAGE('3 Model Projected FS'!F82:G82),3) -> 0.192 | G24: =ROUND('3 Model Projected FS'!H39/AVERAGE('3 Model Projected FS'!G82:H82),3) -> 0.229 | H24: =ROUND('3 Model Projected FS'!I39/AVERAGE('3 Model Projected FS'!H82:I82),3) -> 0.266
B25: Debt to Equity (x) | D25: =ROUND(SUM('3 Model Projected FS'!E88,'3 Model Projected FS'!E100)/'3 Model Projected FS'!E82,1) -> 1.1 | E25: =ROUND(SUM('3 Model Projected FS'!F88,'3 Model Projected FS'!F100)/'3 Model Projected FS'!F82,1) -> 0.9 | F25: =ROUND(SUM('3 Model Projected FS'!G88,'3 Model Projected FS'!G100)/'3 Model Projected FS'!G82,1) -> 0.7 | G25: =ROUND(SUM('3 Model Projected FS'!H88,'3 Model Projected FS'!H100)/'3 Model Projected FS'!H82,1) -> 0.9 | H25: =ROUND(SUM('3 Model Projected FS'!I88,'3 Model Projected FS'!I100)/'3 Model Projected FS'!I82,1) -> 0.8
B26: Net Debt to EBITDA (x) | D26: =ROUND(('3 Model Projected FS'!E88+'3 Model Projected FS'!E100-'3 Model Projected FS'!E67-'3 Model Projected FS'!E68)/D5,1) -> 4.2 | E26: =ROUND(('3 Model Projected FS'!F88+'3 Model Projected FS'!F100-'3 Model Projected FS'!F67-'3 Model Projected FS'!F68)/E5,1) -> 2.5 | F26: =ROUND(('3 Model Projected FS'!G88+'3 Model Projected FS'!G100-'3 Model Projected FS'!G67-'3 Model Projected FS'!G68)/F5,1) -> 2.2 | G26: =ROUND(('3 Model Projected FS'!H88+'3 Model Projected FS'!H100-'3 Model Projected FS'!H67-'3 Model Projected FS'!H68)/G5,1) -> 1.6 | H26: =ROUND(('3 Model Projected FS'!I88+'3 Model Projected FS'!I100-'3 Model Projected FS'!I67-'3 Model Projected FS'!I68)/H5,1) -> 1.2
B27: Valuation Ratios
B28: P/E (x) | D28: =ROUND(Scenarios!H391/Scenarios!H395,1) -> 25.7 | E28: =ROUND(Scenarios!I391/Scenarios!I395,1) -> 36.6 | F28: =ROUND(Scenarios!J391/Scenarios!J395,1) -> 22.9 | G28: =ROUND(Scenarios!K391/Scenarios!K395,1) -> 26.9 | H28: =ROUND(Scenarios!L391/Scenarios!L395,1) -> 26.9
B29: P/B (x) | D29: =ROUND(Scenarios!H391/Scenarios!H394,1) -> 3 | E29: =ROUND(Scenarios!I391/Scenarios!I394,1) -> 5.6 | F29: =ROUND(Scenarios!J391/Scenarios!J394,1) -> 4.1 | G29: =ROUND(Scenarios!K391/Scenarios!K394,1) -> 6.3 | H29: =ROUND(Scenarios!L391/Scenarios!L394,1) -> 6.4
B30: Enterprise Ratios
B31: EV/EBITDA (x) | D31: =ROUND(Scenarios!H401/'3 Model Projected FS'!E19,1) -> 16.6 | E31: =ROUND(Scenarios!I401/'3 Model Projected FS'!F19,1) -> 21.3 | F31: =ROUND(Scenarios!J401/'3 Model Projected FS'!G19,1) -> 16.1 | G31: =ROUND(Scenarios!K401/'3 Model Projected FS'!H19,1) -> 18.3 | H31: =ROUND(Scenarios!L401/'3 Model Projected FS'!I19,1) -> 18.5
B32: EV/Sales (x) | D32: =ROUND(Scenarios!H401/'3 Model Projected FS'!E9,1) -> 8.7 | E32: =ROUND(Scenarios!I401/'3 Model Projected FS'!F9,1) -> 12.6 | F32: =ROUND(Scenarios!J401/'3 Model Projected FS'!G9,1) -> 9.6 | G32: =ROUND(Scenarios!K401/'3 Model Projected FS'!H9,1) -> 11 | H32: =ROUND(Scenarios!L401/'3 Model Projected FS'!I9,1) -> 11.1
B33: Dividend Ratios
B34: Dividend Payout | D34: =ROUND(Scenarios!H393/'3 Model Projected FS'!E39,3) -> 0.203 | E34: =ROUND(Scenarios!I393/'3 Model Projected FS'!F39,3) -> 0.16 | F34: =ROUND(Scenarios!J393/'3 Model Projected FS'!G39,3) -> 0.14 | G34: =ROUND(Scenarios!K393/'3 Model Projected FS'!H39,3) -> 0.15 | H34: =ROUND(Scenarios!L393/'3 Model Projected FS'!I39,3) -> 0.155
B35: Dividend Yield | D35: =ROUND(Scenarios!H396/Scenarios!H391,4) -> 0.0079 | E35: =ROUND(Scenarios!I396/Scenarios!I391,4) -> 0.0044 | F35: =ROUND(Scenarios!J396/Scenarios!J391,4) -> 0.0061 | G35: =ROUND(Scenarios!K396/Scenarios!K391,4) -> 0.0056 | H35: =ROUND(Scenarios!L396/Scenarios!L391,4) -> 0.0057

Sheet Peer Comparison
A1: Peer Comparison | K1: =Scenarios!L1 -> Currently Running: Base Case Scenario
B3: Particulars | D3: Adani Ports and SEZ | G3: JSW Infrastructure | J3: DP World
B4: Operational Metrics
B5: Operational Port Capacity | D5: 784 MMT | G5: 177 MMT | J5: Over 102 million TEUs (~1,120 MMT)
B6: Revenue by Segment (H1FY26 and H1 2025 for DP World)) | D6: Domestic Ports: 68.3% | International Ports: 11.2% | Logistics: 12.2% | Marine: 6.5% | Port Development & SEZ: 1.6% | G6: Ports: 52.4% | Logistics: 16.1% | J6: Ports and Terminals: 38.8% | Logistics, Parks and Economic Zones: 41.9% | Marine Services: 19.3%
B7: EBITDA Margins by Segment | D7: Domestic Ports: 74.2% | International Ports: 22.7% | Logistics: 19.4% | Marine: 52.7% | Port Development & SEZ: 100% | G7: Ports: % | Logistics: 12.1% | J7: Ports and Terminals: 51.7% | Logistics, Parks and Economic Zones: 13.6% | Marine Services: 23.1%
B8: Capex Guidance | D8: 65,000-75,000 Cr from FY25-FY29 | G8: 9,000 Cr from FY25-FY30 | J8: 22,000 Cr capital expenditure for 2025, of which 9,600 Cr was invested in H1FY25
B10: Financial Metrics | C10: FY23 | D10: FY24 | E10: FY25 | F10: =C10 -> FY23 | G10: =D10 -> FY24 | H10: =E10 -> FY25 | I10: 2022 | J10: 2023 | K10: 2024
B11: Revenue (₹'cr) | C11: ='Consol. Historical FS'!E9 -> 20851.91 | D11: ='Consol. Historical FS'!F9 -> 26710.56 | E11: ='Consol. Historical FS'!G9 -> 30475.33 | F11: 3195 | G11: 3763 | H11: 4476 | I11: 152412 | J11: 162429 | K11: 178206
B12: Revenue Growth | D12: =D11/C11-1 -> 0.28096467 | E12: =E11/D11-1 -> 0.14094688 | G12: =G11/F11-1 -> 0.17777778 | H12: =H11/G11-1 -> 0.18947648 | J12: =J11/I11-1 -> 0.065723171 | K12: =K11/J11-1 -> 0.09713167 | M12: =L12*89*1000/10000000 -> 0
B14: Gross Profit (₹'cr) | C14: ='Consol. Historical FS'!E13 -> 15197.35 | D14: ='Consol. Historical FS'!F13 -> 19594.22 | E14: ='Consol. Historical FS'!G13 -> 22405.58 | F14: =F11*0.6223 -> 1988.2485 | G14: =G11*0.6389 -> 2404.1807 | H14: =H11*0.6105 -> 2732.598 | I14: 45728 | J14: 48396 | K14: 53540
B15: Gross Profit Growth | D15: =D14/C14-1 -> 0.2893182 | E15: =E14/D14-1 -> 0.14347905 | G15: =G14/F14-1 -> 0.20919528 | H15: =H14/G14-1 -> 0.13660259 | J15: =J14/I14-1 -> 0.058344997 | K15: =K14/J14-1 -> 0.10628978
B17: EBITDA (₹'cr) | C17: ='Consol. Historical FS'!E17 -> 10947.13 | D17: ='Consol. Historical FS'!F17 -> 15751.1 | E17: ='Consol. Historical FS'!G17 -> 18140.52 | F17: 1623 | G17: 1968 | H17: 2262 | I17: 42457 | J17: 43891 | K17: 46903
B18: EBITDA Growth | D18: =D17/C17-1 -> 0.43883374 | E18: =E17/D17-1 -> 0.15169861 | G18: =G17/F17-1 -> 0.21256932 | H18: =H17/G17-1 -> 0.14939024 | J18: =J17/I17-1 -> 0.033775349 | K18: =K17/J17-1 -> 0.068624547
B20: Net Profit (₹'cr) | C20: ='Consol. Historical FS'!E34 -> 5392.75 | D20: ='Consol. Historical FS'!F34 -> 8103.99 | E20: ='Consol. Historical FS'!G34 -> 11061.26 | F20: 750 | G20: 1161 | H20: 1521 | I20: 14488 | J20: 11559 | K20: 11633
B21: Net Profit Growth | D21: =D20/C20-1 -> 0.50275648 | E21: =E20/D20-1 -> 0.36491531 | G21: =G20/F20-1 -> 0.548 | H21: =H20/G20-1 -> 0.31007752 | J21: =J20/I20-1 -> -0.20216731 | K21: =K20/J20-1 -> 0.0064019379
B23: Ratios
B24: Gross Profit Margin | C24: =ROUND(C14/C11,3) -> 0.729 | D24: =ROUND(D14/D11,3) -> 0.734 | E24: =ROUND(E14/E11,3) -> 0.735 | F24: =ROUND(F14/F11,3) -> 0.622 | G24: =ROUND(G14/G11,3) -> 0.639 | H24: =ROUND(H14/H11,3) -> 0.611 | I24: =ROUND(I14/I11,3) -> 0.3 | J24: =ROUND(J14/J11,3) -> 0.298 | K24: =ROUND(K14/K11,3) -> 0.3
B25: EBITDA Margin | C25: =ROUND(C17/C11,3) -> 0.525 | D25: =ROUND(D17/D11,3) -> 0.59 | E25: =ROUND(E17/E11,3) -> 0.595 | F25: =ROUND(F17/F11,3) -> 0.508 | G25: =ROUND(G17/G11,3) -> 0.523 | H25: =ROUND(H17/H11,3) -> 0.505 | I25: =ROUND(I17/I11,3) -> 0.279 | J25: =ROUND(J17/J11,3) -> 0.27 | K25: =ROUND(K17/K11,3) -> 0.263
B26: Net Profit Margin | C26: =ROUND(C20/C11,3) -> 0.259 | D26: =ROUND(D20/D11,3) -> 0.303 | E26: =ROUND(E20/E11,3) -> 0.363 | F26: =ROUND(F20/F11,3) -> 0.235 | G26: =ROUND(G20/G11,3) -> 0.309 | H26: =ROUND(H20/H11,3) -> 0.34 | I26: =ROUND(I20/I11,3) -> 0.095 | J26: =ROUND(J20/J11,3) -> 0.071 | K26: =ROUND(K20/K11,3) -> 0.065
B27: RoCE | C27: =Graphs!D23 -> 0.082 | D27: =Graphs!E23 -> 0.12 | E27: =Graphs!F23 -> 0.13 | F27: 0.1678 | G27: 0.1407 | H27: 0.1419 | I27: =2790479/(46982395-9348683) -> 0.074148386 | J27: =2870308/(44736097-7393648) -> 0.076864482 | K27: =3176292/(49671718-8023182) -> 0.076264193
B28: RoE | C28: =Graphs!D24 -> 0.121 | D28: =Graphs!E24 -> 0.165 | E28: =Graphs!F24 -> 0.192 | F28: 0.1852 | G28: 0.144 | H28: 0.155 | I28: =1627860/19040092 -> 0.085496436 | J28: =1298726/12325684 -> 0.10536746 | K28: =1307036/13450539 -> 0.097173504
B30: Total Debt (₹'cr) | C30: =ROUND(SUM('Consol. Historical FS'!E85,'Consol. Historical FS'!E97),2) -> 49819.31 | D30: =ROUND(SUM('Consol. Historical FS'!F85,'Consol. Historical FS'!F97),2) -> 46279.23 | E30: =ROUND(SUM('Consol. Historical FS'!G85,'Consol. Historical FS'!G97),2) -> 45810.03 | F30: 4568 | G30: 4758 | H30: 5042 | I30: 126670 | J30: 165178 | K30: 173288
B31: Total Equity (₹'cr) | C31: ='Consol. Historical FS'!E79 -> 45583.58 | D31: ='Consol. Historical FS'!F79 -> 52944.77 | E31: ='Consol. Historical FS'!G79 -> 62435.39 | F31: 3995 | G31: 8026 | H31: 9697 | I31: 169457 | J31: 109699 | K31: 119710
B32: Cash & Cash Equi. (₹'cr) | C32: =ROUND(SUM('Consol. Historical FS'!E64:E65),2) -> 4248.78 | D32: =ROUND(SUM('Consol. Historical FS'!F64:F65),2) -> 7631.88 | E32: =ROUND(SUM('Consol. Historical FS'!G64:G65),2) -> 6605.97 | F32: 1632 | G32: 4090 | H32: 2482 | I32: 30632 | J32: 29744 | K32: 40510
B33: Net Debt to Equity (x) | C33: =ROUND((C30-C32)/C31,1) -> 1 | D33: =ROUND((D30-D32)/D31,1) -> 0.7 | E33: =ROUND((E30-E32)/E31,1) -> 0.6 | F33: =ROUND((F30-F32)/F31,1) -> 0.7 | G33: =ROUND((G30-G32)/G31,1) -> 0.1 | H33: =ROUND((H30-H32)/H31,1) -> 0.3 | I33: =ROUND((I30-I32)/I31,1) -> 0.6 | J33: =ROUND((J30-J32)/J31,1) -> 1.2 | K33: =ROUND((K30-K32)/K31,1) -> 1.1
B34: 3-year Cumulative FCFF (₹'cr) | C34: 24790 | F34: 1719 | I34: 76442
B36: Valuation Metrics
B37: H1FY25 P/E (x) | D37: =ROUND(D41/11972,1) -> 29.4 | G37: =ROUND(G41/1610,1) -> 41.1 | I37: =ROUND(I41/K20,1) -> #VALUE!
B38: HFY25 P/B (x) | D38: =ROUND(D41/69707,1) -> 5.1 | G38: =ROUND(G41/10204,1) -> 6.5 | I38: =ROUND(I41/K31,1) -> #VALUE!
B39: H1FY25 EV/EBIDTA (x) | D39: =ROUND((D41+47102)/20643,1) -> 19.3 | G39: =ROUND((G41+4213)/2418,1) -> 29.1 | I39: =ROUND((I41+K30-K32)/K17,1) -> #VALUE!
B40: H1FY25 EV/Sales (x) | D40: =ROUND((D41+47102)/34746,1) -> 11.5 | G40: =ROUND((G41+4213)/4954,1) -> 14.2 | I40: =ROUND((I41+K30-K32)/K11,1) -> #VALUE!
B41: H1FY25 Market Cap (₹'cr) | D41: 352188 | G41: 66202.5 | I41: n.a.
B43: Holdings | C43: Mar'23 | D43: Mar'24 | E43: Mar'25 | F43: =C43 -> Mar'23 | G43: =D43 -> Mar'24 | H43: =E43 -> Mar'25 | I43: =F43 -> Mar'23 | J43: =G43 -> Mar'24 | K43: =H43 -> Mar'25
B44: Promoters | C44: 0.4621 | D44: 0.4511 | E44: 0.4411 | F44: 0.3116 | G44: 0.2944 | H44: 0.2831 | I44: 0.6753 | J44: 0.6753 | K44: 0.6753
B45: Shares Pledged | C45: 0.0003 | D45: 0.0001 | E45: 0.0001 | F45: 0 | G45: 0 | H45: 0 | I45: 0 | J45: 0 | K45: 0
B46: FIIs | C46: 0.2892 | D46: 0.2833 | E46: 0.2693 | F46: 0.2571 | G46: 0.3069 | H46: 0.3178 | I46: 0.0166 | J46: 0.0334 | K46: 0.0275
N48: Particulars | O48: Adani Ports and SEZ | P48: JSW Infrastructure | Q48: DP World
N49: Operational Metrics
N50: Operational Port Capacity | O50: 784 MMT | P50: 177 MMT | Q50: Over 102 million TEUs (~1,120 MMT)
N51: Revenue by Segment (H1FY26 and H1 2025 for DP World) | O51: Domestic Ports: 68.3% | International Ports: 11.2% | Logistics: 12.2% | Marine: 6.5% | Port Development & SEZ: 1.6% | P51: Ports: 52.4% | Logistics: 16.1% | Q51: Ports and Terminals: 38.8% | Logistics, Parks and Economic Zones: 41.9% | Marine Services: 19.3%
N52: EBITDA Margins by Segment | O52: Domestic Ports: 74.2% | International Ports: 22.7% | Logistics: 19.4% | Marine: 52.7% | Port Development & SEZ: 100% | P52: Ports: % | Logistics: 12.1% | Q52: Ports and Terminals: 51.7% | Logistics, Parks and Economic Zones: 13.6% | Marine Services: 23.1%
N53: Capex Guidance | O53: 65,000-75,000 Cr from FY25-FY29 | P53: 9,000 Cr from FY25-FY30 | Q53: 22,000 Cr capital expenditure for 2025, of which 9,600 Cr was invested in H1FY25

Sheet Shareholding Pattern
B2: SHAREHOLDING PATTERN
B3: Particulars | C3: FY21 | D3: FY22 | E3: FY23 | F3: FY24 | G3: FY25 | H3: Jun'25
B4: Promoters | C4: 0.6374 | D4: 0.6555 | E4: 0.6103 | F4: 0.6589 | G4: 0.6589 | H4: 0.6589
B5: Gautambhai Shantilal Adani & Rajeshbhai Shantilal Adani (on behalf of S.B. Adani Family Trust) | C5: 0.3934 | D5: 0.3784 | E5: 0.329 | F5: 0.329 | G5: 0.329 | H5: 0.329
B6: Adani Tradeline Private Limited | C6: 0 | D6: 0 | E6: 0.0447 | F6: 0.0638 | G6: 0.064 | H6: 0.064
B7: Flourishing Trade and Investment Ltd | C7: 0.0511 | D7: 0.0542 | E7: 0.0576 | F7: 0.0576 | G7: 0.0576 | H7: 0.0576
B8: Emerging Market Investment DMCC | C8: 0.0414 | D8: 0.0399 | E8: 0.039 | F8: 0.0631 | G8: 0.0631 | H8: 0.0631
B9: Adani Tradeline Llp | C9: 0.068 | D9: 0.0654 | E9: 0.0193 | F9: 0.0001 | G9: 0 | H9: 0
B10: Afro Asia Trade And Investments Limited | C10: 0.0443 | D10: 0.0426 | E10: 0.0416 | F10: 0.0416 | G10: 0.0416 | H10: 0.0416
B11: Worldwide Emerging Market Holding Limited | C11: 0.0383 | D11: 0.0408 | E11: 0.0399 | F11: 0.0399 | G11: 0.0399 | H11: 0.0399
B12: Adani Rail Infra Private Limited | C12: 0 | D12: 0.0334 | E12: 0.0327 | F12: 0.0327 | G12: 0.0327 | H12: 0.0327
B13: Resurgent Trade And Investment Ltd | C13: 0 | D13: 0 | E13: 0 | F13: 0.0245 | G13: 0.0245 | H13: 0.0245
B14: Spitze Trade And Investment Limited | C14: 0 | D14: 0 | E14: 0.0057 | F14: 0.0057 | G14: 0.0057 | H14: 0.0057
B15: Adani Properties Private Limiteed | C15: 0.0008 | D15: 0.0008 | E15: 0.0008 | F15: 0.0008 | G15: 0.0008 | H15: 0.0008
B16: Other Promoters | C16: =ROUND(C4-SUM(C5:C15),4) -> 0.0001 | D16: =ROUND(D4-SUM(D5:D15),4) -> 0 | E16: =ROUND(E4-SUM(E5:E15),4) -> 0 | F16: =ROUND(F4-SUM(F5:F15),4) -> 0.0001 | G16: =ROUND(G4-SUM(G5:G15),4) -> 0 | H16: =ROUND(H4-SUM(H5:H15),4) -> 0
B18: FIIs | C18: 0.179 | D18: 0.1426 | E18: 0.1799 | F18: 0.1498 | G18: 0.1343 | H18: 0.1361
B19: Goldman Sachs Trust Ii - Goldman Sachs Gqg Partners International Opportunities Fund | C19: 0 | D19: 0 | E19: 0.0182 | F19: 0.0266 | G19: 0.0243 | H19: =G19-0.0001 -> 0.0242
B20: Gqg Partners Emerging Markets Equity Fund | C20: 0 | D20: 0 | E20: 0 | F20: 0.0141 | G20: 0.015 | H20: 0.0107
B21: Camas Investments Pte. Ltd. | C21: 0.013 | D21: 0.0125 | E21: 0.0122 | F21: 0 | G21: 0 | H21: 0
B23: DIIs | C23: 0.1483 | D23: 0.1532 | E23: 0.1302 | F23: 0.1184 | G23: 0.1473 | H23: 0.1503
B24: Life Insurance Corporation of India | C24: 0.1077 | D24: 0.0992 | E24: 0.0912 | F24: 0.0786 | G24: 0.081 | H24: 0.0773
B25: Sbi Nifty 50 Etf | C25: 0 | D25: 0 | E25: 0 | F25: 0 | G25: 0.0181 | H25: 0.0188
B27: Government | C27: 0.0007 | D27: 0.0003 | E27: 0 | F27: 0 | G27: 0 | H27: 0
B29: Public | C29: 0.0346 | D29: 0.0484 | E29: 0.0795 | F29: 0.073 | G29: 0.0594 | H29: 0.0548
B30: Dandu Corporate Services Private Limited | C30: 0 | D30: 0 | E30: 0.0123 | F30: 0.0123 | G30: 0 | H30: 0
B32: Total | C32: =ROUND(SUM(C4,C18,C23,C27,C29),4) -> 1 | D32: =ROUND(SUM(D4,D18,D23,D27,D29),4) -> 1 | E32: =ROUND(SUM(E4,E18,E23,E27,E29),4) -> 0.9999 | F32: =ROUND(SUM(F4,F18,F23,F27,F29),4) -> 1.0001 | G32: =ROUND(SUM(G4,G18,G23,G27,G29),4) -> 0.9999 | H32: =ROUND(SUM(H4,H18,H23,H27,H29),4) -> 1.0001

Sheet Contingent Liabilities
B2: Contingent Liabilities (₹'cr) | C2: FY25 | D2: FY24
B3: a) Certain facilities availed by the joint venture entities against credit facilities sanctioned to the company. | C3: 104.35 | D3: 0.66
B4: b) Bank Guarantees given to government authorities and banks. | C4: 280.54 | D4: 340.47
B5: c) Show cause notices received from the Custom Authorities against duty on port related cargo. The Company has given deposit of ₹0.05 crore (previous year ₹0.05 crore) against the demand. The management is reasonably confident that no liability will devolve on the Company and hence no liability has been recognised in the books of accounts. | C5: 0.14 | D5: 0.14
B6: d) Various show cause notices received from Commissioner/ Additional Commissioner/ Joint Commissioner/ Deputy Commissioner of Customs and Central Excise, Rajkot and Commissioner of Service Tax, Ahmedabad and appeal there of, for wrongly availing of Cenvat credit/ Service tax credit and Education Cess credit on input services and steel, cement and other fixed assets during financial year 2006-07 to 2016-17. In similar matter, the Excise department has demanded recovery of the duty along with penalty and interest thereon. The Company has given deposit of ₹4.50 crore (previous Year ₹4.50 crore) against the demand. These matters are pending before the Supreme Court, the High Court of Gujarat, Commissioner of Central Excise (Appeals), Rajkot and Commissioner of Service Tax, Ahmedabad. The Company has taken an external opinion in the matter based on which the management is of the view that no liability shall arise on the Company. Further, during the earlier year, the Company has received favourable order from High Court of Gujarat against demand in respect of dispute relating to financial year 2005-06 and favourable order from CESTAT against similar demand in respect of dispute relating to FY 2005- 06 to FY 2010 -11 (up to Sept 2011). | C6: 32.63 | D6: 32.63
B7: e) Show cause notices received from Commissioner of Customs and Central Excise, Rajkot and appeal thereof in respect of levy of service tax on various services provided by the Company and wrong availment of CENVAT credit by the Company during financial year 2009-10 to 2011-12. These matters are currently pending at High Court of Gujarat ₹6.72 crore (previous Year ₹6.72 crore) and Customs, Excise and Service Tax Appellate Tribunal, Ahmedabad ₹0.15 crore (previous Year ₹0.15 crore) and Commissioner of Service Tax Ahmedabad ₹0.03 crore (previous Year ₹0.03 crore). The Company has taken an external opinion in the matter based on which the management is of the view that no liability shall arise on the Company. | C7: 6.9 | D7: 6.9
B8: f) In terms of the Show Cause Notice issued to a subsidiary company by the Office of the Commissioner of Customs for a demand of ` 18.33 crore along with applicable interest and penalty thereon for the differential amount of Customs Duty in respect of import of Bombardier Challenger CL-600 under Non-Scheduled Operation Permit (NSOP) has been raised on the subsidiary company. The management is reasonably confident that no liability will devolve and the same has been considered as remote liability. | C8: - | D8: 18.33
B9: g) In terms of the Show Cause cum Demand Notice issued to subsidiary company by the Office of the Commissioner of Customs Preventive Section dated 27/02/2009, a demand of ₹14.67 crore along with applicable interest and penalty thereon for the differential amount of Customs Duty in respect of import of Aircraft Hawker 850 XP under Non-Scheduled Operation Permit (NSOP) has been raised on the subsidiary company. Currently the matter is pending with Gujarat High Court for hearing. The management is reasonably confident that no liability will devolve and the same has been considered as remote liability. | C9: - | D9: 14.53
B10: h) Various matters pending relating to Service Tax, Customs and Goods and Service Tax (including Cess). The management is of the view that no liability shall arise on the subsidiaries companies. | C10: 187.47 | D10: 61.99
B11: i) Various matters of subsidiary companies pending with Income Tax Authorities. | C11: 12.81 | D11: 4.99
B12: j) (i) Claims not acknowledged as debts by Indian Subsidiaries :-
B13: - Other claims | C13: 1.15 | D13: 1.14
B14: (ii) Claims not acknowledged as debts by Foreign Subsidiaries :-
B15: - Claims pertaining to cargo damage, third party damage, longshoreman damage and other accidents | C15: 98.63 | D15: 75.92
B16: - Liabilities against lawsuits, monetary claims and tax | C16: 171.63 | D16: 202.36
B17: - Various Guarantees | C17: 69.53 | D17: 73.67
B18: k) The Company’s tax assessments is completed till Assessment year 2022-23, Appeals are pending with High Court/Supreme Court for Assessment Year 2008-09 to AY 2016-17, with CIT for AY 2017-18 to AY 2021-22. Company has received favourable orders on most of the matters for AY 2008-09 to AY 2021-22 from CIT(A)/ITAT/High Court, hence the management is reasonably confident that no liability will devolve on the Company. Company has considered it as remote liability. | C18: 0 | D18: 0
B19: l) Matters of acquired subsidiaries for which indemnity is available from previous owner/seller :-
B20: (i) Matters pending with Central Warehousing Corporation | C20: 10.14 | D20: 10.14
B21: (ii) Matters pending with Income Tax, Service Tax and Various other authorities | C21: 473.76 | D21: 473.76
B22: m) During the financial year 2020-21, the group has received notice from one of the port trust authority, relating to royalty on deemed storage income for ₹41.40 crore. The Group has applied for extending the relief of rationalised tariff retrospectively, available under guidelines issued by Ministry of Shipping dated July 11, 2018. The Group has paid an amount of ₹18.67 crore and provided the same in books on prudent basis and doesn’t anticipate any further outflow. | C22: 0 | D22: 0
B23: Total | C23: =SUM(C3:C22) -> 1449.68 | D23: =SUM(D3:D22) -> 1317.63
B24: % of Equity | C24: =C23/'Consol. Historical FS'!G81 -> 0.022311921 | D24: =D23/'Consol. Historical FS'!F81 -> 0.024157637

Sheet Dividend
B2: DIVIDEND POLICY
B3: Particulars | C3: FY21 | D3: FY22 | E3: FY23 | F3: FY24 | G3: FY25
B4: Dividend payout ratio (%) | C4: =ROUND(Scenarios!F393/'3 Model Projected FS'!C39,3) -> 0.202 | D4: =ROUND(Scenarios!G393/'3 Model Projected FS'!D39,3) -> 0.223 | E4: =ROUND(Scenarios!H393/'3 Model Projected FS'!E39,3) -> 0.203 | F4: =ROUND(Scenarios!I393/'3 Model Projected FS'!F39,3) -> 0.16 | G4: =ROUND(Scenarios!J393/'3 Model Projected FS'!G39,3) -> 0.14
B5: Dividend per share (₹) | C5: =Scenarios!F396 -> 4.97 | D5: =Scenarios!G396 -> 5.16 | E5: =Scenarios!H396 -> 4.99 | F5: =Scenarios!I396 -> 6 | G5: =Scenarios!J396 -> 7.17
B6: Dividend yield (%) | C6: =ROUND(Scenarios!F396/Scenarios!F391,4) -> 0.0068 | D6: =ROUND(Scenarios!G396/Scenarios!G391,4) -> 0.0066 | E6: =ROUND(Scenarios!H396/Scenarios!H391,4) -> 0.0079 | F6: =ROUND(Scenarios!I396/Scenarios!I391,4) -> 0.0044 | G6: =ROUND(Scenarios!J396/Scenarios!J391,4) -> 0.0061

Sheet Credit Rating
B2: Credit Rating
B3: Jul'25 | C3: ICRA AAA/Stable / A1+
B4: Jul'25 | C4: Care AAA/Stable / A1+
B5: April'25 | C5: Care AAA/Stable / A1+
B6: April'25 | C6: CRISIL AAA/Stable / A1+
B7: Sep'24 | C7: CRISIL AAA/Stable / A1+
B8: April'24 | C8: Care AAA/Stable / A1+
